Workbook
Name _1st_shift_percentage: Data!$B$60
Name _2nd_shift_percentage: Data!$B$59
Name Amazon_Replen: Data!$B$58
Name Autobagger_Bander: [1]Data!$B$28
Name Autobagger_Bander: [2]Data!$B$28
Name Autobagger_Bander: [2]Data!$B$28
Name Autobagger_Bander: Data!$B$28
Name Autobagger_Operator: [1]Data!$B$27
Name Autobagger_Operator: [2]Data!$B$27
Name Autobagger_Operator: [2]Data!$B$27
Name Autobagger_Operator: Data!$B$27
Name Average_units_per_bin: Data!$B$52
Name Cartbuilding: Data!$B$18
Name Cartons_per_hour_Cubiscan: Data!$B$38
Name Cubiscan: Data!$B$36
Name DD: #REF!
Name DTC: Data!$B$9
Name DTC_to_replen: Data!$B$35
Name Exceptions: [1]Data!$B$42
Name Exceptions: [2]Data!$B$42
Name Exceptions: [2]Data!$B$42
Name Exceptions: Data!$B$42
Name Gift_cards: Data!$B$21
Name Gift_cards_per_hour: Data!$B$26
Name Hours_1st: Data!$B$3
Name Hours_2nd: Data!$B$4
Name Inventory: Data!$B$50
Name Narvar: [1]Data!$B$41
Name Narvar: [2]Data!$B$41
Name Narvar: [2]Data!$B$41
Name Narvar: Data!$B$41
Name Open_orders: Data!$B$54
Name Overstock: [1]Data!$B$33
Name Overstock: [2]Data!$B$33
Name Overstock: [2]Data!$B$33
Name Overstock: Data!$B$33
Name Overstock_cycle_count: Data!$B$53
Name Pecentage_of_goal_2nd: Data!$B$6
Name Percentage_1st_Goal: Data!$B$43
Name Percentage_2nd_Goal: Data!$B$44
Name Percentage_Exceptions: Data!$B$47
Name Percentage_Narvar: Data!$B$45
Name Percentage_Non_Narvar: Data!$B$46
Name Percentage_of_goal_1st: Data!$B$5
Name Percentage_regular: Data!$B$14
Name Percentage_singles: Data!$B$15
Name Picking_cycle_count: Data!$B$51
Name Pieces_per_package: Data!$B$48
Name Planning: Data!$B$2
Name Receiving: [1]Data!$B$34
Name Receiving: [2]Data!$B$34
Name Receiving: [2]Data!$B$34
Name Receiving: Data!$B$34
Name Receiving_DD: #REF!
Name Region_1: Data!$B$10
Name Region_2: Data!$B$11
Name Region_7: Data!$B$12
Name Repack: Data!$B$22
Name Repack_goal: Data!$B$23
Name Replenishment_pull: [1]Data!$B$31

Sheet SOS Topics & Reminders
A1: Date Added | B1: Topic | C1: Notes | D1: Inital and Date Covered on 1st Shift | E1: Inital and Date Covered on 2nd Shift | F1: Inital and Date Covered on Wknd Shift
A2: 46086 | B2: Cell Phone Policy | C2: Issue reminder that all cell phones must be set to silent, vibrate mode or turned off during work hours, Employees are permitted to use cell phones only during designated breaks and lunch periods, and such use must occur off the warehouse floor. Use of your cell phone is strictly prohibited while operating an industrial vehicle, this is a serious safety violation. Please inform your supervisor and step off the floor if you must use your phone. | D2: 3/5/2026 - SC | E2: 03/08/2026-AG | F2: 3/6/26-sjn
A3: 45721 | B3: Weekly Production Review and Monthly TB Review | C3: Remind the team we review production weekly and conduct monthly TB with the team. Ensure they understand these metrics are being monitored and will be reviewed. | D3: 3/5/2026 - SC | E3: 03/08/2026-AG | F3: 3/6/26--sjn
A4: 46090 | B4: Counting errors | C4: Let people know that we are going to start adding cycle count errors to the rollup and will be tracking people's accuracy in counting going forward. | E4: 3/9/2026-MR | F4: 3/13/2026-sjn
A5: 46090 | B5: Vacation requests | C5: Please put in your vacation requests as early as you can. The time off calendar fills up quickly and we approve requests on a first come/first served basis. | D5: 3/10/2026 SC-CG | E5: 3/9/2026-MR | F5: 3/13/2026-sjn
A6: 45725 | B6: LMS scanning | C6: We discussed the importance of LMS and its impact on production and labor coding. | D6: 03/09/26 -SC-CG | E6: 03/15/2026 AG | F6: 3/13/2026 EP
A7: 46091 | B7: Update in PTO in Paylocity | C7: HR is working on this. We know it's not correct. We need to let the system resolve itself. Manually entering in hours is not working. | D7: 3/10/26 - CG/SC | E7: 03/15/2026 AG | F7: 46094
A8: 46091 | B8: Position Update | C8: O&T role is officially posted! If you wish to apply there is a QR code on the postings in the breakroom! | D8: 3/11/26 - CG/SC | E8: 3/15/2026 AG | F8: 3/13/2026-EP
A9: 46092 | B9: 401K Meeting | C9: Spanish Session for Monday 3/16 | D9: 3/12/26 - CG/SC | E9: 03/15/2026 AG | F9: 3/15/26 ep
A10: 46094 | B10: Food on the floor | C10: Remind folks that they can only have water on the floor. No candy, sodas, chips etc. | D10: 3/16/26 -CG | E10: 3/15/2026 AG | F10: 3/14/2026- sjn
A11: 46096 | B11: PTO request time frame | C11: All Paid Time Off (PTO) requests must be submitted before the weekly report closes for the applicable work week | E11: 03/15/2026 AG | F11: 3/15/2026 EP
A12: 46098 | B12: Coffe reminder | C12: Employees can only make ccoffee durning their break times. | D12: 03/17/2026- CG/SC | E12: 03/15/2026 AG | F12: 3/20/2026--sjn
A13: 46099 | B13: Incoming Volume and sale | C13: We discussed the upcoming incoming volume and sale, and reminded the team that there will be a PTO blackout. The team was also advised to be prepared for the increased workload. | D13: 03/18/26 CG-SC | E13: 03/18/2026 AG | F13: 3/20/2026 EP
A14: 46104 | B14: No cellphones after they clock in. | C14: Today, we communicated that team members are not permitted to use their cell phones once they are clocked in. All employees must be prepared for the SOS meeting with their phones turned off. | D14: 03/23/26 SC/CG | E14: 03/24/2026 AG | F14: 03/23/26 EP
A15: 46105 | B15: O&T Postion FINAL reminder | C15: The posting for the O&T position will be taken down tomorrow at noon. This is your final reminder to apply if you're interested! | D15: 3/25/26 - CG | E15: 03/24/2026 AG | F15: 3/27/26 EP
A16: 46111 | B16: Cell phones | C16: Reminder that cell phones left in the breakroom should please be put on silent. Please be mindful that this is shared space and sometimes people's notifications, ringtones and alarms are so loud they can be heard in offices and sometimes people are in meetings. | D16: 04/02/26 - SC | E16: 04/06/2026 ag | F16: 4/10/2026 sjn
A17: 46118 | B17: Cell phones, scanning, cherry picking | C17: Reminder that cell phones left in the breakroom should please be put on silent. Please be mindful that this is shared space, No cherry picking carts in picking, make sure to scan to the correct functions. | D17: 04/06/2026 -CG / SC | E17: 04/06/2026 ag | F17: 04/06/26 --SJ
A18: 46118 | B18: Washed but wanted Sale! | C18: We will be having a washed but wanted sale from Friday 4/10 to Thursday 4/16! We are looking for volunteers to sign up to work the sale, these people will get the first peak at the inventory for the day. Each employee will also receive $50 in Hanna Bucks to shop the sale. Please keep an eye out to sign up for the shopping slots and see your supervisor if you would like to sign up for working the sale! | D18: 04/07/2026 - CG/SC | E18: 04/07/2026 ag | F18: 4/10/26 sjn
A19: 46118 | B19: Use of chairs | C19: We found a chair in receiving at the vendor compliance station, this is a gentle reminder that the use of chairs in the warehouse in prohibited. Next time a chair is oberved it could result in disciplinary action. | D19: 04/07/2026 - CG/SC | E19: 04/07/2026 ag | F19: 4/10/26 sjn
A20: 04/072026 | B20: Housekeeping | C20: Return ladders, brooms, and dustbins to their designated aisles and rack locations. All carts and totes must also be returned to their assigned areas. Restock and clean shipping areas. | D20: 04/07/2026 - CG/SC | E20: 04/07/2026 ag | F20: 4/10/26 sjn
A21: 04/072026 | B21: DC Connect April-May | C21: The DC Connect team covered the activities for the months of April and May. | D21: 0407/2026 - MC/SA | E21: 04/07/2026 ag | F21: 4/10/26 sjn
A22: 46120 | B22: Washed but wanted | C22: We have recently found boxes of WBW where it appears someone has put their washed but wanted for the day in a box instead of sorting it down and just wrote WBW on it. This is a gentle reminder that all units must be sorted by size. The size must be written on all 4 sides of the carton. When a box is full you must seal it up and replace it. If someone is found to not be following proper proceedure they will receive corrective action. | F22: 4/10/26 sjn
A23: 46122 | B23: 401K meeting for English speakers | C23: 401K meeting for English speakers is on Monday, 4/13 at 3 pm. | D23: 04/13/26 - SJN-MC-SC | E23: 4/13/2026 ag
A24: 46122 | B24: Food in lockers | C24: The safety committee's EHS checklist modules have had noted that we have open food containers in lockers. Reminder that food left in lockers must be non-perishable and be completely sealed to avoid attracking bugs and rodents. Additionally, the same rules apply for the refridgerator, there should be no open food or drink containers. | D24: 04/13/26 - SJN-MC-SC | E24: 04/13/2026 ag | F24: 4/11/2026-sjn
A25: 46122 | B25: Friends and Family Sale | C25: The Friends and Family sale starts Tuesday April 21st and runs through Monday May 4th. We are currently working on a schedule and will release it as soon as it's complete but wanted to give everyone a head's up that there will be scheduled overtime. | D25: 04/13/26 - SJN-MC-SC | E25: 04/19/2026 ag | F25: 4/11/2026-sjn
A26: 46129 | B26: Reporting Accidents and Safety issues | C26: Remind people that they need to report Safety issues and Accidents and near misses right away. | E26: 04/19/2026 ag | F26: 4/18/26-sjn
A27: 46130 | B27: Cycle count errors being recorded | C27: Remind people that we are recording cycle count errors and these will turn up on their TB each month. | E27: 04/19/2026 ag | F27: 4/19/26-sjn
A28: 46131 | B28: Earth Day celebration on Friday | C28: Friday we will have a small celebration of Earth Day with plant give aways and snacks | E28: 04/19/2026 ag | F28: 4/19/26-sjn
A29: 46133 | B29: Safety Committee | C29: We are opening up positions on the Safety Committee and moving to an annual refresh cycle to give more team members the opportunity to participate and build valuable experience. Serving on the committee is a great way to contribute to a safer workplace, share ideas, collaborate across teams, and develop leadership and problem-solving skills. If you’re interested in joining, please speak with your supervisor to express your interest. You are able to apply if you are currently on the safety committee and would like to continue involvement. In the event that there are not enough volunteers, supervisors will select team members to ensure all areas are represented. We encourage everyone to consider getting involved and helping us continue to strengthen our safety culture | D29: 4/22/2026 - CG/SC/MC | E29: 04/19/2026 ag | F29: 4/24/26--sjn
A30: 46133 | B30: Safety Reminder | C30: Never open doors or entry gates for strangers, alert your supervisor immediately and direct anyone not currently employeed at Hanna to the reception area. Report any suspicious behavior or non-Hanna employee if seen in the parking lot. Do not let anyone "piggy back" entering the building. Safety should be priority for all associates. | D30: 4/24/26-sjn | E30: 04/26/2026 ag | F30: 4/24/26--sjn
A31: 46136 | B31: Safety Meeting | C31: There will be a safety meeting Monday 4/27 with Jackie, Vega, Rolexis, Richard and Jonat | D31: 4/27/26 -sjn | F31: 4/25/2026 EP
A32: 46136 | B32: Don't override when putting away overstock. | C32: Remind stockers not to use override when putting away overstock. We have been mistakenly putting boxes into Invalid locations. | D32: 4/27/26 -sjn | E32: 04/26/2026 ag | F32: 4/27/26--sjn
A33: 46144 | B33: Incorrect lift scans | C33: Do not use Inbound indirect scans for long periods of time. You should not be using 509 if you are pulling replenishment all day for instance. | D33: 5/11/2026 -cjg | E33: 05/17/2026 ag | F33: 5/2/2026 EP
A34: 46150 | B34: Mother's day | C34: DC will be close on 5/10/2026, to allow employee to celebrate Mother's day | D34: na | E34: na | F34: 5/8/2026-sjn
A35: 46150 | B35: Incorrect lift scans | C35: Reminder. Do not use Inbound indirect scans for long periods of time. You should not be using 509 if you are pulling replenishment all day for instance. | D35: 5/11/2026 -cjg | E35: 05/11/2026 AG | F35: 5/9/2026-sjn
A36: 46151 | B36: Empty boxes not empty | C36: When pulling empty boxes from picking, make sure the box is really empty. | D36: 5/11/2026 -cjg | E36: 05/11/2026 AG | F36: 5/9/2026-sjn
A37: 46153 | B37: Safety Reminder | C37: With it starting to get warmer, please remember to drink plenty of water! With this, please make sure it's in a plastic or metal sealable/spill proof bottle. A bottle that does not have a closable lid can lead to spills that can cause a slip and fall, glass bottles can fall and bust which lead to slip and fall as well as pose a cut risk | E37: 05/17/2026 ag | F37: 5/15/26-EP
A38: 46153 | B38: Memorial Day Sale | C38: Please let everyone know that the Memorial Day Sale starts this Thursday 5/14, please prepare for working scheduled overtime next week! | D38: 05/13 - SC-CG-MC | E38: 05/17/2026 ag | F38: 5/15/26-EP
A39: 46155 | B39: Safety Reminder | C39: Reminder for anyone driving industrial vehicles, you are responsible for reporting any observed vehicle issues or safety concerns to your supervisor immediately upon discovery. Do not continue operating a vehicle with an issue, no matter how small or insignificant you think it is. Safety comes first, we would much rather lock and tag out a vehicle, have it inspected and cleared by maintenance than someone get hurt or be involved in an accident. | D39: 05/14/2026- SC-DG-MC | E39: 05/17/2026 ag | F39: 5/15/26-EP
A40: 46155 | B40: Memorial Day Schedule | C40: Pay attention to posting in breakroom! | D40: 05/14/2026- SC-DG-MC | E40: 05/17/2026 ag | F40: 5/15/26-EP
A41: 46157 | B41: Safety Reminder | C41: Reminder: For safety reasons, smoking and vaping are not allowed inside the building. Smoking is only permitted in the designated smoking room and during break times. | D41: 5/18/2026 - SC/CG | E41: 05/17/2026 ag | F41: 5/15/26-EP
A42: 46161 | B42: Picking Reminder | C42: Using the check digit on the outside of the cartons is strictly prohibited, this is causing a lot of order errors. Moving forward, if your receive an error, your incentive will be declined and we will begin the corrective action process. | D42: 05/20 - SCCG-MC | E42: 05/19/2026 AG | F42: 5/23/2026-EP
A43: 46161 | B43: Process change for stocking team! | C43: Please pull your stockers (see email for pictures) we would like to begin placing the pull sticker over the ASN label. Do not cover the LP barcode or 20 digit number but instead place it over the SKU information as show in the picture. We would also like you to begin marking out the UPC IF there is a UPC sticker on the outside of the box. | D43: 05/20 - SCCG-MC | E43: 05/19/2026 ag | F43: 5/23/2026-EP
A44: 46167 | B44: Tampering with Thermostat | C44: Setting thermostats too low will cause leaks and AC unit coils to freeze. Lets make sure we aren't setting the temperature below 70. It will only make the DC hotter if we break the units. | D44: 5/25 - CG | E44: 05/27/2026 AG | F44: 5/29/26--sjn
A45: 46167 | B45: Charger #5 | C45: Charger 5 is configured for the sit down. It has a different voltage and Cell count than the Order Pickers. Make sure Charger 5 is only being used on the sit-down forklift (SD5). | D45: 5/25 - CG | E45: 05/27/2026 AG | F45: 5/29/26--sjn
A46: 46170 | B46: Safety Reminder | C46: We have found 2 fire extinguishers that show evidence of hit damage. Reminder that hitting or damaging these must be reported as they will need to be inspected and returned to service. Damage to the extinguishers can pose a safety risk. Please make sure you are watching out for these when moving through the warehouse. This should be viewed the same as any other accident, failure to report can result in separation of employment. | D46: 5/29/26--sjn | E46: 06/01/2026 ag | F46: 5/29/26--sjn
A47: 46173 | B47: Returns reminder | C47: If you have returns pieces that you can't put away because of a problem with the location or the work id, don't put these pieces into the red/blue bins. Take them back to the returns sort area and put them into the marked totes so the Inventory Leads can take care of them. You can also take them to the Lead or a supervisor on your shift. | D47: 06/03/26 CG-SC-MC | E47: 06/02/2026 ag | F47: 6/1/2026-sjn
A48: 46174 | B48: Returns reminder | C48: Reminder for those processing returns that socks and underwear do not get repackaged. For underwear, if the bag has been opened, due to not knowing whether these have been tried on or not it is unsanitary to process these as first quality. Repackaging this will result in a processing error and any earned incentive being declined. If issues continue it will result in disciplinary actions. | D48: 06/03/26 CG-SC-MC | E48: 06/02/2026 ag | F48: 6/5/26-sjn
A49: 46175 | B49: Safety Reminder | C49: As a reminder all Incidents must be reported the same day to a supervisor or manager if not reported employee will be terminated | D49: 06/03/26 CG-SC-MC | E49: 06/02/2026 ag | F49: 6/5/26-sjn
A50: 46175 | B50: Housekeeping/ Stockers | C50: Please talk to your stocking teams and let them know that they must remove the empty cartons, they can place them at the end of the aisle or even take them straight to the compactor area. If we start to see this area full of empty cartons again we will look at the cameras, see who is doing it and it will result in disciplinary action. | D50: 06/03/26 CG-SC-MC | E50: 06/03/2026 AG | F50: 6/5/26-sjn

Sheet Sheet1
A1: DC Links
A2: Outbound | B2: Inbound | C2: Supervisor Links | D2: Training/Crosstraining | E2: Test Password
A3: Outbound WIP | B3: Inbound Dashboard | C3: FC_Rollup | D3: Advanced Stocking Functions | E3: hannast
A4: Voice Console | B4: Receiving Dashboard | C4: IT Ticket Entry | D4: Advanced Stocking Functions - SP | E4: hannast
A5: Voicelink | D5: Throw Assessment | E5: hannas1
D6: Throw Assessment - SP | E6: hannat
D7: Picking Region 1 | E7: hannap
D8: Picking Region 1 - SP | E8: hannap

Sheet Monday Deployment
B1: {=IFERROR(_xlfn.IFS(E5=0,"",E5>0,E5),"")} -> Maria Carrasco | C1: {=IFERROR(_xlfn.IFS(F5=0,"",F5>0,F5),"")} -> SL | E1: Monday SHIFT DEPLOYMENT | O1: 1st shift | U1: =TODAY() -> 46189 | Z1: Outbound | AA1: Cart Building | AB1: AB Super User | AC1: AB Bander | AE1: Shipping | AF1: Taper | AG1: Special Projects | AH1: Training | AI1: ="Picking"&" "&COUNTA(AI2:AI38)-COUNTBLANK(AI2:AI38) -> Picking 1 | AJ1: ="Picking"&" "&COUNTA(AJ2:AJ38)-COUNTBLANK(AJ2:AJ38) -> Picking 0
B2: {=IFERROR(_xlfn.IFS(E6=0,"",E6>0,E6),"")} -> Brandee Foster- IL | C2: {=IFERROR(_xlfn.IFS(F6=0,"",F6>0,F6),"")} -> i | O2: Key | P2: Function | Q2: =TODAY() -> 46189 | R2: Work | S2: GM Plan | AA2: {=IFERROR(INDEX($B$1:$B$272,SMALL(IF($O$3=$C$1:$C$272,ROW($C$1:$C$272)-MIN(ROW($B$1:$B$272))+1,""), ROW()-1)),"")} | AB2: {=IFERROR(INDEX($B$1:$B$272,SMALL(IF($O$10=$C$1:$C$272,ROW($C$1:$C$272)-MIN(ROW($B$1:$B$272))+1,""), ROW()-1)),"")} | AC2: {=IFERROR(INDEX($B$1:$B$272,SMALL(IF($O$9=$C$1:$C$272,ROW($C$1:$C$272)-MIN(ROW($B$1:$B$272))+1,""), ROW()-1)),"")} | AE2: {=IFERROR(INDEX($B$1:$B$272,SMALL(IF($O$6=$C$1:$C$272,ROW($C$1:$C$272)-MIN(ROW($B$1:$B$272))+1,""), ROW()-1)),"")} | AF2: {=IFERROR(INDEX($B$1:$B$272,SMALL(IF($O$8=$C$1:$C$272,ROW($C$1:$C$272)-MIN(ROW($B$1:$B$272))+1,""), ROW()-1)),"")} | AG2: {=IFERROR(INDEX($B$1:$B$272,SMALL(IF($O$31=$C$1:$C$272,ROW($C$1:$C$272)-MIN(ROW($B$1:$B$272))+1,""), ROW()-1)),"")} | AH2: {=IFERROR(INDEX($B$1:$B$272,SMALL(IF($O$21=$C$1:$C$272,ROW($C$1:$C$272)-MIN(ROW($B$1:$B$272))+1,""), ROW()-1)),"")} | AI2: {=IFERROR(INDEX($B$1:$B$31,SMALL(IF($O$4=$C$1:$C$31,ROW($C$1:$C$31)-MIN(ROW($B$1:$B$31))+1,""), ROW()-1)),"")} -> Dania Curbelo | AJ2: {=IFERROR(INDEX($B$32:$B$646,SMALL(IF($O$4=$C$32:$C$646,ROW($C$32:$C$646)-MIN(ROW($B$32:$B$646))+1,""), ROW()-1)),"")} | AL2: Bander
B3: {=IFERROR(_xlfn.IFS(E7=0,"",E7>0,E7),"")} -> Ailin Reynaldo | C3: {=IFERROR(_xlfn.IFS(F7=0,"",F7>0,F7),"")} -> I | E3: Hanna employees | J3: GIG employees | O3: CB | P3: Cartbuilding | Q3: =COUNTIFS($F$5:$F$33,O3)+COUNTIFS($I$5:$I$33,O3) -> 0 | R3: =V7 -> 3677 | S3: =LOOKUP(U1,'Deployment needs'!$2:$2,'Deployment needs'!58:58) -> 0.4837963 | U3: DC Daily Goal | V3: =LOOKUP(U1,'Deployment needs'!2:2,'Deployment needs'!5:5) -> 13000 | AA3: {=IFERROR(INDEX($B$1:$B$272,SMALL(IF($O$3=$C$1:$C$272,ROW($C$1:$C$272)-MIN(ROW($B$1:$B$272))+1,""), ROW()-1)),"")} | AB3: {=IFERROR(INDEX($B$1:$B$272,SMALL(IF($O$10=$C$1:$C$272,ROW($C$1:$C$272)-MIN(ROW($B$1:$B$272))+1,""), ROW()-1)),"")} | AC3: {=IFERROR(INDEX($B$1:$B$272,SMALL(IF($O$9=$C$1:$C$272,ROW($C$1:$C$272)-MIN(ROW($B$1:$B$272))+1,""), ROW()-1)),"")} | AE3: {=IFERROR(INDEX($B$1:$B$272,SMALL(IF($O$6=$C$1:$C$272,ROW($C$1:$C$272)-MIN(ROW($B$1:$B$272))+1,""), ROW()-1)),"")} | AF3: {=IFERROR(INDEX($B$1:$B$272,SMALL(IF($O$8=$C$1:$C$272,ROW($C$1:$C$272)-MIN(ROW($B$1:$B$272))+1,""), ROW()-1)),"")} | AG3: {=IFERROR(INDEX($B$1:$B$272,SMALL(IF($O$31=$C$1:$C$272,ROW($C$1:$C$272)-MIN(ROW($B$1:$B$272))+1,""), ROW()-1)),"")} | AH3: {=IFERROR(INDEX($B$1:$B$272,SMALL(IF($O$21=$C$1:$C$272,ROW($C$1:$C$272)-MIN(ROW($B$1:$B$272))+1,""), ROW()-1)),"")} | AI3: {=IFERROR(INDEX($B$1:$B$31,SMALL(IF($O$4=$C$1:$C$31,ROW($C$1:$C$31)-MIN(ROW($B$1:$B$31))+1,""), ROW()-1)),"")} -> Hector Rocha | AJ3: {=IFERROR(INDEX($B$32:$B$646,SMALL(IF($O$4=$C$32:$C$646,ROW($C$32:$C$646)-MIN(ROW($B$32:$B$646))+1,""), ROW()-1)),"")} | AL3: Groups | AM3: Sunday | AN3: Monday | AO3: Tuesday | AP3: Wednesday | AQ3: Thursday | AR3: Friday | AS3: Saturday
B4: {=IFERROR(_xlfn.IFS(E8=0,"",E8>0,E8),"")} -> Chrissy Parisek | C4: {=IFERROR(_xlfn.IFS(F8=0,"",F8>0,F8),"")} -> x | E4: 1st SHIFT DEPLOYMENT | F4: area | G4: Weekend Deployment | I4: area | J4: Names | L4: area | O4: P | P4: Picking- Bulk | Q4: =COUNTIFS($F$5:$F$33,O4)+COUNTIFS($I$5:$I$33,O4) -> 0 | R4: =V9 -> 2718 | S4: =LOOKUP(U1,'Deployment needs'!$2:$2,'Deployment needs'!54:54)+LOOKUP(U1,'Deployment needs'!$2:$2,'Deployment needs'!55:55) -> 4.0689815 | U4: 1st Shift Goal | V4: =LOOKUP(U1,'Deployment needs'!$2:$2,'Deployment needs'!$53:$53) -> 7150 | AA4: {=IFERROR(INDEX($B$1:$B$272,SMALL(IF($O$3=$C$1:$C$272,ROW($C$1:$C$272)-MIN(ROW($B$1:$B$272))+1,""), ROW()-1)),"")} | AB4: {=IFERROR(INDEX($B$1:$B$272,SMALL(IF($O$10=$C$1:$C$272,ROW($C$1:$C$272)-MIN(ROW($B$1:$B$272))+1,""), ROW()-1)),"")} | AC4: {=IFERROR(INDEX($B$1:$B$272,SMALL(IF($O$9=$C$1:$C$272,ROW($C$1:$C$272)-MIN(ROW($B$1:$B$272))+1,""), ROW()-1)),"")} | AE4: {=IFERROR(INDEX($B$1:$B$272,SMALL(IF($O$6=$C$1:$C$272,ROW($C$1:$C$272)-MIN(ROW($B$1:$B$272))+1,""), ROW()-1)),"")} | AF4: {=IFERROR(INDEX($B$1:$B$272,SMALL(IF($O$8=$C$1:$C$272,ROW($C$1:$C$272)-MIN(ROW($B$1:$B$272))+1,""), ROW()-1)),"")} | AG4: {=IFERROR(INDEX($B$1:$B$272,SMALL(IF($O$31=$C$1:$C$272,ROW($C$1:$C$272)-MIN(ROW($B$1:$B$272))+1,""), ROW()-1)),"")} | AH4: {=IFERROR(INDEX($B$1:$B$272,SMALL(IF($O$21=$C$1:$C$272,ROW($C$1:$C$272)-MIN(ROW($B$1:$B$272))+1,""), ROW()-1)),"")} | AI4: {=IFERROR(INDEX($B$1:$B$31,SMALL(IF($O$4=$C$1:$C$31,ROW($C$1:$C$31)-MIN(ROW($B$1:$B$31))+1,""), ROW()-1)),"")} | AJ4: {=IFERROR(INDEX($B$32:$B$646,SMALL(IF($O$4=$C$32:$C$646,ROW($C$32:$C$646)-MIN(ROW($B$32:$B$646))+1,""), ROW()-1)),"")} | AL4: 1st | AN4: {=IFERROR(INDEX($B$1:$B$675,SMALL(IF($O$15=$C$1:$C$675,ROW($C$1:$C$675)-MIN(ROW($B$1:$B$675))+1,""), ROW()-12)),"")}
B5: {=IFERROR(_xlfn.IFS(E9=0,"",E9>0,E9),"")} -> Yasmin Montero | C5: {=IFERROR(_xlfn.IFS(F9=0,"",F9>0,F9),"")} -> x | E5: Maria Carrasco | F5: SL | G5: Deja Andersson | I5: SL | J5: 7:30 AM-11:30 AM Crew | O5: SN | P5: Picking- Singles | Q5: =COUNTIFS($F$5:$F$33,O5)+COUNTIFS($I$5:$I$33,O5) -> 0 | U5: Projected Goal | V5: 10000 | AA5: {=IFERROR(INDEX($B$1:$B$272,SMALL(IF($O$3=$C$1:$C$272,ROW($C$1:$C$272)-MIN(ROW($B$1:$B$272))+1,""), ROW()-1)),"")} | AB5: {=IFERROR(INDEX($B$1:$B$272,SMALL(IF($O$10=$C$1:$C$272,ROW($C$1:$C$272)-MIN(ROW($B$1:$B$272))+1,""), ROW()-1)),"")} | AC5: {=IFERROR(INDEX($B$1:$B$272,SMALL(IF($O$9=$C$1:$C$272,ROW($C$1:$C$272)-MIN(ROW($B$1:$B$272))+1,""), ROW()-1)),"")} | AE5: {=IFERROR(INDEX($B$1:$B$272,SMALL(IF($O$6=$C$1:$C$272,ROW($C$1:$C$272)-MIN(ROW($B$1:$B$272))+1,""), ROW()-1)),"")} | AF5: {=IFERROR(INDEX($B$1:$B$272,SMALL(IF($O$8=$C$1:$C$272,ROW($C$1:$C$272)-MIN(ROW($B$1:$B$272))+1,""), ROW()-1)),"")} | AG5: {=IFERROR(INDEX($B$1:$B$272,SMALL(IF($O$31=$C$1:$C$272,ROW($C$1:$C$272)-MIN(ROW($B$1:$B$272))+1,""), ROW()-1)),"")} | AH5: {=IFERROR(INDEX($B$1:$B$272,SMALL(IF($O$21=$C$1:$C$272,ROW($C$1:$C$272)-MIN(ROW($B$1:$B$272))+1,""), ROW()-1)),"")} | AI5: {=IFERROR(INDEX($B$1:$B$31,SMALL(IF($O$4=$C$1:$C$31,ROW($C$1:$C$31)-MIN(ROW($B$1:$B$31))+1,""), ROW()-1)),"")} | AJ5: {=IFERROR(INDEX($B$32:$B$646,SMALL(IF($O$4=$C$32:$C$646,ROW($C$32:$C$646)-MIN(ROW($B$32:$B$646))+1,""), ROW()-1)),"")}
B6: {=IFERROR(_xlfn.IFS(E10=0,"",E10>0,E10),"")} -> Annaliet Rodriguez Perez | C6: {=IFERROR(_xlfn.IFS(F10=0,"",F10>0,F10),"")} -> x | E6: Brandee Foster- IL | F6: i | G6: Eumary Quinones | I6: I | O6: S | P6: Shipping | Q6: =COUNTIFS($F$5:$F$33,O6)+COUNTIFS($I$5:$I$33,O6) -> 0 | S6: {=LOOKUP(U1,'Deployment needs'!$2:$2,('Deployment needs'!56:56+'Deployment needs'!57:57))} -> 1.0857407 | U6: Total Units | V6: 28542 | AA6: {=IFERROR(INDEX($B$1:$B$272,SMALL(IF($O$3=$C$1:$C$272,ROW($C$1:$C$272)-MIN(ROW($B$1:$B$272))+1,""), ROW()-1)),"")} | AB6: {=IFERROR(INDEX($B$1:$B$272,SMALL(IF($O$10=$C$1:$C$272,ROW($C$1:$C$272)-MIN(ROW($B$1:$B$272))+1,""), ROW()-1)),"")} | AC6: {=IFERROR(INDEX($B$1:$B$272,SMALL(IF($O$9=$C$1:$C$272,ROW($C$1:$C$272)-MIN(ROW($B$1:$B$272))+1,""), ROW()-1)),"")} | AE6: {=IFERROR(INDEX($B$1:$B$272,SMALL(IF($O$6=$C$1:$C$272,ROW($C$1:$C$272)-MIN(ROW($B$1:$B$272))+1,""), ROW()-1)),"")} | AF6: Truck | AG6: Baby Bundle Project | AH6: {=IFERROR(INDEX($B$1:$B$272,SMALL(IF($O$21=$C$1:$C$272,ROW($C$1:$C$272)-MIN(ROW($B$1:$B$272))+1,""), ROW()-1)),"")} | AI6: {=IFERROR(INDEX($B$1:$B$31,SMALL(IF($O$4=$C$1:$C$31,ROW($C$1:$C$31)-MIN(ROW($B$1:$B$31))+1,""), ROW()-1)),"")} | AJ6: {=IFERROR(INDEX($B$32:$B$646,SMALL(IF($O$4=$C$32:$C$646,ROW($C$32:$C$646)-MIN(ROW($B$32:$B$646))+1,""), ROW()-1)),"")}
B7: {=IFERROR(_xlfn.IFS(E11=0,"",E11>0,E11),"")} -> Damaris Curbelo | C7: {=IFERROR(_xlfn.IFS(F11=0,"",F11>0,F11),"")} -> x | E7: Ailin Reynaldo | F7: I | G7: Sunia Hernandez | I7: x | O7: TR | P7: Truck loading | Q7: =COUNTIFS($F$5:$F$33,O7)+COUNTIFS($I$5:$I$33,O7) -> 0 | S7: =LOOKUP(U1,'Deployment needs'!$2:$2,'Deployment needs'!60:60) -> 0.18868056 | U7: Created Wave Units | V7: 3677 | AA7: {=IFERROR(INDEX($B$1:$B$272,SMALL(IF($O$3=$C$1:$C$272,ROW($C$1:$C$272)-MIN(ROW($B$1:$B$272))+1,""), ROW()-1)),"")} | AB7: Pick Singles | AC7: {=IFERROR(INDEX($B$1:$B$272,SMALL(IF($O$9=$C$1:$C$272,ROW($C$1:$C$272)-MIN(ROW($B$1:$B$272))+1,""), ROW()-1)),"")} | AE7: {=IFERROR(INDEX($B$1:$B$272,SMALL(IF($O$6=$C$1:$C$272,ROW($C$1:$C$272)-MIN(ROW($B$1:$B$272))+1,""), ROW()-1)),"")} | AF7: {=IFERROR(INDEX($B$1:$B$272,SMALL(IF($O$7=$C$1:$C$272,ROW($C$1:$C$272)-MIN(ROW($B$1:$B$272))+1,""), ROW()-6)),"")} | AG7: {=IFERROR(INDEX($B$1:$B$272,SMALL(IF($O$28=$C$1:$C$272,ROW($C$1:$C$272)-MIN(ROW($B$1:$B$272))+1,""), ROW()-6)),"")} | AH7: {=IFERROR(INDEX($B$1:$B$272,SMALL(IF($O$21=$C$1:$C$272,ROW($C$1:$C$272)-MIN(ROW($B$1:$B$272))+1,""), ROW()-1)),"")} | AI7: {=IFERROR(INDEX($B$1:$B$31,SMALL(IF($O$4=$C$1:$C$31,ROW($C$1:$C$31)-MIN(ROW($B$1:$B$31))+1,""), ROW()-1)),"")} | AJ7: {=IFERROR(INDEX($B$32:$B$646,SMALL(IF($O$4=$C$32:$C$646,ROW($C$32:$C$646)-MIN(ROW($B$32:$B$646))+1,""), ROW()-1)),"")}
B8: {=IFERROR(_xlfn.IFS(E12=0,"",E12>0,E12),"")} -> Dania Curbelo | C8: P | E8: Chrissy Parisek | F8: x | G8: Orlis Daniel Zaldivar | I8: x | O8: TP | P8: Taper/Downsize | Q8: =COUNTIFS($F$5:$F$33,O8)+COUNTIFS($I$5:$I$33,O8) -> 0 | S8: {=LOOKUP(U1,'Deployment needs'!$2:$2,('Deployment needs'!59:59+'Deployment needs'!62:62))} -> 0.27547222 | U8: Available Units | V8: 19216 | AA8: Lead - Support/Trainer | AB8: {=IFERROR(INDEX($B$1:$B$272,SMALL(IF($O$5=$C$1:$C$272,ROW($C$1:$C$272)-MIN(ROW($B$1:$B$272))+1,""), ROW()-7)),"")} | AC8: {=IFERROR(INDEX($B$1:$B$272,SMALL(IF($O$9=$C$1:$C$272,ROW($C$1:$C$272)-MIN(ROW($B$1:$B$272))+1,""), ROW()-1)),"")} | AE8: {=IFERROR(INDEX($B$1:$B$272,SMALL(IF($O$6=$C$1:$C$272,ROW($C$1:$C$272)-MIN(ROW($B$1:$B$272))+1,""), ROW()-1)),"")} | AF8: {=IFERROR(INDEX($B$1:$B$272,SMALL(IF($O$7=$C$1:$C$10,ROW($C$1:$C$272)-MIN(ROW($B$1:$B$272))+1,""), ROW()-6)),"")} | AG8: {=IFERROR(INDEX($B$1:$B$272,SMALL(IF($O$28=$C$1:$C$272,ROW($C$1:$C$272)-MIN(ROW($B$1:$B$272))+1,""), ROW()-6)),"")} | AH8: {=IFERROR(INDEX($B$1:$B$272,SMALL(IF($O$21=$C$1:$C$272,ROW($C$1:$C$272)-MIN(ROW($B$1:$B$272))+1,""), ROW()-1)),"")} | AI8: {=IFERROR(INDEX($B$1:$B$31,SMALL(IF($O$4=$C$1:$C$31,ROW($C$1:$C$31)-MIN(ROW($B$1:$B$31))+1,""), ROW()-1)),"")} | AJ8: {=IFERROR(INDEX($B$32:$B$646,SMALL(IF($O$4=$C$32:$C$646,ROW($C$32:$C$646)-MIN(ROW($B$32:$B$646))+1,""), ROW()-1)),"")}
B9: {=IFERROR(_xlfn.IFS(E13=0,"",E13>0,E13),"")} -> Esther Fonseca | C9: {=IFERROR(_xlfn.IFS(F13=0,"",F13>0,F13),"")} -> x | E9: Yasmin Montero | F9: x | G9: Rolexis Lopez Diaz | I9: x | O9: B | P9: Bander | Q9: =COUNTIFS($F$5:$F$33,O9)+COUNTIFS($I$5:$I$33,O9) -> 0 | S9: =LOOKUP(U1,'Deployment needs'!$2:$2,'Deployment needs'!63:63) -> 1.1585648 | U9: Units at Bander | V9: 2718 | AA9: {=IFERROR(INDEX($B$1:$B$272,SMALL(IF($O$30=$C$1:$C$272,ROW($C$1:$C$272)-MIN(ROW($B$1:$B$272))+1,""),ROW()-8)),"")} -> Maria Carrasco | AB9: {=IFERROR(INDEX($B$1:$B$272,SMALL(IF($O$5=$C$1:$C$272,ROW($C$1:$C$272)-MIN(ROW($B$1:$B$272))+1,""), ROW()-7)),"")} | AC9: {=IFERROR(INDEX($B$1:$B$272,SMALL(IF($O$9=$C$1:$C$272,ROW($C$1:$C$272)-MIN(ROW($B$1:$B$272))+1,""), ROW()-1)),"")} | AE9: {=IFERROR(INDEX($B$1:$B$272,SMALL(IF($O$6=$C$1:$C$272,ROW($C$1:$C$272)-MIN(ROW($B$1:$B$272))+1,""), ROW()-1)),"")} | AF9: {=IFERROR(INDEX($B$1:$B$272,SMALL(IF($O$7=$C$1:$C$10,ROW($C$1:$C$272)-MIN(ROW($B$1:$B$272))+1,""), ROW()-6)),"")} | AG9: {=IFERROR(INDEX($B$1:$B$272,SMALL(IF($O$28=$C$1:$C$272,ROW($C$1:$C$272)-MIN(ROW($B$1:$B$272))+1,""), ROW()-6)),"")} | AH9: {=IFERROR(INDEX($B$1:$B$272,SMALL(IF($O$21=$C$1:$C$272,ROW($C$1:$C$272)-MIN(ROW($B$1:$B$272))+1,""), ROW()-1)),"")} | AI9: {=IFERROR(INDEX($B$1:$B$31,SMALL(IF($O$4=$C$1:$C$31,ROW($C$1:$C$31)-MIN(ROW($B$1:$B$31))+1,""), ROW()-1)),"")} | AJ9: {=IFERROR(INDEX($B$32:$B$646,SMALL(IF($O$4=$C$32:$C$646,ROW($C$32:$C$646)-MIN(ROW($B$32:$B$646))+1,""), ROW()-1)),"")}
B10: {=IFERROR(_xlfn.IFS(E14=0,"",E14>0,E14),"")} -> Yordanka Manzanares | C10: {=IFERROR(_xlfn.IFS(F14=0,"",F14>0,F14),"")} -> x | E10: Annaliet Rodriguez Perez | F10: x | G10: Joaquin Lopez Enrique | I10: x | O10: AB | P10: Autobagger | Q10: =COUNTIFS($F$5:$F$33,O10)+COUNTIFS($I$5:$I$33,O10) -> 0 | S10: =LOOKUP(U1,'Deployment needs'!$2:$2,'Deployment needs'!64:64) -> 1 | U10: Held by Replen | V10: 868 | AA10: {=IFERROR(INDEX($B$1:$B$272,SMALL(IF($O$30=$C$1:$C$272,ROW($C$1:$C$272)-MIN(ROW($B$1:$B$272))+1,""),ROW()-8)),"")} -> Deja Andersson | AB10: {=IFERROR(INDEX($B$1:$B$272,SMALL(IF($O$5=$C$1:$C$272,ROW($C$1:$C$272)-MIN(ROW($B$1:$B$272))+1,""), ROW()-7)),"")} | AC10: {=IFERROR(INDEX($B$1:$B$272,SMALL(IF($O$9=$C$1:$C$272,ROW($C$1:$C$272)-MIN(ROW($B$1:$B$272))+1,""), ROW()-1)),"")} | AE10: {=IFERROR(INDEX($B$1:$B$272,SMALL(IF($O$6=$C$1:$C$272,ROW($C$1:$C$272)-MIN(ROW($B$1:$B$272))+1,""), ROW()-1)),"")} | AF10: {=IFERROR(INDEX($B$1:$B$272,SMALL(IF($O$7=$C$1:$C$10,ROW($C$1:$C$272)-MIN(ROW($B$1:$B$272))+1,""), ROW()-6)),"")} | AG10: {=IFERROR(INDEX($B$1:$B$272,SMALL(IF($O$28=$C$1:$C$272,ROW($C$1:$C$272)-MIN(ROW($B$1:$B$272))+1,""), ROW()-6)),"")} | AH10: {=IFERROR(INDEX($B$1:$B$272,SMALL(IF($O$21=$C$1:$C$272,ROW($C$1:$C$272)-MIN(ROW($B$1:$B$272))+1,""), ROW()-1)),"")} | AI10: {=IFERROR(INDEX($B$1:$B$31,SMALL(IF($O$4=$C$1:$C$31,ROW($C$1:$C$31)-MIN(ROW($B$1:$B$31))+1,""), ROW()-1)),"")} | AJ10: {=IFERROR(INDEX($B$32:$B$646,SMALL(IF($O$4=$C$32:$C$646,ROW($C$32:$C$646)-MIN(ROW($B$32:$B$646))+1,""), ROW()-1)),"")} | AL10: 2nd
B11: {=IFERROR(_xlfn.IFS(E15=0,"",E15>0,E15),"")} -> Jackie Gomez | C11: {=IFERROR(_xlfn.IFS(F15=0,"",F15>0,F15),"")} -> x | E11: Damaris Curbelo | F11: x | G11: Dora Lopez (Alicia) | I11: x | O11: R | P11: Resets | Q11: =COUNTIFS($F$5:$F$33,O11)+COUNTIFS($I$5:$I$33,O11) -> 0 | S11: =LOOKUP(U1,'Deployment needs'!$2:$2,'Deployment needs'!93:93) -> 0.18055556 | U11: Actual Picked | V11: TBD | AA11: {=IFERROR(INDEX($B$1:$B$272,SMALL(IF($O$30=$C$1:$C$272,ROW($C$1:$C$272)-MIN(ROW($B$1:$B$272))+1,""),ROW()-8)),"")} | AB11: {=IFERROR(INDEX($B$1:$B$272,SMALL(IF($O$5=$C$1:$C$272,ROW($C$1:$C$272)-MIN(ROW($B$1:$B$272))+1,""), ROW()-7)),"")} | AC11: {=IFERROR(INDEX($B$1:$B$272,SMALL(IF($O$9=$C$1:$C$272,ROW($C$1:$C$272)-MIN(ROW($B$1:$B$272))+1,""), ROW()-1)),"")} | AE11: {=IFERROR(INDEX($B$1:$B$272,SMALL(IF($O$6=$C$1:$C$272,ROW($C$1:$C$272)-MIN(ROW($B$1:$B$272))+1,""), ROW()-1)),"")} | AF11: ="Returns"&" "&R22&" "&"orders"&" "&COUNTA(AF12:AF27)-COUNTBLANK(AF12:AF27) -> Returns 535 orders -1 | AG11: {=IFERROR(INDEX($B$1:$B$272,SMALL(IF($O$28=$C$1:$C$272,ROW($C$1:$C$272)-MIN(ROW($B$1:$B$272))+1,""), ROW()-6)),"")} | AH11: {=IFERROR(INDEX($B$1:$B$272,SMALL(IF($O$21=$C$1:$C$272,ROW($C$1:$C$272)-MIN(ROW($B$1:$B$272))+1,""), ROW()-1)),"")} | AI11: {=IFERROR(INDEX($B$1:$B$31,SMALL(IF($O$4=$C$1:$C$31,ROW($C$1:$C$31)-MIN(ROW($B$1:$B$31))+1,""), ROW()-1)),"")} | AJ11: {=IFERROR(INDEX($B$32:$B$646,SMALL(IF($O$4=$C$32:$C$646,ROW($C$32:$C$646)-MIN(ROW($B$32:$B$646))+1,""), ROW()-1)),"")}
B12: {=IFERROR(_xlfn.IFS(E16=0,"",E16>0,E16),"")} -> Madelayne Oduardo | C12: {=IFERROR(_xlfn.IFS(F16=0,"",F16>0,F16),"")} -> x | E12: Dania Curbelo | F12: x | G12: Sonia Lopez Medina | I12: x | O12: E | P12: Resets Exeptions | Q12: =COUNTIFS($F$5:$F$33,O12)+COUNTIFS($I$5:$I$33,O12) -> 0 | U12: BI Shift Shipped | V12: TBD | Z12: Inventory | AA12: Resets | AB12: Picking Cycle Counts / Spot Count | AC12: Outbound Exception | AE12: Tasks | AF12: {=IFERROR(INDEX($B$1:$B$272,SMALL(IF($C$1:$C$272=$O$22, ROW($B$1:$B$272)-ROW($B$1)+1),ROWS($AF$12:AF12) ) ), "")} | AG12: Sort Returns Putaway | AH12: Inventory & CC Reconcile | AI12: {=IFERROR(INDEX($B$1:$B$31,SMALL(IF($O$4=$C$1:$C$31,ROW($C$1:$C$31)-MIN(ROW($B$1:$B$31))+1,""), ROW()-1)),"")} | AJ12: {=IFERROR(INDEX($B$32:$B$646,SMALL(IF($O$4=$C$32:$C$646,ROW($C$32:$C$646)-MIN(ROW($B$32:$B$646))+1,""), ROW()-1)),"")}
B13: {=IFERROR(_xlfn.IFS(E17=0,"",E17>0,E17),"")} -> Roxana Lloret | C13: {=IFERROR(_xlfn.IFS(F17=0,"",F17>0,F17),"")} -> x | E13: Esther Fonseca | F13: x | G13: Josefa Martinez | I13: x | J13: 12 pm- 4 pm crew | O13: IP | P13: Ipads | Q13: =COUNTIFS($F$5:$F$33,O13)+COUNTIFS($I$5:$I$33,O13) -> 0 | U13: % to Plan Shipped | V13: =V12/V4 -> #VALUE! | AA13: {=IFERROR(INDEX($B$1:$B$272,SMALL(IF($O$11=$C$1:$C$272,ROW($C$1:$C$272)-MIN(ROW($B$1:$B$272))+1,""), ROW()-12)),"")} | AB13: {=IFERROR(INDEX($B$1:$B$272,SMALL(IF($O$16=$C$1:$C$272,ROW($C$1:$C$272)-MIN(ROW($B$1:$B$272))+1,""), ROW()-12)),"")} | AC13: {=IFERROR(INDEX($B$1:$B$272,SMALL(IF($O$14=$C$1:$C$272,ROW($C$1:$C$272)-MIN(ROW($B$1:$B$272))+1,""), ROW()-12)),"")} | AE13: Rush | AF13: {=IFERROR(INDEX($B$1:$B$272,SMALL(IF($C$1:$C$272=$O$22, ROW($B$1:$B$272)-ROW($B$1)+1),ROWS($AF$12:AF13) ) ), "")} | AG13: {=IFERROR(INDEX($B$1:$B$272,SMALL(IF($O$24=$C$1:$C$272,ROW($C$1:$C$272)-MIN(ROW($B$1:$B$272))+1,""), ROW()-12)),"")} | AH13: {=IFERROR(INDEX($B$1:$B$272,SMALL(IF($O$32=$C$1:$C$272,ROW($C$1:$C$272)-MIN(ROW($B$1:$B$272))+1,""), ROW()-12)),"")} -> Brandee Foster- IL | AI13: {=IFERROR(INDEX($B$1:$B$31,SMALL(IF($O$4=$C$1:$C$31,ROW($C$1:$C$31)-MIN(ROW($B$1:$B$31))+1,""), ROW()-1)),"")} | AJ13: {=IFERROR(INDEX($B$32:$B$646,SMALL(IF($O$4=$C$32:$C$646,ROW($C$32:$C$646)-MIN(ROW($B$32:$B$646))+1,""), ROW()-1)),"")}
B14: {=IFERROR(_xlfn.IFS(E18=0,"",E18>0,E18),"")} -> Shvodra Anderson | C14: {=IFERROR(_xlfn.IFS(F18=0,"",F18>0,F18),"")} -> x | E14: Yordanka Manzanares | F14: x | G14: Ernesto Reyes Perez | I14: x | O14: DS | P14: Outbound Exception | Q14: =COUNTIFS($F$5:$F$33,O14)+COUNTIFS($I$5:$I$33,O14) -> 0 | S14: {=LOOKUP(U1,'Deployment needs'!$2:$2,('Deployment needs'!91:91+'Deployment needs'!92:92+'Deployment needs'!61:61))} -> 0.5662037 | U14: Clustered Carts | V14: 60 | AA14: {=IFERROR(INDEX($B$1:$B$272,SMALL(IF($O$11=$C$1:$C$272,ROW($C$1:$C$272)-MIN(ROW($B$1:$B$272))+1,""), ROW()-12)),"")} | AB14: {=IFERROR(INDEX($B$1:$B$272,SMALL(IF($O$16=$C$1:$C$272,ROW($C$1:$C$272)-MIN(ROW($B$1:$B$272))+1,""), ROW()-12)),"")} | AC14: {=IFERROR(INDEX($B$1:$B$272,SMALL(IF($O$14=$C$1:$C$272,ROW($C$1:$C$272)-MIN(ROW($B$1:$B$272))+1,""), ROW()-12)),"")} | AE14: Aged orders/Emails | AF14: {=IFERROR(INDEX($B$1:$B$272,SMALL(IF($C$1:$C$272=$O$22, ROW($B$1:$B$272)-ROW($B$1)+1),ROWS($AF$12:AF14) ) ), "")} | AG14: {=IFERROR(INDEX($B$1:$B$272,SMALL(IF($O$24=$C$1:$C$272,ROW($C$1:$C$272)-MIN(ROW($B$1:$B$272))+1,""), ROW()-12)),"")} | AH14: {=IFERROR(INDEX($B$1:$B$272,SMALL(IF($O$32=$C$1:$C$272,ROW($C$1:$C$272)-MIN(ROW($B$1:$B$272))+1,""), ROW()-12)),"")} -> Ailin Reynaldo | AI14: {=IFERROR(INDEX($B$1:$B$31,SMALL(IF($O$4=$C$1:$C$31,ROW($C$1:$C$31)-MIN(ROW($B$1:$B$31))+1,""), ROW()-1)),"")} | AJ14: {=IFERROR(INDEX($B$32:$B$646,SMALL(IF($O$4=$C$32:$C$646,ROW($C$32:$C$646)-MIN(ROW($B$32:$B$646))+1,""), ROW()-1)),"")}
B15: {=IFERROR(_xlfn.IFS(E19=0,"",E19>0,E19),"")} -> Laura Gonzalez Bustamante | C15: {=IFERROR(_xlfn.IFS(F19=0,"",F19>0,F19),"")} -> x | E15: Jackie Gomez | F15: x | G15: Yordany Miranda | I15: x | O15: MP | P15: DTC Putaway | Q15: =COUNTIFS($F$5:$F$33,O15)+COUNTIFS($I$5:$I$33,O15) -> 0 | S15: =LOOKUP(U1,'Deployment needs'!$2:$2,'Deployment needs'!95:95) -> 0.25 | U15: Multis to Pick | V15: 46186 | AA15: {=IFERROR(INDEX($B$1:$B$272,SMALL(IF($O$11=$C$1:$C$272,ROW($C$1:$C$272)-MIN(ROW($B$1:$B$272))+1,""), ROW()-12)),"")} | AB15: {=IFERROR(INDEX($B$1:$B$272,SMALL(IF($O$16=$C$1:$C$272,ROW($C$1:$C$272)-MIN(ROW($B$1:$B$272))+1,""), ROW()-12)),"")} | AC15: {=IFERROR(INDEX($B$1:$B$272,SMALL(IF($O$14=$C$1:$C$272,ROW($C$1:$C$272)-MIN(ROW($B$1:$B$272))+1,""), ROW()-12)),"")} | AF15: {=IFERROR(INDEX($B$1:$B$272,SMALL(IF($C$1:$C$272=$O$22, ROW($B$1:$B$272)-ROW($B$1)+1),ROWS($AF$12:AF15) ) ), "")} | AG15: {=IFERROR(INDEX($B$1:$B$272,SMALL(IF($O$24=$C$1:$C$272,ROW($C$1:$C$272)-MIN(ROW($B$1:$B$272))+1,""), ROW()-12)),"")} | AH15: {=IFERROR(INDEX($B$1:$B$272,SMALL(IF($O$32=$C$1:$C$272,ROW($C$1:$C$272)-MIN(ROW($B$1:$B$272))+1,""), ROW()-12)),"")} -> Eumary Quinones | AI15: {=IFERROR(INDEX($B$1:$B$31,SMALL(IF($O$4=$C$1:$C$31,ROW($C$1:$C$31)-MIN(ROW($B$1:$B$31))+1,""), ROW()-1)),"")} | AJ15: {=IFERROR(INDEX($B$32:$B$646,SMALL(IF($O$4=$C$32:$C$646,ROW($C$32:$C$646)-MIN(ROW($B$32:$B$646))+1,""), ROW()-1)),"")}
B16: {=IFERROR(_xlfn.IFS(E20=0,"",E20>0,E20),"")} -> Mbaya Kapita | C16: {=IFERROR(_xlfn.IFS(F20=0,"",F20>0,F20),"")} -> x | E16: Madelayne Oduardo | F16: x | G16: Carlos Molina | I16: x | O16: PC | P16: Picking CC | Q16: =COUNTIFS($F$5:$F$33,O16)+COUNTIFS($I$5:$I$33,O16) -> 0 | S16: =LOOKUP(U1,'Deployment needs'!$2:$2,'Deployment needs'!88:88) -> 2.4138889 | U16: Singles to Pick | V16: 46187 | AA16: {=IFERROR(INDEX($B$1:$B$272,SMALL(IF($O$11=$C$1:$C$272,ROW($C$1:$C$272)-MIN(ROW($B$1:$B$272))+1,""), ROW()-12)),"")} | AB16: {=IFERROR(INDEX($B$1:$B$272,SMALL(IF($O$16=$C$1:$C$272,ROW($C$1:$C$272)-MIN(ROW($B$1:$B$272))+1,""), ROW()-12)),"")} | AC16: ="CubiScan - in / out"&" "&R27 -> CubiScan - in / out 0 | AE16: Misspicks/DTC Putaway | AF16: {=IFERROR(INDEX($B$1:$B$272,SMALL(IF($C$1:$C$272=$O$22, ROW($B$1:$B$272)-ROW($B$1)+1),ROWS($AF$12:AF16) ) ), "")} | AG16: {=IFERROR(INDEX($B$1:$B$272,SMALL(IF($O$24=$C$1:$C$272,ROW($C$1:$C$272)-MIN(ROW($B$1:$B$272))+1,""), ROW()-12)),"")} | AH16: {=IFERROR(INDEX($B$1:$B$272,SMALL(IF($O$32=$C$1:$C$272,ROW($C$1:$C$272)-MIN(ROW($B$1:$B$272))+1,""), ROW()-12)),"")} | AI16: {=IFERROR(INDEX($B$1:$B$31,SMALL(IF($O$4=$C$1:$C$31,ROW($C$1:$C$31)-MIN(ROW($B$1:$B$31))+1,""), ROW()-1)),"")} | AJ16: {=IFERROR(INDEX($B$32:$B$646,SMALL(IF($O$4=$C$32:$C$646,ROW($C$32:$C$646)-MIN(ROW($B$32:$B$646))+1,""), ROW()-1)),"")}
B17: {=IFERROR(_xlfn.IFS(E21=0,"",E21>0,E21),"")} -> Tamara Izada Aguado | C17: {=IFERROR(_xlfn.IFS(F21=0,"",F21>0,F21),"")} -> x | E17: Roxana Lloret | F17: x | O17: OC | P17: Overstock CC | Q17: =COUNTIFS($F$5:$F$33,O17)+COUNTIFS($I$5:$I$33,O17) -> 0 | S17: =LOOKUP(U1,'Deployment needs'!$2:$2,'Deployment needs'!75:75) -> 1.0126111 | U17: UPP | V17: 4,2 | AA17: {=IFERROR(INDEX($B$1:$B$272,SMALL(IF($O$11=$C$1:$C$272,ROW($C$1:$C$272)-MIN(ROW($B$1:$B$272))+1,""), ROW()-12)),"")} | AB17: {=IFERROR(INDEX($B$1:$B$272,SMALL(IF($O$16=$C$1:$C$272,ROW($C$1:$C$272)-MIN(ROW($B$1:$B$272))+1,""), ROW()-12)),"")} | AC17: {=IFERROR(INDEX($B$1:$B$272,SMALL(IF($O$27=$C$1:$C$272,ROW($C$1:$C$272)-MIN(ROW($B$1:$B$272))+1,""), ROW()-16)),"")} | AE17: {=IFERROR(INDEX($B$1:$B$272,SMALL(IF($O$15=$C$1:$C$272,ROW($C$1:$C$272)-MIN(ROW($B$1:$B$272))+1,""), ROW()-16)),"")} | AF17: {=IFERROR(INDEX($B$1:$B$272,SMALL(IF($C$1:$C$272=$O$22, ROW($B$1:$B$272)-ROW($B$1)+1),ROWS($AF$12:AF17) ) ), "")} | AG17: ="Returns Putaway"&" "&R24 -> Returns Putaway 637 | AH17: {=IFERROR(INDEX($B$1:$B$272,SMALL(IF($O$32=$C$1:$C$272,ROW($C$1:$C$272)-MIN(ROW($B$1:$B$272))+1,""), ROW()-12)),"")} | AI17: {=IFERROR(INDEX($B$1:$B$31,SMALL(IF($O$4=$C$1:$C$31,ROW($C$1:$C$31)-MIN(ROW($B$1:$B$31))+1,""), ROW()-1)),"")} | AJ17: {=IFERROR(INDEX($B$32:$B$646,SMALL(IF($O$4=$C$32:$C$646,ROW($C$32:$C$646)-MIN(ROW($B$32:$B$646))+1,""), ROW()-1)),"")} | AL17: Rotation DTC putaway
B18: {=IFERROR(_xlfn.IFS(E22=0,"",E22>0,E22),"")} -> Hector Rocha | C18: p | E18: Shvodra Anderson | F18: x | O18: O | P18: Overstock putaway | Q18: =COUNTIFS($F$5:$F$33,O18)+COUNTIFS($I$5:$I$33,O18) -> 0 | R18: =LOOKUP($U$1-1,'Inbound SOS & EOD'!$1:$1,'Inbound SOS & EOD'!74:74) -> 140 | S18: =LOOKUP(U1,'Deployment needs'!$2:$2,'Deployment needs'!72:72) -> 4.4217778 | U18: Resets | V18: 0 | AA18: {=IFERROR(INDEX($B$1:$B$272,SMALL(IF($O$11=$C$1:$C$272,ROW($C$1:$C$272)-MIN(ROW($B$1:$B$272))+1,""), ROW()-12)),"")} | AB18: {=IFERROR(INDEX($B$1:$B$272,SMALL(IF(O$16=$C$1:$C$272,ROW($C$1:$C$272)-MIN(ROW($B$1:$B$272))+1,""), ROW()-12)),"")} | AC18: {=IFERROR(INDEX($B$1:$B$272,SMALL(IF($O$27=$C$1:$C$272,ROW($C$1:$C$272)-MIN(ROW($B$1:$B$272))+1,""), ROW()-16)),"")} | AE18: {=IFERROR(INDEX($B$1:$B$272,SMALL(IF($O$15=$C$1:$C$272,ROW($C$1:$C$272)-MIN(ROW($B$1:$B$272))+1,""), ROW()-16)),"")} | AF18: {=IFERROR(INDEX($B$1:$B$272,SMALL(IF($C$1:$C$272=$O$22, ROW($B$1:$B$272)-ROW($B$1)+1),ROWS($AF$12:AF18) ) ), "")} | AG18: {=IFERROR(INDEX($B$1:$B$272,SMALL(IF($O$25=$C$1:$C$272,ROW($C$1:$C$272)-MIN(ROW($B$1:$B$272))+1,""), ROW()-17)),"")} | AH18: {=IFERROR(INDEX($B$1:$B$272,SMALL(IF($O$32=$C$1:$C$272,ROW($C$1:$C$272)-MIN(ROW($B$1:$B$272))+1,""), ROW()-12)),"")} | AI18: {=IFERROR(INDEX($B$1:$B$31,SMALL(IF($O$4=$C$1:$C$31,ROW($C$1:$C$31)-MIN(ROW($B$1:$B$31))+1,""), ROW()-1)),"")} | AJ18: {=IFERROR(INDEX($B$32:$B$646,SMALL(IF($O$4=$C$32:$C$646,ROW($C$32:$C$646)-MIN(ROW($B$32:$B$646))+1,""), ROW()-1)),"")} | AL18: Groups | AM18: Sunday | AN18: Monday | AO18: Tuesday | AP18: Wednesday | AQ18: Thursday | AR18: Friday | AS18: Saturday
B19: {=IFERROR(_xlfn.IFS(E23=0,"",E23>0,E23),"")} -> Iraldo Rodriguez | C19: {=IFERROR(_xlfn.IFS(F23=0,"",F23>0,F23),"")} -> x | E19: Laura Gonzalez Bustamante | F19: x | O19: RP | P19: Replen Pull | Q19: =COUNTIFS($F$5:$F$33,O19)+COUNTIFS($I$5:$I$33,O19) -> 0 | R19: =LOOKUP($U$1-1,'Inbound SOS & EOD'!$1:$1,'Inbound SOS & EOD'!84:84) -> 88 | S19: =LOOKUP(U1,'Deployment needs'!$2:$2,'Deployment needs'!70:70) -> 0.30895062 | U19: Region 1 UPH | V19: TBD | Z19: Inbound | AA19: Reset Exceptions | AE19: {=IFERROR(INDEX($B$1:$B$272,SMALL(IF($O$15=$C$1:$C$272,ROW($C$1:$C$272)-MIN(ROW($B$1:$B$272))+1,""), ROW()-16)),"")} | AF19: {=IFERROR(INDEX($B$1:$B$272,SMALL(IF($C$1:$C$272=$O$22, ROW($B$1:$B$272)-ROW($B$1)+1),ROWS($AF$12:AF19) ) ), "")} | AG19: {=IFERROR(INDEX($B$1:$B$272,SMALL(IF($O$25=$C$1:$C$272,ROW($C$1:$C$272)-MIN(ROW($B$1:$B$272))+1,""), ROW()-17)),"")} | AH19: {=IFERROR(INDEX($B$1:$B$272,SMALL(IF($O$32=$C$1:$C$272,ROW($C$1:$C$272)-MIN(ROW($B$1:$B$272))+1,""), ROW()-12)),"")} | AI19: {=IFERROR(INDEX($B$1:$B$31,SMALL(IF($O$4=$C$1:$C$31,ROW($C$1:$C$31)-MIN(ROW($B$1:$B$31))+1,""), ROW()-1)),"")} | AJ19: {=IFERROR(INDEX($B$32:$B$646,SMALL(IF($O$4=$C$32:$C$646,ROW($C$32:$C$646)-MIN(ROW($B$32:$B$646))+1,""), ROW()-1)),"")} | AL19: 1st
B20: {=IFERROR(_xlfn.IFS(E25=0,"",E25>0,E25),"")} -> Jose Posse | C20: {=IFERROR(_xlfn.IFS(F25=0,"",F25>0,F25),"")} -> x | E20: Mbaya Kapita | F20: x | O20: RT | P20: Replen Throw | Q20: =COUNTIFS($F$5:$F$33,O20)+COUNTIFS($I$5:$I$33,O20) -> 0 | R20: =LOOKUP($U$1-1,'Inbound SOS & EOD'!$1:$1,'Inbound SOS & EOD'!85:85) -> 0 | S20: =LOOKUP(U1,'Deployment needs'!$2:$2,'Deployment needs'!71:71) -> 0.39722222 | U20: Region 2 UPH | V20: TBD | AA20: {=IFERROR(INDEX($B$1:$B$272,SMALL(IF($O$11=$C$1:$C$272,ROW($C$1:$C$272)-MIN(ROW($B$1:$B$272))+1,""), ROW()-12)),"")} | AE20: {=IFERROR(INDEX($B$1:$B$272,SMALL(IF($O$15=$C$1:$C$272,ROW($C$1:$C$272)-MIN(ROW($B$1:$B$272))+1,""), ROW()-16)),"")} | AF20: {=IFERROR(INDEX($B$1:$B$272,SMALL(IF($C$1:$C$272=$O$22, ROW($B$1:$B$272)-ROW($B$1)+1),ROWS($AF$12:AF20) ) ), "")} | AG20: {=IFERROR(INDEX($B$1:$B$272,SMALL(IF($O$25=$C$1:$C$272,ROW($C$1:$C$272)-MIN(ROW($B$1:$B$272))+1,""), ROW()-17)),"")} | AH20: {=IFERROR(INDEX($B$1:$B$272,SMALL(IF($O$32=$C$1:$C$272,ROW($C$1:$C$272)-MIN(ROW($B$1:$B$272))+1,""), ROW()-12)),"")} | AI20: {=IFERROR(INDEX($B$1:$B$31,SMALL(IF($O$4=$C$1:$C$31,ROW($C$1:$C$31)-MIN(ROW($B$1:$B$31))+1,""), ROW()-1)),"")} | AJ20: {=IFERROR(INDEX($B$32:$B$646,SMALL(IF($O$4=$C$32:$C$646,ROW($C$32:$C$646)-MIN(ROW($B$32:$B$646))+1,""), ROW()-1)),"")}
B21: {=IFERROR(_xlfn.IFS(E26=0,"",E26>0,E26),"")} -> John Franco Morenos Rosales | C21: {=IFERROR(_xlfn.IFS(F26=0,"",F26>0,F26),"")} -> x | E21: Tamara Izada Aguado | F21: x | O21: T | P21: Training | Q21: =COUNTIFS($F$5:$F$33,O21)+COUNTIFS($I$5:$I$33,O21) -> 0 | R21: 0 | S21: =LOOKUP(U1,'Deployment needs'!$2:$2,'Deployment needs'!94:94) -> 0 | U21: Region 12 UPH | V21: TBD | AA21: {=IFERROR(INDEX($B$1:$B$272,SMALL(IF($O$11=$C$1:$C$272,ROW($C$1:$C$272)-MIN(ROW($B$1:$B$272))+1,""), ROW()-12)),"")} | AB21: {=IFERROR(INDEX($B$1:$B$272,SMALL(IF(O$16=$C$1:$C$272,ROW($C$1:$C$272)-MIN(ROW($B$1:$B$272))+1,""), ROW()-12)),"")} | AC21: {=IFERROR(INDEX($B$1:$B$272,SMALL(IF($O$27=$C$1:$C$272,ROW($C$1:$C$272)-MIN(ROW($B$1:$B$272))+1,""), ROW()-16)),"")} | AE21: {=IFERROR(INDEX($B$1:$B$272,SMALL(IF($O$15=$C$1:$C$272,ROW($C$1:$C$272)-MIN(ROW($B$1:$B$272))+1,""), ROW()-16)),"")} | AF21: {=IFERROR(INDEX($B$1:$B$272,SMALL(IF($C$1:$C$272=$O$22, ROW($B$1:$B$272)-ROW($B$1)+1),ROWS($AF$12:AF21) ) ), "")} | AG21: {=IFERROR(INDEX($B$1:$B$272,SMALL(IF($O$25=$C$1:$C$272,ROW($C$1:$C$272)-MIN(ROW($B$1:$B$272))+1,""), ROW()-17)),"")} | AH21: {=IFERROR(INDEX($B$1:$B$272,SMALL(IF($O$32=$C$1:$C$272,ROW($C$1:$C$272)-MIN(ROW($B$1:$B$272))+1,""), ROW()-12)),"")} | AI21: {=IFERROR(INDEX($B$1:$B$272,SMALL(IF($O$4=$C$1:$C$272,ROW($C$1:$C$272)-MIN(ROW($B$1:$B$272))+1,""), ROW()-1)),"")} | AJ21: {=IFERROR(INDEX($B$32:$B$646,SMALL(IF($O$4=$C$32:$C$646,ROW($C$32:$C$646)-MIN(ROW($B$32:$B$646))+1,""), ROW()-1)),"")}
E22: Hector Rocha | F22: x | O22: RN | P22: Returns Processing | Q22: =COUNTIFS($F$5:$F$33,O22)+COUNTIFS($I$5:$I$33,O22) -> 0 | R22: =LOOKUP($U$1-1,'Inbound SOS & EOD'!$1:$1,'Inbound SOS & EOD'!41:41) -> 535 | S22: =LOOKUP(U1,'Deployment needs'!$2:$2,'Deployment needs'!81:81) -> 0.7027134 | AA22: {=IFERROR(INDEX($B$1:$B$272,SMALL(IF($O$11=$C$1:$C$272,ROW($C$1:$C$272)-MIN(ROW($B$1:$B$272))+1,""), ROW()-12)),"")} | AB22: {=IFERROR(INDEX($B$1:$B$272,SMALL(IF(O$16=$C$1:$C$272,ROW($C$1:$C$272)-MIN(ROW($B$1:$B$272))+1,""), ROW()-12)),"")} | AC22: Replen pull | AD22: Priority | AE22: {=IFERROR(INDEX($B$1:$B$272,SMALL(IF($O$15=$C$1:$C$272,ROW($C$1:$C$272)-MIN(ROW($B$1:$B$272))+1,""), ROW()-16)),"")} | AF22: {=IFERROR(INDEX($B$1:$B$272,SMALL(IF($C$1:$C$272=$O$22, ROW($B$1:$B$272)-ROW($B$1)+1),ROWS($AF$12:AF22) ) ), "")} | AG22: {=IFERROR(INDEX($B$1:$B$272,SMALL(IF($O$25=$C$1:$C$272,ROW($C$1:$C$272)-MIN(ROW($B$1:$B$272))+1,""), ROW()-17)),"")} | AH22: {=IFERROR(INDEX($B$1:$B$272,SMALL(IF($O$32=$C$1:$C$272,ROW($C$1:$C$272)-MIN(ROW($B$1:$B$272))+1,""), ROW()-12)),"")} | AI22: {=IFERROR(INDEX($B$1:$B$272,SMALL(IF($O$4=$C$1:$C$272,ROW($C$1:$C$272)-MIN(ROW($B$1:$B$272))+1,""), ROW()-1)),"")} | AJ22: {=IFERROR(INDEX($B$32:$B$646,SMALL(IF($O$4=$C$32:$C$646,ROW($C$32:$C$646)-MIN(ROW($B$32:$B$646))+1,""), ROW()-1)),"")}
E23: Iraldo Rodriguez | F23: x | O23: RE | P23: Returns Exceptions | Q23: =COUNTIFS($F$5:$F$33,O23)+COUNTIFS($I$5:$I$33,O23) -> 0 | R23: =LOOKUP($U$1-1,'Inbound SOS & EOD'!$1:$1,'Inbound SOS & EOD'!45:45) -> 40 | S23: =LOOKUP(U1,'Deployment needs'!$2:$2,'Deployment needs'!82:82) -> 0.062215434 | AA23: ="Receiving"&" "&R32 -> Receiving | AB23: Task | AC23: {=IFERROR(INDEX($B$1:$B$272,SMALL(IF($C$1:$C$272=$O$19, ROW($B$1:$B$272)-ROW($B$1)+1),ROWS($AC$23:AC23) ) ), "")} | AD23: All | AE23: {=IFERROR(INDEX($B$1:$B$272,SMALL(IF($O$15=$C$1:$C$272,ROW($C$1:$C$272)-MIN(ROW($B$1:$B$272))+1,""), ROW()-16)),"")} | AF23: {=IFERROR(INDEX($B$1:$B$272,SMALL(IF($C$1:$C$272=$O$22, ROW($B$1:$B$272)-ROW($B$1)+1),ROWS($AF$12:AF23) ) ), "")} | AG23: {=IFERROR(INDEX($B$1:$B$272,SMALL(IF($O$25=$C$1:$C$272,ROW($C$1:$C$272)-MIN(ROW($B$1:$B$272))+1,""), ROW()-17)),"")} | AH23: {=IFERROR(INDEX($B$1:$B$272,SMALL(IF($O$32=$C$1:$C$272,ROW($C$1:$C$272)-MIN(ROW($B$1:$B$272))+1,""), ROW()-12)),"")} | AI23: {=IFERROR(INDEX($B$1:$B$272,SMALL(IF($O$4=$C$1:$C$272,ROW($C$1:$C$272)-MIN(ROW($B$1:$B$272))+1,""), ROW()-1)),"")} | AJ23: {=IFERROR(INDEX($B$32:$B$646,SMALL(IF($O$4=$C$32:$C$646,ROW($C$32:$C$646)-MIN(ROW($B$32:$B$646))+1,""), ROW()-1)),"")}
E24: Jose Miro Quintana | F24: x | O24: RS | P24: Returns Sorting | Q24: =COUNTIFS($F$5:$F$33,O24)+COUNTIFS($I$5:$I$33,O24) -> 0 | R24: =LOOKUP($U$1-1,'Inbound SOS & EOD'!$1:$1,'Inbound SOS & EOD'!59:59) -> 637 | S24: =LOOKUP(U1,'Deployment needs'!$2:$2,'Deployment needs'!83:83) -> 0.22219798 | AJ24: {=IFERROR(INDEX($B$32:$B$646,SMALL(IF($O$4=$C$32:$C$646,ROW($C$32:$C$646)-MIN(ROW($B$32:$B$646))+1,""), ROW()-1)),"")}
E25: Jose Posse | F25: x | O25: RPA | P25: Returns put-away | Q25: =COUNTIFS($F$5:$F$33,O25)+COUNTIFS($I$5:$I$33,O25) -> 0 | AA25: {=IFERROR(INDEX($B$1:$B$272,SMALL(IF($C$1:$C$272=$O$26, ROW($B$1:$B$272)-ROW($B$1)+1),ROWS($AA$25:AA25) ) ), "")} | AC25: {=IFERROR(INDEX($B$1:$B$272,SMALL(IF($C$1:$C$272=$O$19, ROW($B$1:$B$272)-ROW($B$1)+1),ROWS($AC$23:AC25) ) ), "")} | AE25: Replen throw | AF25: {=IFERROR(INDEX($B$1:$B$272,SMALL(IF($C$1:$C$272=$O$22, ROW($B$1:$B$272)-ROW($B$1)+1),ROWS($AF$12:AF25) ) ), "")} | AG25: {=IFERROR(INDEX($B$1:$B$272,SMALL(IF($O$25=$C$1:$C$272,ROW($C$1:$C$272)-MIN(ROW($B$1:$B$272))+1,""), ROW()-17)),"")} | AH25: {=IFERROR(INDEX($B$1:$B$272,SMALL(IF($O$32=$C$1:$C$272,ROW($C$1:$C$272)-MIN(ROW($B$1:$B$272))+1,""), ROW()-12)),"")} | AI25: {=IFERROR(INDEX($B$1:$B$272,SMALL(IF($O$4=$C$1:$C$272,ROW($C$1:$C$272)-MIN(ROW($B$1:$B$272))+1,""), ROW()-1)),"")} | AJ25: {=IFERROR(INDEX($B$32:$B$646,SMALL(IF($O$4=$C$32:$C$646,ROW($C$32:$C$646)-MIN(ROW($B$32:$B$646))+1,""), ROW()-1)),"")}
E26: John Franco Morenos Rosales | F26: x | O26: RC | P26: Receiving | Q26: =COUNTIFS($F$5:$F$33,O26)+COUNTIFS($I$5:$I$33,O26) -> 0 | R26: =LOOKUP($U$1-1,'Inbound SOS & EOD'!$1:$1,'Inbound SOS & EOD'!56:56) -> 0 | S26: =LOOKUP(U1,'Deployment needs'!$2:$2,'Deployment needs'!73:73) -> 1.4739259 | AA26: {=IFERROR(INDEX($B$1:$B$272,SMALL(IF($C$1:$C$272=$O$26, ROW($B$1:$B$272)-ROW($B$1)+1),ROWS($AA$25:AA26) ) ), "")} | AC26: {=IFERROR(INDEX($B$1:$B$272,SMALL(IF($C$1:$C$272=$O$19, ROW($B$1:$B$272)-ROW($B$1)+1),ROWS($AC$23:AC26) ) ), "")} | AE26: {=IFERROR(INDEX($B$1:$B$272,SMALL(IF($C$1:$C$272=$O$20, ROW($B$1:$B$272)-ROW($B$1)+1),ROWS($AE$26:AE26) ) ), "")} | AF26: {=IFERROR(INDEX($B$1:$B$272,SMALL(IF($C$1:$C$272=$O$22, ROW($B$1:$B$272)-ROW($B$1)+1),ROWS($AF$12:AF26) ) ), "")} | AG26: {=IFERROR(INDEX($B$1:$B$272,SMALL(IF($O$25=$C$1:$C$272,ROW($C$1:$C$272)-MIN(ROW($B$1:$B$272))+1,""), ROW()-17)),"")} | AH26: {=IFERROR(INDEX($B$1:$B$272,SMALL(IF($O$32=$C$1:$C$272,ROW($C$1:$C$272)-MIN(ROW($B$1:$B$272))+1,""), ROW()-12)),"")} | AI26: {=IFERROR(INDEX($B$1:$B$272,SMALL(IF($O$4=$C$1:$C$272,ROW($C$1:$C$272)-MIN(ROW($B$1:$B$272))+1,""), ROW()-1)),"")} | AJ26: {=IFERROR(INDEX($B$32:$B$646,SMALL(IF($O$4=$C$32:$C$646,ROW($C$32:$C$646)-MIN(ROW($B$32:$B$646))+1,""), ROW()-1)),"")}
E27: David Almaguer-Benitez | F27: x | O27: CS | P27: Cubiscan | Q27: =COUNTIFS($F$5:$F$33,O27)+COUNTIFS($I$5:$I$33,O27) -> 0 | R27: =LOOKUP($U$1-1,'Inbound SOS & EOD'!$1:$1,'Inbound SOS & EOD'!57:57) -> 0 | S27: =LOOKUP(U1,'Deployment needs'!$2:$2,'Deployment needs'!74:74) -> 1.6581667 | AA27: {=IFERROR(INDEX($B$1:$B$272,SMALL(IF($C$1:$C$272=$O$26, ROW($B$1:$B$272)-ROW($B$1)+1),ROWS($AA$25:AA27) ) ), "")} | AC27: {=IFERROR(INDEX($B$1:$B$272,SMALL(IF($C$1:$C$272=$O$19, ROW($B$1:$B$272)-ROW($B$1)+1),ROWS($AC$23:AC27) ) ), "")} | AE27: {=IFERROR(INDEX($B$1:$B$272,SMALL(IF($C$1:$C$272=$O$20, ROW($B$1:$B$272)-ROW($B$1)+1),ROWS($AE$26:AE27) ) ), "")} | AF27: {=IFERROR(INDEX($B$1:$B$272,SMALL(IF($C$1:$C$272=$O$22, ROW($B$1:$B$272)-ROW($B$1)+1),ROWS($AF$12:AF27) ) ), "")} | AG27: {=IFERROR(INDEX($B$1:$B$272,SMALL(IF($O$25=$C$1:$C$272,ROW($C$1:$C$272)-MIN(ROW($B$1:$B$272))+1,""), ROW()-17)),"")} | AH27: {=IFERROR(INDEX($B$1:$B$272,SMALL(IF($O$32=$C$1:$C$272,ROW($C$1:$C$272)-MIN(ROW($B$1:$B$272))+1,""), ROW()-12)),"")} | AI27: {=IFERROR(INDEX($B$1:$B$272,SMALL(IF($O$4=$C$1:$C$272,ROW($C$1:$C$272)-MIN(ROW($B$1:$B$272))+1,""), ROW()-1)),"")} | AJ27: {=IFERROR(INDEX($B$32:$B$646,SMALL(IF($O$4=$C$32:$C$646,ROW($C$32:$C$646)-MIN(ROW($B$32:$B$646))+1,""), ROW()-1)),"")}
O28: BB | P28: Baby Bundle Project | Q28: =COUNTIFS($F$5:$F$33,O28)+COUNTIFS($I$5:$I$33,O28) -> 0 | R28: ='[3]2025 Progress tracker'!$D$15 -> 0 | U28: hours | V28: 2.5 | W28: 5 | X28: 10 | AA28: {=IFERROR(INDEX($B$1:$B$272,SMALL(IF($C$1:$C$272=$O$26, ROW($B$1:$B$272)-ROW($B$1)+1),ROWS($AA$25:AA28) ) ), "")} | AC28: {=IFERROR(INDEX($B$1:$B$272,SMALL(IF($O$19=$C$1:$C$272,ROW($C$1:$C$272)-MIN(ROW($B$1:$B$272))+1,""), ROW()-21)),"")} | AE28: {=IFERROR(INDEX($B$1:$B$272,SMALL(IF($C$1:$C$272=$O$20, ROW($B$1:$B$272)-ROW($B$1)+1),ROWS($AE$26:AE28) ) ), "")} | AF28: ="Returns Exceptions"&" "&$X$48 -> Returns Exceptions estimate | AG28: {=IFERROR(INDEX($B$1:$B$272,SMALL(IF($O$25=$C$1:$C$272,ROW($C$1:$C$272)-MIN(ROW($B$1:$B$272))+1,""), ROW()-17)),"")} | AH28: {=IFERROR(INDEX($B$1:$B$272,SMALL(IF($O$32=$C$1:$C$272,ROW($C$1:$C$272)-MIN(ROW($B$1:$B$272))+1,""), ROW()-12)),"")} | AI28: {=IFERROR(INDEX($B$1:$B$272,SMALL(IF($O$4=$C$1:$C$272,ROW($C$1:$C$272)-MIN(ROW($B$1:$B$272))+1,""), ROW()-1)),"")} | AJ28: {=IFERROR(INDEX($B$32:$B$646,SMALL(IF($O$4=$C$32:$C$646,ROW($C$32:$C$646)-MIN(ROW($B$32:$B$646))+1,""), ROW()-1)),"")}
O29: WU | P29: Warehouse Utility | Q29: =COUNTIFS($F$5:$F$33,O29)+COUNTIFS($I$5:$I$33,O29) -> 0 | U29: region | V29: # pickers | W29: UPH | X29: estimate | AA29: {=IFERROR(INDEX($B$1:$B$272,SMALL(IF($C$1:$C$272=$O$26, ROW($B$1:$B$272)-ROW($B$1)+1),ROWS($AA$25:AA29) ) ), "")} | AC29: Aisle & DC Cleanup | AE29: {=IFERROR(INDEX($B$1:$B$272,SMALL(IF($C$1:$C$272=$O$20, ROW($B$1:$B$272)-ROW($B$1)+1),ROWS($AE$26:AE29) ) ), "")} | AF29: {=IFERROR(INDEX($B$1:$B$272,SMALL(IF($O$23=$C$1:$C$272,ROW($C$1:$C$272)-MIN(ROW($B$1:$B$272))+1,""), ROW()-26)),"")} | AG29: {=IFERROR(INDEX($B$1:$B$272,SMALL(IF($O$25=$C$1:$C$272,ROW($C$1:$C$272)-MIN(ROW($B$1:$B$272))+1,""), ROW()-17)),"")} | AH29: {=IFERROR(INDEX($B$1:$B$272,SMALL(IF($O$32=$C$1:$C$272,ROW($C$1:$C$272)-MIN(ROW($B$1:$B$272))+1,""), ROW()-12)),"")} | AI29: {=IFERROR(INDEX($B$1:$B$272,SMALL(IF($O$4=$C$1:$C$272,ROW($C$1:$C$272)-MIN(ROW($B$1:$B$272))+1,""), ROW()-1)),"")} | AJ29: {=IFERROR(INDEX($B$32:$B$646,SMALL(IF($O$4=$C$32:$C$646,ROW($C$32:$C$646)-MIN(ROW($B$32:$B$646))+1,""), ROW()-1)),"")}
O30: SL | P30: Support | Q30: =COUNTIFS($F$5:$F$33,O30)+COUNTIFS($I$5:$I$33,O30) -> 2 | U30: Picking- Bulk | V30: 20 | W30: 175 | X30: =W30*V30*$W$28 -> 17500 | AA30: {=IFERROR(INDEX($B$1:$B$272,SMALL(IF($C$1:$C$272=$O$26, ROW($B$1:$B$272)-ROW($B$1)+1),ROWS($AA$25:AA30) ) ), "")} | AC30: {=IFERROR(INDEX($B$1:$B$272,SMALL(IF($O$33=$C$1:$C$272,ROW($C$1:$C$272)-MIN(ROW($B$1:$B$272))+1,""), ROW()-26)),"")} | AE30: {=IFERROR(INDEX($B$1:$B$272,SMALL(IF($C$1:$C$272=$O$20, ROW($B$1:$B$272)-ROW($B$1)+1),ROWS($AE$26:AE30) ) ), "")} | AF30: {=IFERROR(INDEX($B$1:$B$272,SMALL(IF($O$23=$C$1:$C$272,ROW($C$1:$C$272)-MIN(ROW($B$1:$B$272))+1,""), ROW()-26)),"")} | AG30: {=IFERROR(INDEX($B$1:$B$272,SMALL(IF($O$25=$C$1:$C$272,ROW($C$1:$C$272)-MIN(ROW($B$1:$B$272))+1,""), ROW()-17)),"")} | AH30: {=IFERROR(INDEX($B$1:$B$272,SMALL(IF($O$32=$C$1:$C$272,ROW($C$1:$C$272)-MIN(ROW($B$1:$B$272))+1,""), ROW()-12)),"")} | AI30: {=IFERROR(INDEX($B$1:$B$272,SMALL(IF($O$4=$C$1:$C$272,ROW($C$1:$C$272)-MIN(ROW($B$1:$B$272))+1,""), ROW()-1)),"")} | AJ30: {=IFERROR(INDEX($B$32:$B$646,SMALL(IF($O$4=$C$32:$C$646,ROW($C$32:$C$646)-MIN(ROW($B$32:$B$646))+1,""), ROW()-1)),"")} | AL30: 2nd
O31: SP | P31: Special Projects | Q31: =COUNTIFS($F$5:$F$33,O31)+COUNTIFS($I$5:$I$33,O31) -> 0 | S31: =LOOKUP(U1,'Deployment needs'!$2:$2,'Deployment needs'!96:96) -> 0 | U31: Picking- Singles | V31: 0 | W31: 175 | X31: =W31*V31*$V$28 -> 0 | AA31: {=IFERROR(INDEX($B$1:$B$272,SMALL(IF($C$1:$C$272=$O$26, ROW($B$1:$B$272)-ROW($B$1)+1),ROWS($AA$25:AA31) ) ), "")} | AC31: {=IFERROR(INDEX($B$1:$B$272,SMALL(IF($O$33=$C$1:$C$272,ROW($C$1:$C$272)-MIN(ROW($B$1:$B$272))+1,""), ROW()-26)),"")} | AE31: {=IFERROR(INDEX($B$1:$B$272,SMALL(IF($C$1:$C$272=$O$20, ROW($B$1:$B$272)-ROW($B$1)+1),ROWS($AE$26:AE31) ) ), "")} | AF31: {=IFERROR(INDEX($B$1:$B$272,SMALL(IF($O$23=$C$1:$C$272,ROW($C$1:$C$272)-MIN(ROW($B$1:$B$272))+1,""), ROW()-26)),"")} | AG31: {=IFERROR(INDEX($B$1:$B$272,SMALL(IF($O$25=$C$1:$C$272,ROW($C$1:$C$272)-MIN(ROW($B$1:$B$272))+1,""), ROW()-17)),"")} | AH31: {=IFERROR(INDEX($B$1:$B$272,SMALL(IF($O$32=$C$1:$C$272,ROW($C$1:$C$272)-MIN(ROW($B$1:$B$272))+1,""), ROW()-12)),"")} | AI31: {=IFERROR(INDEX($B$1:$B$272,SMALL(IF($O$4=$C$1:$C$272,ROW($C$1:$C$272)-MIN(ROW($B$1:$B$272))+1,""), ROW()-1)),"")} | AJ31: {=IFERROR(INDEX($B$32:$B$646,SMALL(IF($O$4=$C$32:$C$646,ROW($C$32:$C$646)-MIN(ROW($B$32:$B$646))+1,""), ROW()-1)),"")}
B32: {=IFERROR(_xlfn.IFS(G5=0,"",G5>0,G5),"")} -> Deja Andersson | C32: {=IFERROR(_xlfn.IFS(I5=0,"",I5>0,I5),"")} -> SL | O32: I | P32: Inventory functions | Q32: =COUNTIFS($F$5:$F$33,O32)+COUNTIFS($I$5:$I$33,O32) -> 3 | S32: {=LOOKUP(U1,'Deployment needs'!$2:$2,('Deployment needs'!76:76+'Deployment needs'!89:89+'Deployment needs'!90:90))} -> 0.5 | AA32: Overstock Cycle Count | AB32: ="Overstock Putaway"&" "&T37 -> Overstock Putaway | AC32: {=IFERROR(INDEX($B$1:$B$272,SMALL(IF($O$33=$C$1:$C$272,ROW($C$1:$C$272)-MIN(ROW($B$1:$B$272))+1,""), ROW()-26)),"")} | AE32: {=IFERROR(INDEX($B$1:$B$272,SMALL(IF($C$1:$C$272=$O$20, ROW($B$1:$B$272)-ROW($B$1)+1),ROWS($AE$26:AE32) ) ), "")} | AF32: {=IFERROR(INDEX($B$1:$B$272,SMALL(IF($O$23=$C$1:$C$272,ROW($C$1:$C$272)-MIN(ROW($B$1:$B$272))+1,""), ROW()-26)),"")} | AG32: {=IFERROR(INDEX($B$1:$B$272,SMALL(IF($O$25=$C$1:$C$272,ROW($C$1:$C$272)-MIN(ROW($B$1:$B$272))+1,""), ROW()-17)),"")} | AH32: {=IFERROR(INDEX($B$1:$B$272,SMALL(IF($O$32=$C$1:$C$272,ROW($C$1:$C$272)-MIN(ROW($B$1:$B$272))+1,""), ROW()-12)),"")} | AI32: {=IFERROR(INDEX($B$1:$B$272,SMALL(IF($O$4=$C$1:$C$272,ROW($C$1:$C$272)-MIN(ROW($B$1:$B$272))+1,""), ROW()-1)),"")} | AJ32: {=IFERROR(INDEX($B$32:$B$646,SMALL(IF($O$4=$C$32:$C$646,ROW($C$32:$C$646)-MIN(ROW($B$32:$B$646))+1,""), ROW()-1)),"")}
B33: {=IFERROR(_xlfn.IFS(G6=0,"",G6>0,G6),"")} -> Eumary Quinones | C33: {=IFERROR(_xlfn.IFS(I6=0,"",I6>0,I6),"")} -> I | E33: =COUNTIFS(E5:E32,"*") -> 23 | F33: =COUNTIFS(F5:F32,$O$38)+COUNTIFS(F5:F32,$O$39)+COUNTIFS(F5:F32,$O$40)+COUNTIFS(F5:F32,$O$41)+COUNTIFS(F5:F32,$O$42)+COUNTIFS(F5:F32,$O$43)+COUNTIFS(F5:F32,$O$44)+COUNTIFS(F5:F32,$O$45)+COUNTIFS(F5:F32,$O$198) -> 20 | G33: =COUNTIFS(G5:G32,"*") -> 12 | I33: =COUNTIFS(I5:I32,$O$38)+COUNTIFS(I5:I32,$O$39)+COUNTIFS(I5:I32,$O$40)+COUNTIFS(I5:I32,$O$41)+COUNTIFS(I5:I32,$O$42)+COUNTIFS(I5:I32,$O$43)+COUNTIFS(I5:I32,$O$44)+COUNTIFS(I5:I32,$O$45)+COUNTIFS(F5:I32,$O$198) -> 10 | J33: =COUNTIFS(L5:L32,"*") -> 0 | L33: =COUNTIFS(L5:L33,$O$77)+COUNTIFS(L5:L33,$O$78)+COUNTIFS(L5:L33,$O$194)+COUNTIFS(L5:L33,$O$195)+COUNTIFS(L5:L33,$O$196)+COUNTIFS(L5:L33,$O$197)+COUNTIFS(L5:L33,$O$199)+COUNTIFS(L5:L33,$O$200) -> 0 | O33: W | P33: Warehouse Cleaning | Q33: =COUNTIFS($F$5:$F$33,O33)+COUNTIFS($I$5:$I$33,O33) -> 0 | S33: =LOOKUP(U1,'Deployment needs'!$2:$2,'Deployment needs'!77:77) -> 1 | U33: TOTAL | X33: =SUM(X30:X32) -> 17500 | AA33: {=IFERROR(INDEX($B$1:$B$272,SMALL(IF($O$17=$C$1:$C$272,ROW($C$1:$C$272)-MIN(ROW($B$1:$B$272))+1,""), ROW()-31)),"")} | AB33: {=IFERROR(INDEX($B$1:$B$272,SMALL(IF($O$18=$C$1:$C$272,ROW($C$1:$C$272)-MIN(ROW($B$1:$B$272))+1,""), ROW()-31)),"")} | AC33: {=IFERROR(INDEX($B$1:$B$272,SMALL(IF($O$33=$C$1:$C$272,ROW($C$1:$C$272)-MIN(ROW($B$1:$B$272))+1,""), ROW()-26)),"")} | AE33: {=IFERROR(INDEX($B$1:$B$272,SMALL(IF($O$20=$C$1:$C$272,ROW($C$1:$C$272)-MIN(ROW($B$1:$B$272))+1,""), ROW()-20)),"")} | AF33: {=IFERROR(INDEX($B$1:$B$272,SMALL(IF($O$23=$C$1:$C$272,ROW($C$1:$C$272)-MIN(ROW($B$1:$B$272))+1,""), ROW()-26)),"")} | AG33: {=IFERROR(INDEX($B$1:$B$272,SMALL(IF($O$25=$C$1:$C$272,ROW($C$1:$C$272)-MIN(ROW($B$1:$B$272))+1,""), ROW()-17)),"")} | AH33: {=IFERROR(INDEX($B$1:$B$272,SMALL(IF($O$32=$C$1:$C$272,ROW($C$1:$C$272)-MIN(ROW($B$1:$B$272))+1,""), ROW()-12)),"")} | AI33: {=IFERROR(INDEX($B$1:$B$272,SMALL(IF($O$4=$C$1:$C$272,ROW($C$1:$C$272)-MIN(ROW($B$1:$B$272))+1,""), ROW()-1)),"")} | AJ33: {=IFERROR(INDEX($B$32:$B$646,SMALL(IF($O$4=$C$32:$C$646,ROW($C$32:$C$646)-MIN(ROW($B$32:$B$646))+1,""), ROW()-1)),"")}
B34: {=IFERROR(_xlfn.IFS(G7=0,"",G7>0,G7),"")} -> Sunia Hernandez | C34: {=IFERROR(_xlfn.IFS(I7=0,"",I7>0,I7),"")} -> x | P34: Total | Q34: =F36-F33-I33 -> 5 | S34: =SUM(S3:S33) -> 23.431665 | AA34: {=IFERROR(INDEX($B$1:$B$272,SMALL(IF($O$17=$C$1:$C$272,ROW($C$1:$C$272)-MIN(ROW($B$1:$B$272))+1,""), ROW()-31)),"")} | AB34: {=IFERROR(INDEX($B$1:$B$272,SMALL(IF($O$18=$C$1:$C$272,ROW($C$1:$C$272)-MIN(ROW($B$1:$B$272))+1,""), ROW()-31)),"")} | AC34: {=IFERROR(INDEX($B$1:$B$272,SMALL(IF($O$33=$C$1:$C$272,ROW($C$1:$C$272)-MIN(ROW($B$1:$B$272))+1,""), ROW()-26)),"")} | AE34: Warehouse Utility | AF34: {=IFERROR(INDEX($B$1:$B$272,SMALL(IF($O$23=$C$1:$C$272,ROW($C$1:$C$272)-MIN(ROW($B$1:$B$272))+1,""), ROW()-26)),"")} | AG34: {=IFERROR(INDEX($B$1:$B$272,SMALL(IF($O$25=$C$1:$C$272,ROW($C$1:$C$272)-MIN(ROW($B$1:$B$272))+1,""), ROW()-17)),"")} | AH34: {=IFERROR(INDEX($B$1:$B$272,SMALL(IF($O$32=$C$1:$C$272,ROW($C$1:$C$272)-MIN(ROW($B$1:$B$272))+1,""), ROW()-12)),"")} | AI34: {=IFERROR(INDEX($B$1:$B$272,SMALL(IF($O$4=$C$1:$C$272,ROW($C$1:$C$272)-MIN(ROW($B$1:$B$272))+1,""), ROW()-1)),"")} | AJ34: {=IFERROR(INDEX($B$32:$B$646,SMALL(IF($O$4=$C$32:$C$646,ROW($C$32:$C$646)-MIN(ROW($B$32:$B$646))+1,""), ROW()-1)),"")}
B35: {=IFERROR(_xlfn.IFS(G8=0,"",G8>0,G8),"")} -> Orlis Daniel Zaldivar | C35: {=IFERROR(_xlfn.IFS(I8=0,"",I8>0,I8),"")} -> x | E35: Headcount | F35: =E33+G33 -> 35 | P35: Plan staffing | Q35: =F36 -> 35 | S35: =LOOKUP(U1,'Deployment needs'!$2:$2,'Deployment needs'!52:52) -> 23.431665 | AA35: {=IFERROR(INDEX($B$1:$B$272,SMALL(IF($O$17=$C$1:$C$272,ROW($C$1:$C$272)-MIN(ROW($B$1:$B$272))+1,""), ROW()-31)),"")} | AB35: {=IFERROR(INDEX($B$1:$B$272,SMALL(IF($O$18=$C$1:$C$272,ROW($C$1:$C$272)-MIN(ROW($B$1:$B$272))+1,""), ROW()-31)),"")} | AC35: {=IFERROR(INDEX($B$1:$B$272,SMALL(IF($O$33=$C$1:$C$272,ROW($C$1:$C$272)-MIN(ROW($B$1:$B$272))+1,""), ROW()-26)),"")} | AE35: {=IFERROR(INDEX($B$1:$B$272,SMALL(IF($O$29=$C$1:$C$272,ROW($C$1:$C$272)-MIN(ROW($B$1:$B$272))+1,""), ROW()-33)),"")} | AF35: {=IFERROR(INDEX($B$1:$B$272,SMALL(IF($O$23=$C$1:$C$272,ROW($C$1:$C$272)-MIN(ROW($B$1:$B$272))+1,""), ROW()-26)),"")} | AG35: {=IFERROR(INDEX($B$1:$B$272,SMALL(IF($O$25=$C$1:$C$272,ROW($C$1:$C$272)-MIN(ROW($B$1:$B$272))+1,""), ROW()-17)),"")} | AH35: {=IFERROR(INDEX($B$1:$B$272,SMALL(IF($O$32=$C$1:$C$272,ROW($C$1:$C$272)-MIN(ROW($B$1:$B$272))+1,""), ROW()-12)),"")} | AI35: {=IFERROR(INDEX($B$1:$B$272,SMALL(IF($O$4=$C$1:$C$272,ROW($C$1:$C$272)-MIN(ROW($B$1:$B$272))+1,""), ROW()-1)),"")} | AJ35: {=IFERROR(INDEX($B$32:$B$646,SMALL(IF($O$4=$C$32:$C$646,ROW($C$32:$C$646)-MIN(ROW($B$32:$B$646))+1,""), ROW()-1)),"")}
B36: {=IFERROR(_xlfn.IFS(G9=0,"",G9>0,G9),"")} -> Rolexis Lopez Diaz | C36: {=IFERROR(_xlfn.IFS(I9=0,"",I9>0,I9),"")} -> x | E36: FTE | F36: 35 | P36: Total Absent | Q36: =F33+I33 -> 30 | U36: SLA other areas | AA36: {=IFERROR(INDEX($B$1:$B$272,SMALL(IF($O$17=$C$1:$C$272,ROW($C$1:$C$272)-MIN(ROW($B$1:$B$272))+1,""), ROW()-31)),"")} | AB36: {=IFERROR(INDEX($B$1:$B$272,SMALL(IF($O$18=$C$1:$C$272,ROW($C$1:$C$272)-MIN(ROW($B$1:$B$272))+1,""), ROW()-31)),"")} | AC36: {=IFERROR(INDEX($B$1:$B$272,SMALL(IF($O$33=$C$1:$C$272,ROW($C$1:$C$272)-MIN(ROW($B$1:$B$272))+1,""), ROW()-26)),"")} | AE36: {=IFERROR(INDEX($B$1:$B$272,SMALL(IF($O$29=$C$1:$C$272,ROW($C$1:$C$272)-MIN(ROW($B$1:$B$272))+1,""), ROW()-33)),"")} | AF36: {=IFERROR(INDEX($B$1:$B$272,SMALL(IF($O$23=$C$1:$C$272,ROW($C$1:$C$272)-MIN(ROW($B$1:$B$272))+1,""), ROW()-26)),"")} | AG36: {=IFERROR(INDEX($B$1:$B$272,SMALL(IF($O$25=$C$1:$C$272,ROW($C$1:$C$272)-MIN(ROW($B$1:$B$272))+1,""), ROW()-17)),"")} | AH36: {=IFERROR(INDEX($B$1:$B$272,SMALL(IF($O$32=$C$1:$C$272,ROW($C$1:$C$272)-MIN(ROW($B$1:$B$272))+1,""), ROW()-12)),"")} | AI36: {=IFERROR(INDEX($B$1:$B$272,SMALL(IF($O$4=$C$1:$C$272,ROW($C$1:$C$272)-MIN(ROW($B$1:$B$272))+1,""), ROW()-1)),"")} | AJ36: {=IFERROR(INDEX($B$32:$B$646,SMALL(IF($O$4=$C$32:$C$646,ROW($C$32:$C$646)-MIN(ROW($B$32:$B$646))+1,""), ROW()-1)),"")}
B37: {=IFERROR(_xlfn.IFS(G10=0,"",G10>0,G10),"")} -> Joaquin Lopez Enrique | C37: {=IFERROR(_xlfn.IFS(I10=0,"",I10>0,I10),"")} -> x | P37: Absent % | Q37: =Q34/Q35 -> 0.14285714 | U37: Area | V37: # folks | W37: UPH | X37: SLA | AA37: {=IFERROR(INDEX($B$1:$B$272,SMALL(IF($O$17=$C$1:$C$272,ROW($C$1:$C$272)-MIN(ROW($B$1:$B$272))+1,""), ROW()-31)),"")} | AB37: {=IFERROR(INDEX($B$1:$B$272,SMALL(IF($O$18=$C$1:$C$272,ROW($C$1:$C$272)-MIN(ROW($B$1:$B$272))+1,""), ROW()-31)),"")} | AC37: {=IFERROR(INDEX($B$1:$B$272,SMALL(IF($O$33=$C$1:$C$272,ROW($C$1:$C$272)-MIN(ROW($B$1:$B$272))+1,""), ROW()-26)),"")} | AE37: {=IFERROR(INDEX($B$1:$B$272,SMALL(IF($O$29=$C$1:$C$272,ROW($C$1:$C$272)-MIN(ROW($B$1:$B$272))+1,""), ROW()-33)),"")} | AF37: {=IFERROR(INDEX($B$1:$B$272,SMALL(IF($O$23=$C$1:$C$272,ROW($C$1:$C$272)-MIN(ROW($B$1:$B$272))+1,""), ROW()-26)),"")} | AG37: {=IFERROR(INDEX($B$1:$B$272,SMALL(IF($O$25=$C$1:$C$272,ROW($C$1:$C$272)-MIN(ROW($B$1:$B$272))+1,""), ROW()-17)),"")} | AH37: {=IFERROR(INDEX($B$1:$B$272,SMALL(IF($O$32=$C$1:$C$272,ROW($C$1:$C$272)-MIN(ROW($B$1:$B$272))+1,""), ROW()-12)),"")} | AI37: {=IFERROR(INDEX($B$1:$B$272,SMALL(IF($O$4=$C$1:$C$272,ROW($C$1:$C$272)-MIN(ROW($B$1:$B$272))+1,""), ROW()-1)),"")} | AJ37: {=IFERROR(INDEX($B$32:$B$646,SMALL(IF($O$4=$C$32:$C$646,ROW($C$32:$C$646)-MIN(ROW($B$32:$B$646))+1,""), ROW()-1)),"")} | AL37: Rotationreturns putaway
B38: {=IFERROR(_xlfn.IFS(G11=0,"",G11>0,G11),"")} -> Dora Lopez (Alicia) | C38: {=IFERROR(_xlfn.IFS(I11=0,"",I11>0,I11),"")} -> x | O38: NC | P38: NC/NS | Q38: =COUNTIFS($F$5:$M$32,O38) -> 0 | U38: Returns Processing | V38: =Q22-0.5 -> -0.5 | W38: =Narvar -> 34 | X38: =(W38*V38*$Y$28) -> 0 | AA38: {=IFERROR(INDEX($B$1:$B$272,SMALL(IF($O$17=$C$1:$C$272,ROW($C$1:$C$272)-MIN(ROW($B$1:$B$272))+1,""), ROW()-31)),"")} | AB38: {=IFERROR(INDEX($B$1:$B$272,SMALL(IF($O$18=$C$1:$C$272,ROW($C$1:$C$272)-MIN(ROW($B$1:$B$272))+1,""), ROW()-31)),"")} | AC38: {=IFERROR(INDEX($B$1:$B$272,SMALL(IF($O$33=$C$1:$C$272,ROW($C$1:$C$272)-MIN(ROW($B$1:$B$272))+1,""), ROW()-26)),"")} | AE38: {=IFERROR(INDEX($B$1:$B$272,SMALL(IF($O$29=$C$1:$C$272,ROW($C$1:$C$272)-MIN(ROW($B$1:$B$272))+1,""), ROW()-33)),"")} | AF38: {=IFERROR(INDEX($B$1:$B$272,SMALL(IF($O$23=$C$1:$C$272,ROW($C$1:$C$272)-MIN(ROW($B$1:$B$272))+1,""), ROW()-26)),"")} | AG38: {=IFERROR(INDEX($B$1:$B$272,SMALL(IF($O$25=$C$1:$C$272,ROW($C$1:$C$272)-MIN(ROW($B$1:$B$272))+1,""), ROW()-17)),"")} | AH38: {=IFERROR(INDEX($B$1:$B$272,SMALL(IF($O$32=$C$1:$C$272,ROW($C$1:$C$272)-MIN(ROW($B$1:$B$272))+1,""), ROW()-12)),"")} | AI38: {=IFERROR(INDEX($B$1:$B$272,SMALL(IF($O$4=$C$1:$C$272,ROW($C$1:$C$272)-MIN(ROW($B$1:$B$272))+1,""), ROW()-1)),"")} | AJ38: {=IFERROR(INDEX($B$32:$B$646,SMALL(IF($O$4=$C$32:$C$646,ROW($C$32:$C$646)-MIN(ROW($B$32:$B$646))+1,""), ROW()-1)),"")} | AL38: Groups | AM38: Sunday | AN38: Monday | AO38: Tuesday | AP38: Wednesday | AQ38: Thursday | AR38: Friday | AS38: Saturday
B39: {=IFERROR(_xlfn.IFS(G12=0,"",G12>0,G12),"")} -> Sonia Lopez Medina | C39: {=IFERROR(_xlfn.IFS(I12=0,"",I12>0,I12),"")} -> x | K39: Potencial deployment GIG | O39: Call | P39: Call in | Q39: =COUNTIFS($F$5:$M$32,O39) -> 0 | U39: Returns Exceptions | V39: =Q23 -> 0 | W39: =Exceptions -> 25 | X39: =(W39*V39*(2)) -> 0 | AL39: 1st
B40: {=IFERROR(_xlfn.IFS(G13=0,"",G13>0,G13),"")} -> Josefa Martinez | C40: {=IFERROR(_xlfn.IFS(I13=0,"",I13>0,I13),"")} -> x | K40: Compactor | L40: 0 | O40: VTO | P40: VTO | Q40: =COUNTIFS($F$5:$M$32,O40) -> 0 | U40: Returns put-away | V40: =Q25 -> 0 | W40: =Returns_put_away -> 100 | X40: =(W40*V40*($Y$28-1)) -> 0
B41: {=IFERROR(_xlfn.IFS(G14=0,"",G14>0,G14),"")} -> Ernesto Reyes Perez | C41: {=IFERROR(_xlfn.IFS(I14=0,"",I14>0,I14),"")} -> x | K41: Trash | L41: 0 | O41: PTO | P41: PTO | Q41: =COUNTIFS($F$5:$M$32,O41) -> 0 | U41: Receiving | V41: =Q26 -> 0 | W41: =Receiving -> 75 | X41: =(W41*V41*$Y$28)/2.45 -> 0
B42: {=IFERROR(_xlfn.IFS(G15=0,"",G15>0,G15),"")} -> Yordany Miranda | C42: {=IFERROR(_xlfn.IFS(I15=0,"",I15>0,I15),"")} -> x | K42: Cartbulding | L42: 0 | O42: VOL | P42: Volunteer | Q42: =COUNTIFS($F$5:$M$32,O42) -> 0 | U42: Resets | V42: =Q11 -> 0 | W42: =Resets_per_hour -> 20 | X42: =(W42*V42*$Y$28) -> 0
B43: {=IFERROR(_xlfn.IFS(G16=0,"",G16>0,G16),"")} -> Carlos Molina | C43: {=IFERROR(_xlfn.IFS(I16=0,"",I16>0,I16),"")} -> x | K43: Taper | L43: 0 | O43: L | P43: leave early/late arrival | Q43: =COUNTIFS($F$5:$M$32,O43) -> 0 | U43: Bander | V43: =Q9 -> 0 | W43: =Autobagger_Bander -> 120 | X43: =(W43*V43*$Y$28)/2 -> 0 | AA43: NCNS | AB43: Call in | AC43: FMLA | AE43: PTO | AF43: VTO | AG43: Leave Early | AH43: No schedule to work | AI43: Volunteer
K44: Truck | L44: 0 | O44: FMLA | P44: FMLA | Q44: =COUNTIFS($F$5:$M$32,O44) -> 0 | U44: Autobagger | V44: =Q10 -> 0 | W44: =Autobagger_Operator -> 600 | X44: =(W44*V44*$Y$28) -> 0 | Z44: 1 | AA44: {=_xlfn._xlws.FILTER($B$1:$B$107, $C$1:$C$107=$O$38, "")} | AB44: {=_xlfn._xlws.FILTER($B$1:$B$107, $C$1:$C$107=$O$39, "")} | AC44: {=_xlfn._xlws.FILTER($B$1:$B$107, $C$1:$C$107=$O$44, "")} | AE44: {=_xlfn._xlws.FILTER($B$1:$B$107, $C$1:$C$107=$O$41, "")} | AG44: {=_xlfn._xlws.FILTER($B$1:$B$107, $C$1:$C$107=$O$43, "")} | AH44: {=_xlfn._xlws.FILTER($B$1:$B$107, $C$1:$C$107=$O$45, "")} -> Chrissy Parisek | AI44: {=_xlfn._xlws.FILTER($B$1:$B$107, $C$1:$C$107=$O$42, "")}
K45: Bander | L45: 4 | O45: X | P45: Not Schedule to work | Q45: =COUNTIFS($F$5:$M$32,O45) -> 30 | U45: Overstock putaway | V45: =Q18 -> 0 | W45: =Overstock -> 50 | X45: =(W45*V45*$Y$28) -> 0 | Z45: 2 | AH45: Yasmin Montero
K46: Total | L46: =SUM(L40:L45) -> 4 | U46: Replen Pull | V46: =Q19 -> 0 | W46: =Replenishment_pull -> 45 | X46: =(W46*V46*$Y$28) -> 0 | Z46: 3 | AH46: Annaliet Rodriguez Perez
U47: Replen Throw | V47: =Q20 -> 0 | W47: =Replenishment_throw -> 35 | X47: =(W47*V47*$Y$28) -> 0 | Z47: 4 | AH47: Damaris Curbelo | AL47: 2nd
U48: region | V48: # pickers | W48: UPH | X48: estimate | Z48: 5 | AH48: Esther Fonseca
U49: Picking- Bulk | V49: =Q26 -> 0 | W49: 160 | X49: =W49*V49*$W$25 -> 0 | Z49: 6 | AH49: Yordanka Manzanares
U50: Picking- Singles | V50: =Q27 -> 0 | W50: 200 | X50: =W50*V50*$Y$25/2 -> 0 | Z50: 7 | AH50: Jackie Gomez
Z51: 8 | AH51: Madelayne Oduardo
U52: TOTAL | X52: =SUM(X49:X51) -> 0 | Z52: 9 | AH52: Roxana Lloret
Z53: 10 | AH53: Shvodra Anderson
Z54: 11 | AH54: Laura Gonzalez Bustamante
V55: Average UPH | W55: Employee count | X55: Expected hours | Y55: Projected 1st Shift | Z55: 12 | AH55: Mbaya Kapita
U56: Veterans | V56: 180 | W56: 0 | X56: 0 | Y56: =V56*W56*X56 -> 0 | Z56: 13 | AH56: Tamara Izada Aguado
U57: New Hires | V57: 150 | W57: 20 | X57: 8 | Y57: =V57*W57*X57 -> 24000 | Z57: 14 | AH57: Iraldo Rodriguez
X58: Total | Y58: =SUM(Y56:Y57) -> 24000 | Z58: 15 | AH58: Jose Posse
Z59: 16 | AH59: John Franco Morenos Rosales
U60: Leave early | V60: 170 | W60: 0 | X60: 0 | Y60: =V60*X60 -> 0 | AH60: Sunia Hernandez
U61: Absents | V61: 160 | W61: 5 | X61: 10 | Y61: =V61*W61*X61 -> 8000 | AH61: Orlis Daniel Zaldivar
U62: System Downtime | Y62: =V62*W62*X62 -> 0 | AH62: Rolexis Lopez Diaz
X63: Units Lost | Y63: =SUM(Y60:Y62) -> 8000 | AH63: Joaquin Lopez Enrique
AH64: Dora Lopez (Alicia)
X65: Total Units | Y65: =Y58-Y63 -> 16000 | AH65: Sonia Lopez Medina
AH66: Josefa Martinez
AH67: Ernesto Reyes Perez
AH68: Yordany Miranda
AH69: Carlos Molina
U222: Average UPH | V222: Employee count | W222: Expected hours | X222: Projected 1st Shift
T223: Veterans | U223: 180 | V223: 0 | W223: 0 | X223: =U223*V223*W223 -> 0
T224: New Hires | U224: 150 | V224: 20 | W224: 8 | X224: =U224*V224*W224 -> 24000
W225: Total | X225: =SUM(X223:X224) -> 24000
T227: Leave early | U227: 170 | V227: 0 | W227: 0 | X227: =U227*W227 -> 0
T228: Absents | U228: 160 | V228: 5 | W228: 10 | X228: =U228*V228*W228 -> 8000
T229: System Downtime | X229: =U229*V229*W229 -> 0
W230: Units Lost | X230: =SUM(X227:X229) -> 8000
W232: Total Units | X232: =X225-X230 -> 16000
B426: ='Wknd Shift'!A129 -> 0 | C426: ='Wknd Shift'!B126 -> 0
B427: ='Wknd Shift'!A130 -> 0 | C427: ='Wknd Shift'!B127 -> 0
B428: ='Wknd Shift'!A131 -> 0 | C428: ='Wknd Shift'!B128 -> 0
B429: ='Wknd Shift'!A132 -> 0 | C429: ='Wknd Shift'!B129 -> 0
B430: ='Wknd Shift'!A133 -> 0 | C430: ='Wknd Shift'!B130 -> 0
B431: ='Wknd Shift'!A134 -> 0 | C431: ='Wknd Shift'!B131 -> 0
B432: ='Wknd Shift'!A135 -> 0 | C432: ='Wknd Shift'!B132 -> 0
B433: ='Wknd Shift'!A136 -> 0 | C433: ='Wknd Shift'!B133 -> 0
B434: ='Wknd Shift'!A137 -> 0 | C434: ='Wknd Shift'!B134 -> 0
B435: ='Wknd Shift'!A138 -> 0 | C435: ='Wknd Shift'!B135 -> 0
B436: ='Wknd Shift'!A139 -> 0 | C436: ='Wknd Shift'!B136 -> 0
B437: ='Wknd Shift'!A140 -> 0 | C437: ='Wknd Shift'!B137 -> 0
... B451: ='Wknd Shift'!A154 -> 0 | C451: ='Wknd Shift'!B151 -> 0

Sheet 1st Shift
B1: {=IFERROR(_xlfn.IFS(E5=0,"",E5>0,E5),"")} -> Maria Carrasco-DS | C1: {=IFERROR(_xlfn.IFS(F5=0,"",F5>0,F5),"")} -> sl | E1: 1st SHIFT DEPLOYMENT | O1: 1st shift | U1: =TODAY() -> 46189 | Z1: Outbound | AA1: Cart Building | AB1: AB Super User | AC1: AB Bander | AE1: Shipping | AF1: Taper | AG1: Special Projects | AH1: Training | AI1: ="Picking"&" "&COUNTA(AI2:AI37)-COUNTBLANK(AI2:AI37) -> Picking 0 | AJ1: ="Picking"&" "&COUNTA(AJ2:AJ37)-COUNTBLANK(AJ2:AJ37) -> Picking 0 | AV1: Emplyee | AW1: Day | AX1: Task
B2: {=IFERROR(_xlfn.IFS(E6=0,"",E6>0,E6),"")} -> Brandee Foster- IL | C2: {=IFERROR(_xlfn.IFS(F6=0,"",F6>0,F6),"")} -> I | O2: Key | P2: Function | Q2: =TODAY() -> 46189 | R2: Work | S2: GM Plan | AA2: {=IFERROR(INDEX($B$1:$B$272,SMALL(IF($O$3=$C$1:$C$272,ROW($C$1:$C$272)-MIN(ROW($B$1:$B$272))+1,""), ROW()-1)),"")} -> Roxana Lloret | AB2: {=IFERROR(INDEX($B$1:$B$272,SMALL(IF($O$10=$C$1:$C$272,ROW($C$1:$C$272)-MIN(ROW($B$1:$B$272))+1,""), ROW()-1)),"")} -> Jose Miro Quintana | AC2: {=IFERROR(INDEX($B$1:$B$272,SMALL(IF($O$9=$C$1:$C$272,ROW($C$1:$C$272)-MIN(ROW($B$1:$B$272))+1,""), ROW()-1)),"")} -> Damaris Curbelo | AE2: {=IFERROR(INDEX($B$1:$B$272,SMALL(IF($O$6=$C$1:$C$272,ROW($C$1:$C$272)-MIN(ROW($B$1:$B$272))+1,""), ROW()-1)),"")} | AF2: {=IFERROR(INDEX($B$1:$B$272,SMALL(IF($O$8=$C$1:$C$272,ROW($C$1:$C$272)-MIN(ROW($B$1:$B$272))+1,""), ROW()-1)),"")} | AG2: {=IFERROR(INDEX($B$1:$B$272,SMALL(IF($O$31=$C$1:$C$272,ROW($C$1:$C$272)-MIN(ROW($B$1:$B$272))+1,""), ROW()-1)),"")} | AH2: {=IFERROR(INDEX($B$1:$B$272,SMALL(IF($O$21=$C$1:$C$272,ROW($C$1:$C$272)-MIN(ROW($B$1:$B$272))+1,""), ROW()-1)),"")} -> Iraldo Rodriguez | AI2: {=IFERROR(INDEX($B$1:$B$30,SMALL(IF($O$4=$C$1:$C$30,ROW($C$1:$C$30)-MIN(ROW($B$1:$B$30))+1,""), ROW()-1)),"")} | AJ2: {=IFERROR(INDEX($B$30:$B$646,SMALL(IF($O$4=$C$30:$C$646,ROW($C$30:$C$646)-MIN(ROW($B$30:$B$646))+1,""), ROW()-1)),"")} | AL2: Bander | AV2: Monday Lunes | AW2: Monday | AX2: Throw
B3: {=IFERROR(_xlfn.IFS(E7=0,"",E7>0,E7),"")} -> Ailin Reynaldo | C3: {=IFERROR(_xlfn.IFS(F7=0,"",F7>0,F7),"")} -> i | E3: Hanna employees | J3: Sup Notes | O3: CB | P3: Cartbuilding | Q3: =COUNTIFS($F$5:$F$664,O3)+COUNTIFS($I$5:$I$664,O3) -> 1 | R3: =V8 -> 1921 | S3: =LOOKUP(U1,'Deployment needs'!$2:$2,'Deployment needs'!58:58) -> 0.4837963 | U3: DC Daily Goal | V3: =LOOKUP(U1,'Deployment needs'!2:2,'Deployment needs'!5:5) -> 13000 | AA3: {=IFERROR(INDEX($B$1:$B$272,SMALL(IF($O$3=$C$1:$C$272,ROW($C$1:$C$272)-MIN(ROW($B$1:$B$272))+1,""), ROW()-1)),"")} | AB3: {=IFERROR(INDEX($B$1:$B$272,SMALL(IF($O$10=$C$1:$C$272,ROW($C$1:$C$272)-MIN(ROW($B$1:$B$272))+1,""), ROW()-1)),"")} | AC3: {=IFERROR(INDEX($B$1:$B$272,SMALL(IF($O$9=$C$1:$C$272,ROW($C$1:$C$272)-MIN(ROW($B$1:$B$272))+1,""), ROW()-1)),"")} -> Dania Curbelo | AE3: {=IFERROR(INDEX($B$1:$B$272,SMALL(IF($O$6=$C$1:$C$272,ROW($C$1:$C$272)-MIN(ROW($B$1:$B$272))+1,""), ROW()-1)),"")} | AF3: {=IFERROR(INDEX($B$1:$B$272,SMALL(IF($O$8=$C$1:$C$272,ROW($C$1:$C$272)-MIN(ROW($B$1:$B$272))+1,""), ROW()-1)),"")} | AG3: {=IFERROR(INDEX($B$1:$B$272,SMALL(IF($O$31=$C$1:$C$272,ROW($C$1:$C$272)-MIN(ROW($B$1:$B$272))+1,""), ROW()-1)),"")} | AH3: {=IFERROR(INDEX($B$1:$B$272,SMALL(IF($O$21=$C$1:$C$272,ROW($C$1:$C$272)-MIN(ROW($B$1:$B$272))+1,""), ROW()-1)),"")} -> John Franco Morenos Rosales | AI3: {=IFERROR(INDEX($B$1:$B$30,SMALL(IF($O$4=$C$1:$C$30,ROW($C$1:$C$30)-MIN(ROW($B$1:$B$30))+1,""), ROW()-1)),"")} | AJ3: {=IFERROR(INDEX($B$30:$B$646,SMALL(IF($O$4=$C$30:$C$646,ROW($C$30:$C$646)-MIN(ROW($B$30:$B$646))+1,""), ROW()-1)),"")} | AL3: Groups | AM3: Sunday | AN3: Monday | AO3: Tuesday | AP3: Wednesday | AQ3: Thursday | AR3: Friday | AS3: Saturday | AW3: Tuesday | AX3: Pull
B4: {=IFERROR(_xlfn.IFS(E8=0,"",E8>0,E8),"")} -> Chrissy Parisek | C4: {=IFERROR(_xlfn.IFS(F8=0,"",F8>0,F8),"")} -> RN | E4: Hanna Names | F4: Task | G4: Hanna Names | I4: area | J4: Names | L4: Task | O4: P | P4: Picking- Bulk | Q4: =COUNTIFS($F$5:$F$664,O4)+COUNTIFS($I$5:$I$664,O4) -> 0 | R4: =V11 -> 1086 | S4: =LOOKUP(U1,'Deployment needs'!$2:$2,'Deployment needs'!54:54)+LOOKUP(U1,'Deployment needs'!$2:$2,'Deployment needs'!55:55) -> 4.0689815 | U4: 1st Shift Goal | V4: =LOOKUP(U1,'Deployment needs'!$2:$2,'Deployment needs'!$53:$53) -> 7150 | AA4: {=IFERROR(INDEX($B$1:$B$272,SMALL(IF($O$3=$C$1:$C$272,ROW($C$1:$C$272)-MIN(ROW($B$1:$B$272))+1,""), ROW()-1)),"")} | AB4: {=IFERROR(INDEX($B$1:$B$272,SMALL(IF($O$10=$C$1:$C$272,ROW($C$1:$C$272)-MIN(ROW($B$1:$B$272))+1,""), ROW()-1)),"")} | AC4: {=IFERROR(INDEX($B$1:$B$272,SMALL(IF($O$9=$C$1:$C$272,ROW($C$1:$C$272)-MIN(ROW($B$1:$B$272))+1,""), ROW()-1)),"")} -> Shvodra Anderson | AE4: {=IFERROR(INDEX($B$1:$B$272,SMALL(IF($O$6=$C$1:$C$272,ROW($C$1:$C$272)-MIN(ROW($B$1:$B$272))+1,""), ROW()-1)),"")} | AF4: {=IFERROR(INDEX($B$1:$B$272,SMALL(IF($O$8=$C$1:$C$272,ROW($C$1:$C$272)-MIN(ROW($B$1:$B$272))+1,""), ROW()-1)),"")} | AG4: {=IFERROR(INDEX($B$1:$B$272,SMALL(IF($O$31=$C$1:$C$272,ROW($C$1:$C$272)-MIN(ROW($B$1:$B$272))+1,""), ROW()-1)),"")} | AH4: {=IFERROR(INDEX($B$1:$B$272,SMALL(IF($O$21=$C$1:$C$272,ROW($C$1:$C$272)-MIN(ROW($B$1:$B$272))+1,""), ROW()-1)),"")} | AI4: {=IFERROR(INDEX($B$1:$B$30,SMALL(IF($O$4=$C$1:$C$30,ROW($C$1:$C$30)-MIN(ROW($B$1:$B$30))+1,""), ROW()-1)),"")} | AJ4: {=IFERROR(INDEX($B$30:$B$646,SMALL(IF($O$4=$C$30:$C$646,ROW($C$30:$C$646)-MIN(ROW($B$30:$B$646))+1,""), ROW()-1)),"")} | AL4: 1st | AN4: {=IFERROR(INDEX($B$1:$B$675,SMALL(IF($O$15=$C$1:$C$675,ROW($C$1:$C$675)-MIN(ROW($B$1:$B$675))+1,""), ROW()-12)),"")} | AW4: Wednesday | AX4: SP
B5: {=IFERROR(_xlfn.IFS(E9=0,"",E9>0,E9),"")} -> Yasmin Montero | C5: {=IFERROR(_xlfn.IFS(F9=0,"",F9>0,F9),"")} -> RN | E5: Maria Carrasco-DS | F5: sl | G5: Iraldo Rodriguez | I5: t | O5: SN | P5: Picking- Singles | Q5: =COUNTIFS($F$5:$F$664,O5)+COUNTIFS($I$5:$I$664,O5) -> 0 | U5: Total Units 8:00am | V5: 23714 | AA5: {=IFERROR(INDEX($B$1:$B$272,SMALL(IF($O$3=$C$1:$C$272,ROW($C$1:$C$272)-MIN(ROW($B$1:$B$272))+1,""), ROW()-1)),"")} | AB5: {=IFERROR(INDEX($B$1:$B$272,SMALL(IF($O$10=$C$1:$C$272,ROW($C$1:$C$272)-MIN(ROW($B$1:$B$272))+1,""), ROW()-1)),"")} | AC5: {=IFERROR(INDEX($B$1:$B$272,SMALL(IF($O$9=$C$1:$C$272,ROW($C$1:$C$272)-MIN(ROW($B$1:$B$272))+1,""), ROW()-1)),"")} -> Mbaya Kapita | AE5: {=IFERROR(INDEX($B$1:$B$272,SMALL(IF($O$6=$C$1:$C$272,ROW($C$1:$C$272)-MIN(ROW($B$1:$B$272))+1,""), ROW()-1)),"")} | AF5: {=IFERROR(INDEX($B$1:$B$272,SMALL(IF($O$8=$C$1:$C$272,ROW($C$1:$C$272)-MIN(ROW($B$1:$B$272))+1,""), ROW()-1)),"")} | AG5: {=IFERROR(INDEX($B$1:$B$272,SMALL(IF($O$31=$C$1:$C$272,ROW($C$1:$C$272)-MIN(ROW($B$1:$B$272))+1,""), ROW()-1)),"")} | AH5: {=IFERROR(INDEX($B$1:$B$272,SMALL(IF($O$21=$C$1:$C$272,ROW($C$1:$C$272)-MIN(ROW($B$1:$B$272))+1,""), ROW()-1)),"")} | AI5: {=IFERROR(INDEX($B$1:$B$30,SMALL(IF($O$4=$C$1:$C$30,ROW($C$1:$C$30)-MIN(ROW($B$1:$B$30))+1,""), ROW()-1)),"")} | AJ5: {=IFERROR(INDEX($B$30:$B$646,SMALL(IF($O$4=$C$30:$C$646,ROW($C$30:$C$646)-MIN(ROW($B$30:$B$646))+1,""), ROW()-1)),"")} | AW5: Thursday | AX5: Inventory
B6: {=IFERROR(_xlfn.IFS(E10=0,"",E10>0,E10),"")} -> Annaliet Rodriguez Perez | C6: {=IFERROR(_xlfn.IFS(F10=0,"",F10>0,F10),"")} -> PC | E6: Brandee Foster- IL | F6: I | G6: Jose Miro Quintana | I6: AB | O6: S | P6: Shipping | Q6: =COUNTIFS($F$5:$F$664,O6)+COUNTIFS($I$5:$I$664,O6) -> 0 | S6: {=LOOKUP(U1,'Deployment needs'!$2:$2,('Deployment needs'!56:56+'Deployment needs'!57:57))} -> 1.0857407 | U6: Total Units 4:00 pm | V6: 0 | AA6: {=IFERROR(INDEX($B$1:$B$272,SMALL(IF($O$3=$C$1:$C$272,ROW($C$1:$C$272)-MIN(ROW($B$1:$B$272))+1,""), ROW()-1)),"")} | AB6: {=IFERROR(INDEX($B$1:$B$272,SMALL(IF($O$10=$C$1:$C$272,ROW($C$1:$C$272)-MIN(ROW($B$1:$B$272))+1,""), ROW()-1)),"")} | AC6: {=IFERROR(INDEX($B$1:$B$272,SMALL(IF($O$9=$C$1:$C$272,ROW($C$1:$C$272)-MIN(ROW($B$1:$B$272))+1,""), ROW()-1)),"")} -> Tamara Izada Aguado | AE6: {=IFERROR(INDEX($B$1:$B$272,SMALL(IF($O$6=$C$1:$C$272,ROW($C$1:$C$272)-MIN(ROW($B$1:$B$272))+1,""), ROW()-1)),"")} | AF6: Truck | AG6: Baby Bundle Project | AH6: {=IFERROR(INDEX($B$1:$B$272,SMALL(IF($O$21=$C$1:$C$272,ROW($C$1:$C$272)-MIN(ROW($B$1:$B$272))+1,""), ROW()-1)),"")} | AI6: {=IFERROR(INDEX($B$1:$B$30,SMALL(IF($O$4=$C$1:$C$30,ROW($C$1:$C$30)-MIN(ROW($B$1:$B$30))+1,""), ROW()-1)),"")} | AJ6: {=IFERROR(INDEX($B$30:$B$646,SMALL(IF($O$4=$C$30:$C$646,ROW($C$30:$C$646)-MIN(ROW($B$30:$B$646))+1,""), ROW()-1)),"")} | AW6: Friday | AX6: Warehouse Clean
B7: {=IFERROR(_xlfn.IFS(E11=0,"",E11>0,E11),"")} -> Damaris Curbelo | C7: {=IFERROR(_xlfn.IFS(F11=0,"",F11>0,F11),"")} -> b | E7: Ailin Reynaldo | F7: i | G7: Jose Posse | I7: PTO | O7: TR | P7: Truck loading | Q7: =COUNTIFS($F$5:$F$664,O7)+COUNTIFS($I$5:$I$664,O7) -> 1 | S7: =LOOKUP(U1,'Deployment needs'!$2:$2,'Deployment needs'!60:60) -> 0.18868056 | U7: Unwaved | V7: 56 | AA7: {=IFERROR(INDEX($B$1:$B$272,SMALL(IF($O$3=$C$1:$C$272,ROW($C$1:$C$272)-MIN(ROW($B$1:$B$272))+1,""), ROW()-1)),"")} | AB7: Pick Singles | AC7: {=IFERROR(INDEX($B$1:$B$272,SMALL(IF($O$9=$C$1:$C$272,ROW($C$1:$C$272)-MIN(ROW($B$1:$B$272))+1,""), ROW()-1)),"")} | AE7: {=IFERROR(INDEX($B$1:$B$272,SMALL(IF($O$6=$C$1:$C$272,ROW($C$1:$C$272)-MIN(ROW($B$1:$B$272))+1,""), ROW()-1)),"")} | AF7: {=IFERROR(INDEX($B$1:$B$272,SMALL(IF($O$7=$C$1:$C$272,ROW($C$1:$C$272)-MIN(ROW($B$1:$B$272))+1,""), ROW()-6)),"")} -> David Almaguer-Benitez | AG7: {=IFERROR(INDEX($B$1:$B$272,SMALL(IF($O$28=$C$1:$C$272,ROW($C$1:$C$272)-MIN(ROW($B$1:$B$272))+1,""), ROW()-6)),"")} | AH7: {=IFERROR(INDEX($B$1:$B$272,SMALL(IF($O$21=$C$1:$C$272,ROW($C$1:$C$272)-MIN(ROW($B$1:$B$272))+1,""), ROW()-1)),"")} | AI7: {=IFERROR(INDEX($B$1:$B$30,SMALL(IF($O$4=$C$1:$C$30,ROW($C$1:$C$30)-MIN(ROW($B$1:$B$30))+1,""), ROW()-1)),"")} | AJ7: {=IFERROR(INDEX($B$30:$B$646,SMALL(IF($O$4=$C$30:$C$646,ROW($C$30:$C$646)-MIN(ROW($B$30:$B$646))+1,""), ROW()-1)),"")} | AV7: Tuesday Martes | AW7: Iraldo | AX7: Receiving
B8: {=IFERROR(_xlfn.IFS(E12=0,"",E12>0,E12),"")} -> Dania Curbelo | C8: {=IFERROR(_xlfn.IFS(F12=0,"",F12>0,F12),"")} -> b | E8: Chrissy Parisek | F8: RN | G8: Hector Rocha | I8: O | O8: TP | P8: Taper/Downsize | Q8: =COUNTIFS($F$5:$F$664,O8)+COUNTIFS($I$5:$I$664,O8) -> 0 | S8: {=LOOKUP(U1,'Deployment needs'!$2:$2,('Deployment needs'!59:59+'Deployment needs'!62:62))} -> 0.27547222 | U8: Open Wave Units | V8: 1921 | AA8: Lead - Support/Trainer | AB8: {=IFERROR(INDEX($B$1:$B$272,SMALL(IF($O$5=$C$1:$C$272,ROW($C$1:$C$272)-MIN(ROW($B$1:$B$272))+1,""), ROW()-7)),"")} | AC8: {=IFERROR(INDEX($B$1:$B$272,SMALL(IF($O$9=$C$1:$C$272,ROW($C$1:$C$272)-MIN(ROW($B$1:$B$272))+1,""), ROW()-1)),"")} | AE8: {=IFERROR(INDEX($B$1:$B$272,SMALL(IF($O$6=$C$1:$C$272,ROW($C$1:$C$272)-MIN(ROW($B$1:$B$272))+1,""), ROW()-1)),"")} | AF8: {=IFERROR(INDEX($B$1:$B$272,SMALL(IF($O$7=$C$1:$C$10,ROW($C$1:$C$272)-MIN(ROW($B$1:$B$272))+1,""), ROW()-6)),"")} | AG8: {=IFERROR(INDEX($B$1:$B$272,SMALL(IF($O$28=$C$1:$C$272,ROW($C$1:$C$272)-MIN(ROW($B$1:$B$272))+1,""), ROW()-6)),"")} | AH8: {=IFERROR(INDEX($B$1:$B$272,SMALL(IF($O$21=$C$1:$C$272,ROW($C$1:$C$272)-MIN(ROW($B$1:$B$272))+1,""), ROW()-1)),"")} | AI8: {=IFERROR(INDEX($B$1:$B$30,SMALL(IF($O$4=$C$1:$C$30,ROW($C$1:$C$30)-MIN(ROW($B$1:$B$30))+1,""), ROW()-1)),"")} | AJ8: {=IFERROR(INDEX($B$30:$B$646,SMALL(IF($O$4=$C$30:$C$646,ROW($C$30:$C$646)-MIN(ROW($B$30:$B$646))+1,""), ROW()-1)),"")} | AW8: Belisario | AX8: Replen Pull
B9: {=IFERROR(_xlfn.IFS(E13=0,"",E13>0,E13),"")} -> Esther Fonseca | C9: {=IFERROR(_xlfn.IFS(F13=0,"",F13>0,F13),"")} -> pto | E9: Yasmin Montero | F9: RN | G9: John Franco Morenos Rosales | I9: t | O9: B | P9: Bander | Q9: =COUNTIFS($F$5:$F$664,O9)+COUNTIFS($I$5:$I$664,O9) -> 5 | S9: =LOOKUP(U1,'Deployment needs'!$2:$2,'Deployment needs'!63:63) -> 1.1585648 | U9: Available Units | V9: 17179 | AA9: {=IFERROR(INDEX($B$1:$B$272,SMALL(IF($O$30=$C$1:$C$272,ROW($C$1:$C$272)-MIN(ROW($B$1:$B$272))+1,""),ROW()-8)),"")} -> Maria Carrasco-DS | AB9: {=IFERROR(INDEX($B$1:$B$272,SMALL(IF($O$5=$C$1:$C$272,ROW($C$1:$C$272)-MIN(ROW($B$1:$B$272))+1,""), ROW()-7)),"")} | AC9: {=IFERROR(INDEX($B$1:$B$272,SMALL(IF($O$9=$C$1:$C$272,ROW($C$1:$C$272)-MIN(ROW($B$1:$B$272))+1,""), ROW()-1)),"")} | AE9: {=IFERROR(INDEX($B$1:$B$272,SMALL(IF($O$6=$C$1:$C$272,ROW($C$1:$C$272)-MIN(ROW($B$1:$B$272))+1,""), ROW()-1)),"")} | AF9: {=IFERROR(INDEX($B$1:$B$272,SMALL(IF($O$7=$C$1:$C$10,ROW($C$1:$C$272)-MIN(ROW($B$1:$B$272))+1,""), ROW()-6)),"")} | AG9: {=IFERROR(INDEX($B$1:$B$272,SMALL(IF($O$28=$C$1:$C$272,ROW($C$1:$C$272)-MIN(ROW($B$1:$B$272))+1,""), ROW()-6)),"")} | AH9: {=IFERROR(INDEX($B$1:$B$272,SMALL(IF($O$21=$C$1:$C$272,ROW($C$1:$C$272)-MIN(ROW($B$1:$B$272))+1,""), ROW()-1)),"")} | AI9: {=IFERROR(INDEX($B$1:$B$30,SMALL(IF($O$4=$C$1:$C$30,ROW($C$1:$C$30)-MIN(ROW($B$1:$B$30))+1,""), ROW()-1)),"")} | AJ9: {=IFERROR(INDEX($B$30:$B$646,SMALL(IF($O$4=$C$30:$C$646,ROW($C$30:$C$646)-MIN(ROW($B$30:$B$646))+1,""), ROW()-1)),"")} | AW9: Hector | AX9: Overstock Throw
B10: {=IFERROR(_xlfn.IFS(E14=0,"",E14>0,E14),"")} -> Yordanka Manzanares | C10: {=IFERROR(_xlfn.IFS(F14=0,"",F14>0,F14),"")} -> pc | E10: Annaliet Rodriguez Perez | F10: PC | G10: David Almaguer-Benitez | I10: tr | O10: AB | P10: Autobagger | Q10: =COUNTIFS($F$5:$F$664,O10)+COUNTIFS($I$5:$I$664,O10) -> 1 | S10: =LOOKUP(U1,'Deployment needs'!$2:$2,'Deployment needs'!64:64) -> 1 | U10: Held by Replen | V10: 1534 | AA10: {=IFERROR(INDEX($B$1:$B$272,SMALL(IF($O$30=$C$1:$C$272,ROW($C$1:$C$272)-MIN(ROW($B$1:$B$272))+1,""),ROW()-8)),"")} | AB10: {=IFERROR(INDEX($B$1:$B$272,SMALL(IF($O$5=$C$1:$C$272,ROW($C$1:$C$272)-MIN(ROW($B$1:$B$272))+1,""), ROW()-7)),"")} | AC10: {=IFERROR(INDEX($B$1:$B$272,SMALL(IF($O$9=$C$1:$C$272,ROW($C$1:$C$272)-MIN(ROW($B$1:$B$272))+1,""), ROW()-1)),"")} | AE10: {=IFERROR(INDEX($B$1:$B$272,SMALL(IF($O$6=$C$1:$C$272,ROW($C$1:$C$272)-MIN(ROW($B$1:$B$272))+1,""), ROW()-1)),"")} | AF10: {=IFERROR(INDEX($B$1:$B$272,SMALL(IF($O$7=$C$1:$C$10,ROW($C$1:$C$272)-MIN(ROW($B$1:$B$272))+1,""), ROW()-6)),"")} | AG10: {=IFERROR(INDEX($B$1:$B$272,SMALL(IF($O$28=$C$1:$C$272,ROW($C$1:$C$272)-MIN(ROW($B$1:$B$272))+1,""), ROW()-6)),"")} | AH10: {=IFERROR(INDEX($B$1:$B$272,SMALL(IF($O$21=$C$1:$C$272,ROW($C$1:$C$272)-MIN(ROW($B$1:$B$272))+1,""), ROW()-1)),"")} | AI10: {=IFERROR(INDEX($B$1:$B$30,SMALL(IF($O$4=$C$1:$C$30,ROW($C$1:$C$30)-MIN(ROW($B$1:$B$30))+1,""), ROW()-1)),"")} | AJ10: {=IFERROR(INDEX($B$30:$B$646,SMALL(IF($O$4=$C$30:$C$646,ROW($C$30:$C$646)-MIN(ROW($B$30:$B$646))+1,""), ROW()-1)),"")} | AL10: 2nd | AW10: Jose P | AX10: Cubiscan
B11: {=IFERROR(_xlfn.IFS(E15=0,"",E15>0,E15),"")} -> Jackie Gomez | C11: {=IFERROR(_xlfn.IFS(F15=0,"",F15>0,F15),"")} -> r | E11: Damaris Curbelo | F11: b | O11: R | P11: Resets | Q11: =COUNTIFS($F$5:$F$664,O11)+COUNTIFS($I$5:$I$664,O11) -> 1 | S11: =LOOKUP(U1,'Deployment needs'!$2:$2,'Deployment needs'!93:93) -> 0.18055556 | U11: In-process | V11: 1086 | AA11: {=IFERROR(INDEX($B$1:$B$272,SMALL(IF($O$30=$C$1:$C$272,ROW($C$1:$C$272)-MIN(ROW($B$1:$B$272))+1,""),ROW()-8)),"")} | AB11: {=IFERROR(INDEX($B$1:$B$272,SMALL(IF($O$5=$C$1:$C$272,ROW($C$1:$C$272)-MIN(ROW($B$1:$B$272))+1,""), ROW()-7)),"")} | AC11: {=IFERROR(INDEX($B$1:$B$272,SMALL(IF($O$9=$C$1:$C$272,ROW($C$1:$C$272)-MIN(ROW($B$1:$B$272))+1,""), ROW()-1)),"")} | AE11: {=IFERROR(INDEX($B$1:$B$272,SMALL(IF($O$6=$C$1:$C$272,ROW($C$1:$C$272)-MIN(ROW($B$1:$B$272))+1,""), ROW()-1)),"")} | AF11: ="Returns"&" "&R22&" "&"orders"&" "&COUNTA(AF12:AF26)-COUNTBLANK(AF12:AF26) -> Returns 535 orders 3 | AG11: {=IFERROR(INDEX($B$1:$B$272,SMALL(IF($O$28=$C$1:$C$272,ROW($C$1:$C$272)-MIN(ROW($B$1:$B$272))+1,""), ROW()-6)),"")} | AH11: {=IFERROR(INDEX($B$1:$B$272,SMALL(IF($O$21=$C$1:$C$272,ROW($C$1:$C$272)-MIN(ROW($B$1:$B$272))+1,""), ROW()-1)),"")} | AI11: {=IFERROR(INDEX($B$1:$B$30,SMALL(IF($O$4=$C$1:$C$30,ROW($C$1:$C$30)-MIN(ROW($B$1:$B$30))+1,""), ROW()-1)),"")} | AJ11: {=IFERROR(INDEX($B$30:$B$646,SMALL(IF($O$4=$C$30:$C$646,ROW($C$30:$C$646)-MIN(ROW($B$30:$B$646))+1,""), ROW()-1)),"")} | AW11: Vega | AX11: Replen Throw
B12: {=IFERROR(_xlfn.IFS(E16=0,"",E16>0,E16),"")} -> Madelayne Oduardo | C12: {=IFERROR(_xlfn.IFS(F16=0,"",F16>0,F16),"")} -> rn | E12: Dania Curbelo | F12: b | O12: E | P12: Resets Exeptions | Q12: =COUNTIFS($F$5:$F$664,O12)+COUNTIFS($I$5:$I$664,O12) -> 0 | U12: Bander | V12: 1595 | Z12: Inventory | AA12: Resets | AB12: Picking Cycle Counts / Spot Count | AC12: Outbound Exception | AE12: Tasks | AF12: {=IFERROR(INDEX($B$1:$B$272,SMALL(IF($C$1:$C$272=$O$22, ROW($B$1:$B$272)-ROW($B$1)+1),ROWS($AF$12:AF12) ) ), "")} -> Chrissy Parisek | AG12: Sort Returns Putaway | AH12: Inventory & CC Reconcile | AI12: {=IFERROR(INDEX($B$1:$B$30,SMALL(IF($O$4=$C$1:$C$30,ROW($C$1:$C$30)-MIN(ROW($B$1:$B$30))+1,""), ROW()-1)),"")} | AJ12: {=IFERROR(INDEX($B$30:$B$646,SMALL(IF($O$4=$C$30:$C$646,ROW($C$30:$C$646)-MIN(ROW($B$30:$B$646))+1,""), ROW()-1)),"")} | AV12: Wednesday Miercoles | AW12: Iraldo | AX12: Overstock Throw
B13: {=IFERROR(_xlfn.IFS(E17=0,"",E17>0,E17),"")} -> Roxana Lloret | C13: {=IFERROR(_xlfn.IFS(F17=0,"",F17>0,F17),"")} -> cb | E13: Esther Fonseca | F13: pto | O13: IP | P13: Ipads | Q13: =COUNTIFS($F$5:$F$664,O13)+COUNTIFS($I$5:$I$664,O13) -> 0 | U13: Total picked | V13: 0 | AA13: {=IFERROR(INDEX($B$1:$B$272,SMALL(IF($O$11=$C$1:$C$272,ROW($C$1:$C$272)-MIN(ROW($B$1:$B$272))+1,""), ROW()-12)),"")} -> Jackie Gomez | AB13: {=IFERROR(INDEX($B$1:$B$272,SMALL(IF($O$16=$C$1:$C$272,ROW($C$1:$C$272)-MIN(ROW($B$1:$B$272))+1,""), ROW()-12)),"")} -> Annaliet Rodriguez Perez | AC13: {=IFERROR(INDEX($B$1:$B$272,SMALL(IF($O$14=$C$1:$C$272,ROW($C$1:$C$272)-MIN(ROW($B$1:$B$272))+1,""), ROW()-12)),"")} | AE13: Rush | AF13: {=IFERROR(INDEX($B$1:$B$272,SMALL(IF($C$1:$C$272=$O$22, ROW($B$1:$B$272)-ROW($B$1)+1),ROWS($AF$12:AF13) ) ), "")} -> Yasmin Montero | AG13: {=IFERROR(INDEX($B$1:$B$272,SMALL(IF($O$24=$C$1:$C$272,ROW($C$1:$C$272)-MIN(ROW($B$1:$B$272))+1,""), ROW()-12)),"")} | AH13: {=IFERROR(INDEX($B$1:$B$272,SMALL(IF($O$32=$C$1:$C$272,ROW($C$1:$C$272)-MIN(ROW($B$1:$B$272))+1,""), ROW()-12)),"")} -> Brandee Foster- IL | AI13: {=IFERROR(INDEX($B$1:$B$30,SMALL(IF($O$4=$C$1:$C$30,ROW($C$1:$C$30)-MIN(ROW($B$1:$B$30))+1,""), ROW()-1)),"")} | AJ13: {=IFERROR(INDEX($B$30:$B$646,SMALL(IF($O$4=$C$30:$C$646,ROW($C$30:$C$646)-MIN(ROW($B$30:$B$646))+1,""), ROW()-1)),"")} | AW13: Belisario | AX13: OC
B14: {=IFERROR(_xlfn.IFS(E18=0,"",E18>0,E18),"")} -> Shvodra Anderson | C14: {=IFERROR(_xlfn.IFS(F18=0,"",F18>0,F18),"")} -> b | E14: Yordanka Manzanares | F14: pc | O14: DS | P14: Outbound Exception | Q14: =COUNTIFS($F$5:$F$664,O14)+COUNTIFS($I$5:$I$664,O14) -> 0 | S14: {=LOOKUP(U1,'Deployment needs'!$2:$2,('Deployment needs'!91:91+'Deployment needs'!92:92+'Deployment needs'!61:61))} -> 0.5662037 | U14: BI Shift Shipped | V14: 0 | AA14: {=IFERROR(INDEX($B$1:$B$272,SMALL(IF($O$11=$C$1:$C$272,ROW($C$1:$C$272)-MIN(ROW($B$1:$B$272))+1,""), ROW()-12)),"")} | AB14: {=IFERROR(INDEX($B$1:$B$272,SMALL(IF($O$16=$C$1:$C$272,ROW($C$1:$C$272)-MIN(ROW($B$1:$B$272))+1,""), ROW()-12)),"")} -> Yordanka Manzanares | AC14: {=IFERROR(INDEX($B$1:$B$272,SMALL(IF($O$14=$C$1:$C$272,ROW($C$1:$C$272)-MIN(ROW($B$1:$B$272))+1,""), ROW()-12)),"")} | AE14: Aged orders/Emails | AF14: {=IFERROR(INDEX($B$1:$B$272,SMALL(IF($C$1:$C$272=$O$22, ROW($B$1:$B$272)-ROW($B$1)+1),ROWS($AF$12:AF14) ) ), "")} -> Madelayne Oduardo | AG14: {=IFERROR(INDEX($B$1:$B$272,SMALL(IF($O$24=$C$1:$C$272,ROW($C$1:$C$272)-MIN(ROW($B$1:$B$272))+1,""), ROW()-12)),"")} | AH14: {=IFERROR(INDEX($B$1:$B$272,SMALL(IF($O$32=$C$1:$C$272,ROW($C$1:$C$272)-MIN(ROW($B$1:$B$272))+1,""), ROW()-12)),"")} -> Ailin Reynaldo | AI14: {=IFERROR(INDEX($B$1:$B$30,SMALL(IF($O$4=$C$1:$C$30,ROW($C$1:$C$30)-MIN(ROW($B$1:$B$30))+1,""), ROW()-1)),"")} | AJ14: {=IFERROR(INDEX($B$30:$B$646,SMALL(IF($O$4=$C$30:$C$646,ROW($C$30:$C$646)-MIN(ROW($B$30:$B$646))+1,""), ROW()-1)),"")} | AW14: Hector | AX14: RC
B15: {=IFERROR(_xlfn.IFS(E19=0,"",E19>0,E19),"")} -> Laura Gonzalez Bustamante | C15: {=IFERROR(_xlfn.IFS(F19=0,"",F19>0,F19),"")} -> pto | E15: Jackie Gomez | F15: r | O15: MP | P15: DTC Putaway | Q15: =COUNTIFS($F$5:$F$664,O15)+COUNTIFS($I$5:$I$664,O15) -> 0 | S15: =LOOKUP(U1,'Deployment needs'!$2:$2,'Deployment needs'!95:95) -> 0.25 | U15: % to Plan Shipped | V15: =V14/V4 -> 0 | AA15: {=IFERROR(INDEX($B$1:$B$272,SMALL(IF($O$11=$C$1:$C$272,ROW($C$1:$C$272)-MIN(ROW($B$1:$B$272))+1,""), ROW()-12)),"")} | AB15: {=IFERROR(INDEX($B$1:$B$272,SMALL(IF($O$16=$C$1:$C$272,ROW($C$1:$C$272)-MIN(ROW($B$1:$B$272))+1,""), ROW()-12)),"")} | AC15: {=IFERROR(INDEX($B$1:$B$272,SMALL(IF($O$14=$C$1:$C$272,ROW($C$1:$C$272)-MIN(ROW($B$1:$B$272))+1,""), ROW()-12)),"")} | AF15: {=IFERROR(INDEX($B$1:$B$272,SMALL(IF($C$1:$C$272=$O$22, ROW($B$1:$B$272)-ROW($B$1)+1),ROWS($AF$12:AF15) ) ), "")} | AG15: {=IFERROR(INDEX($B$1:$B$272,SMALL(IF($O$24=$C$1:$C$272,ROW($C$1:$C$272)-MIN(ROW($B$1:$B$272))+1,""), ROW()-12)),"")} | AH15: {=IFERROR(INDEX($B$1:$B$272,SMALL(IF($O$32=$C$1:$C$272,ROW($C$1:$C$272)-MIN(ROW($B$1:$B$272))+1,""), ROW()-12)),"")} | AI15: {=IFERROR(INDEX($B$1:$B$30,SMALL(IF($O$4=$C$1:$C$30,ROW($C$1:$C$30)-MIN(ROW($B$1:$B$30))+1,""), ROW()-1)),"")} | AJ15: {=IFERROR(INDEX($B$30:$B$646,SMALL(IF($O$4=$C$30:$C$646,ROW($C$30:$C$646)-MIN(ROW($B$30:$B$646))+1,""), ROW()-1)),"")} | AW15: Jose P | AX15: Replen Pull
B16: {=IFERROR(_xlfn.IFS(E20=0,"",E20>0,E20),"")} -> Mbaya Kapita | C16: {=IFERROR(_xlfn.IFS(F20=0,"",F20>0,F20),"")} -> b | E16: Madelayne Oduardo | F16: rn | O16: PC | P16: Picking CC | Q16: =COUNTIFS($F$5:$F$664,O16)+COUNTIFS($I$5:$I$664,O16) -> 2 | S16: =LOOKUP(U1,'Deployment needs'!$2:$2,'Deployment needs'!88:88) -> 2.4138889 | U16: Clustered Carts | V16: 62 | AA16: {=IFERROR(INDEX($B$1:$B$272,SMALL(IF($O$11=$C$1:$C$272,ROW($C$1:$C$272)-MIN(ROW($B$1:$B$272))+1,""), ROW()-12)),"")} | AB16: {=IFERROR(INDEX($B$1:$B$272,SMALL(IF($O$16=$C$1:$C$272,ROW($C$1:$C$272)-MIN(ROW($B$1:$B$272))+1,""), ROW()-12)),"")} | AC16: ="CubiScan - in / out"&" "&R27 -> CubiScan - in / out 0 | AE16: Misspicks/DTC Putaway | AF16: {=IFERROR(INDEX($B$1:$B$272,SMALL(IF($C$1:$C$272=$O$22, ROW($B$1:$B$272)-ROW($B$1)+1),ROWS($AF$12:AF16) ) ), "")} | AG16: {=IFERROR(INDEX($B$1:$B$272,SMALL(IF($O$24=$C$1:$C$272,ROW($C$1:$C$272)-MIN(ROW($B$1:$B$272))+1,""), ROW()-12)),"")} | AH16: {=IFERROR(INDEX($B$1:$B$272,SMALL(IF($O$32=$C$1:$C$272,ROW($C$1:$C$272)-MIN(ROW($B$1:$B$272))+1,""), ROW()-12)),"")} | AI16: {=IFERROR(INDEX($B$1:$B$30,SMALL(IF($O$4=$C$1:$C$30,ROW($C$1:$C$30)-MIN(ROW($B$1:$B$30))+1,""), ROW()-1)),"")} | AJ16: {=IFERROR(INDEX($B$30:$B$646,SMALL(IF($O$4=$C$30:$C$646,ROW($C$30:$C$646)-MIN(ROW($B$30:$B$646))+1,""), ROW()-1)),"")} | AW16: Vega | AX16: Returns Putaway
B17: {=IFERROR(_xlfn.IFS(E21=0,"",E21>0,E21),"")} -> Tamara Izada Aguado | C17: {=IFERROR(_xlfn.IFS(F21=0,"",F21>0,F21),"")} -> b | E17: Roxana Lloret | F17: cb | O17: OC | P17: Overstock CC | Q17: =COUNTIFS($F$5:$F$664,O17)+COUNTIFS($I$5:$I$664,O17) -> 0 | S17: =LOOKUP(U1,'Deployment needs'!$2:$2,'Deployment needs'!75:75) -> 1.0126111 | U17: Multis to Pick | V17: 46188 | AA17: {=IFERROR(INDEX($B$1:$B$272,SMALL(IF($O$11=$C$1:$C$272,ROW($C$1:$C$272)-MIN(ROW($B$1:$B$272))+1,""), ROW()-12)),"")} | AB17: {=IFERROR(INDEX($B$1:$B$272,SMALL(IF($O$16=$C$1:$C$272,ROW($C$1:$C$272)-MIN(ROW($B$1:$B$272))+1,""), ROW()-12)),"")} | AC17: {=IFERROR(INDEX($B$1:$B$272,SMALL(IF($O$27=$C$1:$C$272,ROW($C$1:$C$272)-MIN(ROW($B$1:$B$272))+1,""), ROW()-16)),"")} | AE17: {=IFERROR(INDEX($B$1:$B$272,SMALL(IF($O$15=$C$1:$C$272,ROW($C$1:$C$272)-MIN(ROW($B$1:$B$272))+1,""), ROW()-16)),"")} | AF17: {=IFERROR(INDEX($B$1:$B$272,SMALL(IF($C$1:$C$272=$O$22, ROW($B$1:$B$272)-ROW($B$1)+1),ROWS($AF$12:AF17) ) ), "")} | AG17: ="Returns Putaway"&" "&R24 -> Returns Putaway 637 | AH17: {=IFERROR(INDEX($B$1:$B$272,SMALL(IF($O$32=$C$1:$C$272,ROW($C$1:$C$272)-MIN(ROW($B$1:$B$272))+1,""), ROW()-12)),"")} | AI17: {=IFERROR(INDEX($B$1:$B$30,SMALL(IF($O$4=$C$1:$C$30,ROW($C$1:$C$30)-MIN(ROW($B$1:$B$30))+1,""), ROW()-1)),"")} | AJ17: {=IFERROR(INDEX($B$30:$B$646,SMALL(IF($O$4=$C$30:$C$646,ROW($C$30:$C$646)-MIN(ROW($B$30:$B$646))+1,""), ROW()-1)),"")} | AL17: Rotation DTC putaway | AV17: Thursday Jueves | AW17: Iraldo | AX17: Cubiscan
B18: {=IFERROR(_xlfn.IFS(E22=0,"",E22>0,E22),"")} | C18: {=IFERROR(_xlfn.IFS(F22=0,"",F22>0,F22),"")} | E18: Shvodra Anderson | F18: b | O18: O | P18: Overstock putaway | Q18: =COUNTIFS($F$5:$F$664,O18)+COUNTIFS($I$5:$I$664,O18) -> 1 | R18: =LOOKUP($U$1-1,'Inbound SOS & EOD'!$1:$1,'Inbound SOS & EOD'!74:74) -> 140 | S18: =LOOKUP(U1,'Deployment needs'!$2:$2,'Deployment needs'!72:72) -> 4.4217778 | U18: Singles to Pick | V18: 46188 | AA18: {=IFERROR(INDEX($B$1:$B$272,SMALL(IF($O$11=$C$1:$C$272,ROW($C$1:$C$272)-MIN(ROW($B$1:$B$272))+1,""), ROW()-12)),"")} | AB18: {=IFERROR(INDEX($B$1:$B$272,SMALL(IF(O$16=$C$1:$C$272,ROW($C$1:$C$272)-MIN(ROW($B$1:$B$272))+1,""), ROW()-12)),"")} | AC18: {=IFERROR(INDEX($B$1:$B$272,SMALL(IF($O$27=$C$1:$C$272,ROW($C$1:$C$272)-MIN(ROW($B$1:$B$272))+1,""), ROW()-16)),"")} | AE18: {=IFERROR(INDEX($B$1:$B$272,SMALL(IF($O$15=$C$1:$C$272,ROW($C$1:$C$272)-MIN(ROW($B$1:$B$272))+1,""), ROW()-16)),"")} | AF18: {=IFERROR(INDEX($B$1:$B$272,SMALL(IF($C$1:$C$272=$O$22, ROW($B$1:$B$272)-ROW($B$1)+1),ROWS($AF$12:AF18) ) ), "")} | AG18: {=IFERROR(INDEX($B$1:$B$272,SMALL(IF($O$25=$C$1:$C$272,ROW($C$1:$C$272)-MIN(ROW($B$1:$B$272))+1,""), ROW()-17)),"")} | AH18: {=IFERROR(INDEX($B$1:$B$272,SMALL(IF($O$32=$C$1:$C$272,ROW($C$1:$C$272)-MIN(ROW($B$1:$B$272))+1,""), ROW()-12)),"")} | AI18: {=IFERROR(INDEX($B$1:$B$30,SMALL(IF($O$4=$C$1:$C$30,ROW($C$1:$C$30)-MIN(ROW($B$1:$B$30))+1,""), ROW()-1)),"")} | AJ18: {=IFERROR(INDEX($B$30:$B$646,SMALL(IF($O$4=$C$30:$C$646,ROW($C$30:$C$646)-MIN(ROW($B$30:$B$646))+1,""), ROW()-1)),"")} | AL18: Groups | AM18: Sunday | AN18: Monday | AO18: Tuesday | AP18: Wednesday | AQ18: Thursday | AR18: Friday | AS18: Saturday | AW18: Belisario | AX18: Overstock Throw
B19: {=IFERROR(_xlfn.IFS(E23=0,"",E23>0,E23),"")} | C19: {=IFERROR(_xlfn.IFS(F23=0,"",F23>0,F23),"")} | E19: Laura Gonzalez Bustamante | F19: pto | O19: RP | P19: Replen Pull | Q19: =COUNTIFS($F$5:$F$664,O19)+COUNTIFS($I$5:$I$664,O19) -> 0 | R19: =LOOKUP($U$1-1,'Inbound SOS & EOD'!$1:$1,'Inbound SOS & EOD'!84:84) -> 88 | S19: =LOOKUP(U1,'Deployment needs'!$2:$2,'Deployment needs'!70:70) -> 0.30895062 | U19: UPP | V19: 3 | Z19: Inbound | AA19: Reset Exceptions | AE19: {=IFERROR(INDEX($B$1:$B$272,SMALL(IF($O$15=$C$1:$C$272,ROW($C$1:$C$272)-MIN(ROW($B$1:$B$272))+1,""), ROW()-16)),"")} | AF19: {=IFERROR(INDEX($B$1:$B$272,SMALL(IF($C$1:$C$272=$O$22, ROW($B$1:$B$272)-ROW($B$1)+1),ROWS($AF$12:AF19) ) ), "")} | AG19: {=IFERROR(INDEX($B$1:$B$272,SMALL(IF($O$25=$C$1:$C$272,ROW($C$1:$C$272)-MIN(ROW($B$1:$B$272))+1,""), ROW()-17)),"")} | AH19: {=IFERROR(INDEX($B$1:$B$272,SMALL(IF($O$32=$C$1:$C$272,ROW($C$1:$C$272)-MIN(ROW($B$1:$B$272))+1,""), ROW()-12)),"")} | AI19: {=IFERROR(INDEX($B$1:$B$30,SMALL(IF($O$4=$C$1:$C$30,ROW($C$1:$C$30)-MIN(ROW($B$1:$B$30))+1,""), ROW()-1)),"")} | AJ19: {=IFERROR(INDEX($B$30:$B$646,SMALL(IF($O$4=$C$30:$C$646,ROW($C$30:$C$646)-MIN(ROW($B$30:$B$646))+1,""), ROW()-1)),"")} | AL19: 1st | AW19: Hector | AX19: Replen Pull
B20: {=IFERROR(_xlfn.IFS(E24=0,"",E24>0,E24),"")} | C20: {=IFERROR(_xlfn.IFS(F24=0,"",F24>0,F24),"")} | E20: Mbaya Kapita | F20: b | O20: RT | P20: Replen Throw | Q20: =COUNTIFS($F$5:$F$664,O20)+COUNTIFS($I$5:$I$664,O20) -> 0 | R20: =LOOKUP($U$1-1,'Inbound SOS & EOD'!$1:$1,'Inbound SOS & EOD'!85:85) -> 0 | S20: =LOOKUP(U1,'Deployment needs'!$2:$2,'Deployment needs'!71:71) -> 0.39722222 | U20: Resets | V20: 0 | AA20: {=IFERROR(INDEX($B$1:$B$272,SMALL(IF($O$11=$C$1:$C$272,ROW($C$1:$C$272)-MIN(ROW($B$1:$B$272))+1,""), ROW()-12)),"")} | AE20: {=IFERROR(INDEX($B$1:$B$272,SMALL(IF($O$15=$C$1:$C$272,ROW($C$1:$C$272)-MIN(ROW($B$1:$B$272))+1,""), ROW()-16)),"")} | AF20: {=IFERROR(INDEX($B$1:$B$272,SMALL(IF($C$1:$C$272=$O$22, ROW($B$1:$B$272)-ROW($B$1)+1),ROWS($AF$12:AF20) ) ), "")} | AG20: {=IFERROR(INDEX($B$1:$B$272,SMALL(IF($O$25=$C$1:$C$272,ROW($C$1:$C$272)-MIN(ROW($B$1:$B$272))+1,""), ROW()-17)),"")} | AH20: {=IFERROR(INDEX($B$1:$B$272,SMALL(IF($O$32=$C$1:$C$272,ROW($C$1:$C$272)-MIN(ROW($B$1:$B$272))+1,""), ROW()-12)),"")} | AI20: {=IFERROR(INDEX($B$1:$B$30,SMALL(IF($O$4=$C$1:$C$30,ROW($C$1:$C$30)-MIN(ROW($B$1:$B$30))+1,""), ROW()-1)),"")} | AJ20: {=IFERROR(INDEX($B$30:$B$646,SMALL(IF($O$4=$C$30:$C$646,ROW($C$30:$C$646)-MIN(ROW($B$30:$B$646))+1,""), ROW()-1)),"")} | AW20: Jose P | AX20: Project - Wholesale
B21: {=IFERROR(_xlfn.IFS(E25=0,"",E25>0,E25),"")} | C21: {=IFERROR(_xlfn.IFS(F25=0,"",F25>0,F25),"")} | E21: Tamara Izada Aguado | F21: b | O21: T | P21: Training | Q21: =COUNTIFS($F$5:$F$664,O21)+COUNTIFS($I$5:$I$664,O21) -> 2 | R21: 0 | S21: =LOOKUP(U1,'Deployment needs'!$2:$2,'Deployment needs'!94:94) -> 0 | U21: Region 1 UPH | V21: 0 | AA21: {=IFERROR(INDEX($B$1:$B$272,SMALL(IF($O$11=$C$1:$C$272,ROW($C$1:$C$272)-MIN(ROW($B$1:$B$272))+1,""), ROW()-12)),"")} | AB21: {=IFERROR(INDEX($B$1:$B$272,SMALL(IF(O$16=$C$1:$C$272,ROW($C$1:$C$272)-MIN(ROW($B$1:$B$272))+1,""), ROW()-12)),"")} | AC21: {=IFERROR(INDEX($B$1:$B$272,SMALL(IF($O$27=$C$1:$C$272,ROW($C$1:$C$272)-MIN(ROW($B$1:$B$272))+1,""), ROW()-16)),"")} | AE21: {=IFERROR(INDEX($B$1:$B$272,SMALL(IF($O$15=$C$1:$C$272,ROW($C$1:$C$272)-MIN(ROW($B$1:$B$272))+1,""), ROW()-16)),"")} | AF21: {=IFERROR(INDEX($B$1:$B$272,SMALL(IF($C$1:$C$272=$O$22, ROW($B$1:$B$272)-ROW($B$1)+1),ROWS($AF$12:AF21) ) ), "")} | AG21: {=IFERROR(INDEX($B$1:$B$272,SMALL(IF($O$25=$C$1:$C$272,ROW($C$1:$C$272)-MIN(ROW($B$1:$B$272))+1,""), ROW()-17)),"")} | AH21: {=IFERROR(INDEX($B$1:$B$272,SMALL(IF($O$32=$C$1:$C$272,ROW($C$1:$C$272)-MIN(ROW($B$1:$B$272))+1,""), ROW()-12)),"")} | AI21: {=IFERROR(INDEX($B$1:$B$30,SMALL(IF($O$4=$C$1:$C$30,ROW($C$1:$C$30)-MIN(ROW($B$1:$B$30))+1,""), ROW()-1)),"")} | AJ21: {=IFERROR(INDEX($B$30:$B$646,SMALL(IF($O$4=$C$30:$C$646,ROW($C$30:$C$646)-MIN(ROW($B$30:$B$646))+1,""), ROW()-1)),"")} | AW21: Vega | AX21: Project - Wholesale
B22: {=IFERROR(_xlfn.IFS(E26=0,"",E26>0,E26),"")} | C22: {=IFERROR(_xlfn.IFS(F26=0,"",F26>0,F26),"")} | O22: RN | P22: Returns Processing | Q22: =COUNTIFS($F$5:$F$664,O22)+COUNTIFS($I$5:$I$664,O22) -> 3 | R22: =LOOKUP($U$1-1,'Inbound SOS & EOD'!$1:$1,'Inbound SOS & EOD'!41:41) -> 535 | S22: =LOOKUP(U1,'Deployment needs'!$2:$2,'Deployment needs'!81:81) -> 0.7027134 | U22: Region 2 UPH | V22: 0 | AA22: {=IFERROR(INDEX($B$1:$B$272,SMALL(IF($O$11=$C$1:$C$272,ROW($C$1:$C$272)-MIN(ROW($B$1:$B$272))+1,""), ROW()-12)),"")} | AB22: {=IFERROR(INDEX($B$1:$B$272,SMALL(IF(O$16=$C$1:$C$272,ROW($C$1:$C$272)-MIN(ROW($B$1:$B$272))+1,""), ROW()-12)),"")} | AC22: Replen pull | AD22: Priority | AE22: {=IFERROR(INDEX($B$1:$B$272,SMALL(IF($O$15=$C$1:$C$272,ROW($C$1:$C$272)-MIN(ROW($B$1:$B$272))+1,""), ROW()-16)),"")} | AF22: {=IFERROR(INDEX($B$1:$B$272,SMALL(IF($C$1:$C$272=$O$22, ROW($B$1:$B$272)-ROW($B$1)+1),ROWS($AF$12:AF22) ) ), "")} | AG22: {=IFERROR(INDEX($B$1:$B$272,SMALL(IF($O$25=$C$1:$C$272,ROW($C$1:$C$272)-MIN(ROW($B$1:$B$272))+1,""), ROW()-17)),"")} | AH22: {=IFERROR(INDEX($B$1:$B$272,SMALL(IF($O$32=$C$1:$C$272,ROW($C$1:$C$272)-MIN(ROW($B$1:$B$272))+1,""), ROW()-12)),"")} | AI22: {=IFERROR(INDEX($B$1:$B$30,SMALL(IF($O$4=$C$1:$C$30,ROW($C$1:$C$30)-MIN(ROW($B$1:$B$30))+1,""), ROW()-1)),"")} | AJ22: {=IFERROR(INDEX($B$30:$B$646,SMALL(IF($O$4=$C$30:$C$646,ROW($C$30:$C$646)-MIN(ROW($B$30:$B$646))+1,""), ROW()-1)),"")}
B23: {=IFERROR(_xlfn.IFS(E27=0,"",E27>0,E27),"")} | C23: {=IFERROR(_xlfn.IFS(F27=0,"",F27>0,F27),"")} | O23: RE | P23: Returns Exceptions | Q23: =COUNTIFS($F$5:$F$664,O23)+COUNTIFS($I$5:$I$664,O23) -> 0 | R23: =LOOKUP($U$1-1,'Inbound SOS & EOD'!$1:$1,'Inbound SOS & EOD'!45:45) -> 40 | S23: =LOOKUP(U1,'Deployment needs'!$2:$2,'Deployment needs'!82:82) -> 0.062215434 | U23: Region 12 UPH | V23: 0 | AA23: ="Receiving"&" "&R32 -> Receiving | AB23: Task | AC23: {=IFERROR(INDEX($B$1:$B$272,SMALL(IF($C$1:$C$272=$O$19, ROW($B$1:$B$272)-ROW($B$1)+1),ROWS($AC$23:AC23) ) ), "")} | AD23: 0-3 | AE23: {=IFERROR(INDEX($B$1:$B$272,SMALL(IF($O$15=$C$1:$C$272,ROW($C$1:$C$272)-MIN(ROW($B$1:$B$272))+1,""), ROW()-16)),"")} | AF23: {=IFERROR(INDEX($B$1:$B$272,SMALL(IF($C$1:$C$272=$O$22, ROW($B$1:$B$272)-ROW($B$1)+1),ROWS($AF$12:AF23) ) ), "")} | AG23: {=IFERROR(INDEX($B$1:$B$272,SMALL(IF($O$25=$C$1:$C$272,ROW($C$1:$C$272)-MIN(ROW($B$1:$B$272))+1,""), ROW()-17)),"")} | AH23: {=IFERROR(INDEX($B$1:$B$272,SMALL(IF($O$32=$C$1:$C$272,ROW($C$1:$C$272)-MIN(ROW($B$1:$B$272))+1,""), ROW()-12)),"")} | AI23: {=IFERROR(INDEX($B$1:$B$30,SMALL(IF($O$4=$C$1:$C$30,ROW($C$1:$C$30)-MIN(ROW($B$1:$B$30))+1,""), ROW()-1)),"")} | AJ23: {=IFERROR(INDEX($B$30:$B$646,SMALL(IF($O$4=$C$30:$C$646,ROW($C$30:$C$646)-MIN(ROW($B$30:$B$646))+1,""), ROW()-1)),"")}
B24: {=IFERROR(_xlfn.IFS(E28=0,"",E28>0,E28),"")} | C24: {=IFERROR(_xlfn.IFS(F28=0,"",F28>0,F28),"")} | O24: RS | P24: Returns Sorting | Q24: =COUNTIFS($F$5:$F$664,O24)+COUNTIFS($I$5:$I$664,O24) -> 0 | R24: =LOOKUP($U$1-1,'Inbound SOS & EOD'!$1:$1,'Inbound SOS & EOD'!59:59) -> 637 | S24: =LOOKUP(U1,'Deployment needs'!$2:$2,'Deployment needs'!83:83) -> 0.22219798 | AA24: {=IFERROR(INDEX($B$1:$B$272,SMALL(IF($C$1:$C$272=$O$26, ROW($B$1:$B$272)-ROW($B$1)+1),ROWS($AA$24:AA24) ) ), "")} | AB24: Door 6 | AC24: {=IFERROR(INDEX($B$1:$B$272,SMALL(IF($C$1:$C$272=$O$19, ROW($B$1:$B$272)-ROW($B$1)+1),ROWS($AC$23:AC24) ) ), "")} | AE24: Replen throw | AF24: {=IFERROR(INDEX($B$1:$B$272,SMALL(IF($C$1:$C$272=$O$22, ROW($B$1:$B$272)-ROW($B$1)+1),ROWS($AF$12:AF24) ) ), "")} | AG24: {=IFERROR(INDEX($B$1:$B$272,SMALL(IF($O$25=$C$1:$C$272,ROW($C$1:$C$272)-MIN(ROW($B$1:$B$272))+1,""), ROW()-17)),"")} | AH24: {=IFERROR(INDEX($B$1:$B$272,SMALL(IF($O$32=$C$1:$C$272,ROW($C$1:$C$272)-MIN(ROW($B$1:$B$272))+1,""), ROW()-12)),"")} | AI24: {=IFERROR(INDEX($B$1:$B$30,SMALL(IF($O$4=$C$1:$C$30,ROW($C$1:$C$30)-MIN(ROW($B$1:$B$30))+1,""), ROW()-1)),"")} | AJ24: {=IFERROR(INDEX($B$30:$B$646,SMALL(IF($O$4=$C$30:$C$646,ROW($C$30:$C$646)-MIN(ROW($B$30:$B$646))+1,""), ROW()-1)),"")}
B25: {=IFERROR(_xlfn.IFS(E29=0,"",E29>0,E29),"")} | C25: {=IFERROR(_xlfn.IFS(F29=0,"",F29>0,F29),"")} | O25: RPA | P25: Returns put-away | Q25: =COUNTIFS($F$5:$F$664,O25)+COUNTIFS($I$5:$I$664,O25) -> 0 | AA25: {=IFERROR(INDEX($B$1:$B$272,SMALL(IF($C$1:$C$272=$O$26, ROW($B$1:$B$272)-ROW($B$1)+1),ROWS($AA$24:AA25) ) ), "")} | AB25: Door 6 | AC25: {=IFERROR(INDEX($B$1:$B$272,SMALL(IF($C$1:$C$272=$O$19, ROW($B$1:$B$272)-ROW($B$1)+1),ROWS($AC$23:AC25) ) ), "")} | AE25: {=IFERROR(INDEX($B$1:$B$272,SMALL(IF($C$1:$C$272=$O$20, ROW($B$1:$B$272)-ROW($B$1)+1),ROWS($AE$25:AE25) ) ), "")} | AF25: {=IFERROR(INDEX($B$1:$B$272,SMALL(IF($C$1:$C$272=$O$22, ROW($B$1:$B$272)-ROW($B$1)+1),ROWS($AF$12:AF25) ) ), "")} | AG25: {=IFERROR(INDEX($B$1:$B$272,SMALL(IF($O$25=$C$1:$C$272,ROW($C$1:$C$272)-MIN(ROW($B$1:$B$272))+1,""), ROW()-17)),"")} | AH25: {=IFERROR(INDEX($B$1:$B$272,SMALL(IF($O$32=$C$1:$C$272,ROW($C$1:$C$272)-MIN(ROW($B$1:$B$272))+1,""), ROW()-12)),"")} | AI25: {=IFERROR(INDEX($B$1:$B$30,SMALL(IF($O$4=$C$1:$C$30,ROW($C$1:$C$30)-MIN(ROW($B$1:$B$30))+1,""), ROW()-1)),"")} | AJ25: {=IFERROR(INDEX($B$30:$B$646,SMALL(IF($O$4=$C$30:$C$646,ROW($C$30:$C$646)-MIN(ROW($B$30:$B$646))+1,""), ROW()-1)),"")}
B26: {=IFERROR(_xlfn.IFS(E30=0,"",E30>0,E30),"")} | C26: {=IFERROR(_xlfn.IFS(F30=0,"",F30>0,F30),"")} | O26: RC | P26: Receiving | Q26: =COUNTIFS($F$5:$F$664,O26)+COUNTIFS($I$5:$I$664,O26) -> 0 | R26: =LOOKUP($U$1-1,'Inbound SOS & EOD'!$1:$1,'Inbound SOS & EOD'!56:56) -> 0 | S26: =LOOKUP(U1,'Deployment needs'!$2:$2,'Deployment needs'!73:73) -> 1.4739259 | X26: These are picked units , not shipped. | AA26: {=IFERROR(INDEX($B$1:$B$272,SMALL(IF($C$1:$C$272=$O$26, ROW($B$1:$B$272)-ROW($B$1)+1),ROWS($AA$24:AA26) ) ), "")} | AC26: {=IFERROR(INDEX($B$1:$B$272,SMALL(IF($C$1:$C$272=$O$19, ROW($B$1:$B$272)-ROW($B$1)+1),ROWS($AC$23:AC26) ) ), "")} | AE26: {=IFERROR(INDEX($B$1:$B$272,SMALL(IF($C$1:$C$272=$O$20, ROW($B$1:$B$272)-ROW($B$1)+1),ROWS($AE$25:AE26) ) ), "")} | AF26: {=IFERROR(INDEX($B$1:$B$272,SMALL(IF($C$1:$C$272=$O$22, ROW($B$1:$B$272)-ROW($B$1)+1),ROWS($AF$12:AF26) ) ), "")} | AG26: {=IFERROR(INDEX($B$1:$B$272,SMALL(IF($O$25=$C$1:$C$272,ROW($C$1:$C$272)-MIN(ROW($B$1:$B$272))+1,""), ROW()-17)),"")} | AH26: {=IFERROR(INDEX($B$1:$B$272,SMALL(IF($O$32=$C$1:$C$272,ROW($C$1:$C$272)-MIN(ROW($B$1:$B$272))+1,""), ROW()-12)),"")} | AI26: {=IFERROR(INDEX($B$1:$B$30,SMALL(IF($O$4=$C$1:$C$30,ROW($C$1:$C$30)-MIN(ROW($B$1:$B$30))+1,""), ROW()-1)),"")} | AJ26: {=IFERROR(INDEX($B$30:$B$646,SMALL(IF($O$4=$C$30:$C$646,ROW($C$30:$C$646)-MIN(ROW($B$30:$B$646))+1,""), ROW()-1)),"")}
B27: {=IFERROR(_xlfn.IFS(E31=0,"",E31>0,E31),"")} | C27: {=IFERROR(_xlfn.IFS(F31=0,"",F31>0,F31),"")} | O27: CS | P27: Cubiscan | Q27: =COUNTIFS($F$5:$F$664,O27)+COUNTIFS($I$5:$I$664,O27) -> 0 | R27: =LOOKUP($U$1-1,'Inbound SOS & EOD'!$1:$1,'Inbound SOS & EOD'!57:57) -> 0 | S27: =LOOKUP(U1,'Deployment needs'!$2:$2,'Deployment needs'!74:74) -> 1.6581667 | AA27: {=IFERROR(INDEX($B$1:$B$272,SMALL(IF($C$1:$C$272=$O$26, ROW($B$1:$B$272)-ROW($B$1)+1),ROWS($AA$24:AA27) ) ), "")} | AC27: {=IFERROR(INDEX($B$1:$B$272,SMALL(IF($O$19=$C$1:$C$272,ROW($C$1:$C$272)-MIN(ROW($B$1:$B$272))+1,""), ROW()-21)),"")} | AE27: {=IFERROR(INDEX($B$1:$B$272,SMALL(IF($C$1:$C$272=$O$20, ROW($B$1:$B$272)-ROW($B$1)+1),ROWS($AE$25:AE27) ) ), "")} | AF27: ="Returns Exceptions"&" "&$X$54 -> Returns Exceptions estimate | AG27: {=IFERROR(INDEX($B$1:$B$272,SMALL(IF($O$25=$C$1:$C$272,ROW($C$1:$C$272)-MIN(ROW($B$1:$B$272))+1,""), ROW()-17)),"")} | AH27: {=IFERROR(INDEX($B$1:$B$272,SMALL(IF($O$32=$C$1:$C$272,ROW($C$1:$C$272)-MIN(ROW($B$1:$B$272))+1,""), ROW()-12)),"")} | AI27: {=IFERROR(INDEX($B$1:$B$30,SMALL(IF($O$4=$C$1:$C$30,ROW($C$1:$C$30)-MIN(ROW($B$1:$B$30))+1,""), ROW()-1)),"")} | AJ27: {=IFERROR(INDEX($B$30:$B$646,SMALL(IF($O$4=$C$30:$C$646,ROW($C$30:$C$646)-MIN(ROW($B$30:$B$646))+1,""), ROW()-1)),"")}
B28: {=IFERROR(_xlfn.IFS(E32=0,"",E32>0,E32),"")} | C28: {=IFERROR(_xlfn.IFS(F32=0,"",F32>0,F32),"")} | O28: BB | P28: Baby Bundle Project | Q28: =COUNTIFS($F$5:$F$664,O28)+COUNTIFS($I$5:$I$664,O28) -> 0 | R28: ='[3]2025 Progress tracker'!$D$15 -> 0 | AA28: {=IFERROR(INDEX($B$1:$B$272,SMALL(IF($C$1:$C$272=$O$26, ROW($B$1:$B$272)-ROW($B$1)+1),ROWS($AA$24:AA28) ) ), "")} | AC28: Aisle & DC Cleanup | AE28: {=IFERROR(INDEX($B$1:$B$272,SMALL(IF($C$1:$C$272=$O$20, ROW($B$1:$B$272)-ROW($B$1)+1),ROWS($AE$25:AE28) ) ), "")} | AF28: {=IFERROR(INDEX($B$1:$B$272,SMALL(IF($O$23=$C$1:$C$272,ROW($C$1:$C$272)-MIN(ROW($B$1:$B$272))+1,""), ROW()-26)),"")} | AG28: {=IFERROR(INDEX($B$1:$B$272,SMALL(IF($O$25=$C$1:$C$272,ROW($C$1:$C$272)-MIN(ROW($B$1:$B$272))+1,""), ROW()-17)),"")} | AH28: {=IFERROR(INDEX($B$1:$B$272,SMALL(IF($O$32=$C$1:$C$272,ROW($C$1:$C$272)-MIN(ROW($B$1:$B$272))+1,""), ROW()-12)),"")} | AI28: {=IFERROR(INDEX($B$1:$B$30,SMALL(IF($O$4=$C$1:$C$30,ROW($C$1:$C$30)-MIN(ROW($B$1:$B$30))+1,""), ROW()-1)),"")} | AJ28: {=IFERROR(INDEX($B$30:$B$646,SMALL(IF($O$4=$C$30:$C$646,ROW($C$30:$C$646)-MIN(ROW($B$30:$B$646))+1,""), ROW()-1)),"")}
B29: {=IFERROR(_xlfn.IFS(E33=0,"",E33>0,E33),"")} | C29: {=IFERROR(_xlfn.IFS(F33=0,"",F33>0,F33),"")} | O29: WU | P29: Warehouse Utility | Q29: =COUNTIFS($F$5:$F$664,O29)+COUNTIFS($I$5:$I$664,O29) -> 0 | AA29: {=IFERROR(INDEX($B$1:$B$272,SMALL(IF($C$1:$C$272=$O$26, ROW($B$1:$B$272)-ROW($B$1)+1),ROWS($AA$24:AA29) ) ), "")} | AE29: {=IFERROR(INDEX($B$1:$B$272,SMALL(IF($C$1:$C$272=$O$20, ROW($B$1:$B$272)-ROW($B$1)+1),ROWS($AE$25:AE29) ) ), "")} | AF29: {=IFERROR(INDEX($B$1:$B$272,SMALL(IF($O$23=$C$1:$C$272,ROW($C$1:$C$272)-MIN(ROW($B$1:$B$272))+1,""), ROW()-26)),"")} | AG29: {=IFERROR(INDEX($B$1:$B$272,SMALL(IF($O$25=$C$1:$C$272,ROW($C$1:$C$272)-MIN(ROW($B$1:$B$272))+1,""), ROW()-17)),"")} | AH29: {=IFERROR(INDEX($B$1:$B$272,SMALL(IF($O$32=$C$1:$C$272,ROW($C$1:$C$272)-MIN(ROW($B$1:$B$272))+1,""), ROW()-12)),"")} | AI29: {=IFERROR(INDEX($B$1:$B$30,SMALL(IF($O$4=$C$1:$C$30,ROW($C$1:$C$30)-MIN(ROW($B$1:$B$30))+1,""), ROW()-1)),"")} | AJ29: {=IFERROR(INDEX($B$30:$B$646,SMALL(IF($O$4=$C$30:$C$646,ROW($C$30:$C$646)-MIN(ROW($B$30:$B$646))+1,""), ROW()-1)),"")} | AL29: 2nd
B30: {=IFERROR(_xlfn.IFS(E34=0,"",E34>0,E34),"")} | C30: {=IFERROR(_xlfn.IFS(F34=0,"",F34>0,F34),"")} | O30: SL | P30: Support | Q30: =COUNTIFS($F$5:$F$664,O30)+COUNTIFS($I$5:$I$664,O30) -> 1 | AA30: {=IFERROR(INDEX($B$1:$B$272,SMALL(IF($C$1:$C$272=$O$26, ROW($B$1:$B$272)-ROW($B$1)+1),ROWS($AA$24:AA30) ) ), "")} | AC30: {=IFERROR(INDEX($B$1:$B$272,SMALL(IF($O$33=$C$1:$C$272,ROW($C$1:$C$272)-MIN(ROW($B$1:$B$272))+1,""), ROW()-26)),"")} | AE30: {=IFERROR(INDEX($B$1:$B$272,SMALL(IF($C$1:$C$272=$O$20, ROW($B$1:$B$272)-ROW($B$1)+1),ROWS($AE$25:AE30) ) ), "")} | AF30: {=IFERROR(INDEX($B$1:$B$272,SMALL(IF($O$23=$C$1:$C$272,ROW($C$1:$C$272)-MIN(ROW($B$1:$B$272))+1,""), ROW()-26)),"")} | AG30: {=IFERROR(INDEX($B$1:$B$272,SMALL(IF($O$25=$C$1:$C$272,ROW($C$1:$C$272)-MIN(ROW($B$1:$B$272))+1,""), ROW()-17)),"")} | AH30: {=IFERROR(INDEX($B$1:$B$272,SMALL(IF($O$32=$C$1:$C$272,ROW($C$1:$C$272)-MIN(ROW($B$1:$B$272))+1,""), ROW()-12)),"")} | AI30: {=IFERROR(INDEX($B$1:$B$30,SMALL(IF($O$4=$C$1:$C$30,ROW($C$1:$C$30)-MIN(ROW($B$1:$B$30))+1,""), ROW()-1)),"")} | AJ30: {=IFERROR(INDEX($B$30:$B$646,SMALL(IF($O$4=$C$30:$C$646,ROW($C$30:$C$646)-MIN(ROW($B$30:$B$646))+1,""), ROW()-1)),"")}
B31: {=IFERROR(_xlfn.IFS(G5=0,"",G5>0,G5),"")} -> Iraldo Rodriguez | C31: {=IFERROR(_xlfn.IFS(I5=0,"",I5>0,I5),"")} -> t | O31: SP | P31: Special Projects | Q31: =COUNTIFS($F$5:$F$664,O31)+COUNTIFS($I$5:$I$664,O31) -> 0 | S31: =LOOKUP(U1,'Deployment needs'!$2:$2,'Deployment needs'!96:96) -> 0 | AA31: Overstock Cycle Count | AB31: ="Overstock Putaway"&" "&T36 -> Overstock Putaway | AC31: {=IFERROR(INDEX($B$1:$B$272,SMALL(IF($O$33=$C$1:$C$272,ROW($C$1:$C$272)-MIN(ROW($B$1:$B$272))+1,""), ROW()-26)),"")} | AE31: {=IFERROR(INDEX($B$1:$B$272,SMALL(IF($C$1:$C$272=$O$20, ROW($B$1:$B$272)-ROW($B$1)+1),ROWS($AE$25:AE31) ) ), "")} | AF31: {=IFERROR(INDEX($B$1:$B$272,SMALL(IF($O$23=$C$1:$C$272,ROW($C$1:$C$272)-MIN(ROW($B$1:$B$272))+1,""), ROW()-26)),"")} | AG31: {=IFERROR(INDEX($B$1:$B$272,SMALL(IF($O$25=$C$1:$C$272,ROW($C$1:$C$272)-MIN(ROW($B$1:$B$272))+1,""), ROW()-17)),"")} | AH31: {=IFERROR(INDEX($B$1:$B$272,SMALL(IF($O$32=$C$1:$C$272,ROW($C$1:$C$272)-MIN(ROW($B$1:$B$272))+1,""), ROW()-12)),"")} | AI31: {=IFERROR(INDEX($B$1:$B$30,SMALL(IF($O$4=$C$1:$C$30,ROW($C$1:$C$30)-MIN(ROW($B$1:$B$30))+1,""), ROW()-1)),"")} | AJ31: {=IFERROR(INDEX($B$30:$B$646,SMALL(IF($O$4=$C$30:$C$646,ROW($C$30:$C$646)-MIN(ROW($B$30:$B$646))+1,""), ROW()-1)),"")}
B32: {=IFERROR(_xlfn.IFS(G6=0,"",G6>0,G6),"")} -> Jose Miro Quintana | C32: {=IFERROR(_xlfn.IFS(I6=0,"",I6>0,I6),"")} -> AB | O32: I | P32: Inventory functions | Q32: =COUNTIFS($F$5:$F$664,O32)+COUNTIFS($I$5:$I$664,O32) -> 2 | S32: {=LOOKUP(U1,'Deployment needs'!$2:$2,('Deployment needs'!76:76+'Deployment needs'!89:89+'Deployment needs'!90:90))} -> 0.5 | U32: hours | V32: 1 | W32: 4 | X32: 2 | AA32: {=IFERROR(INDEX($B$1:$B$272,SMALL(IF($O$17=$C$1:$C$272,ROW($C$1:$C$272)-MIN(ROW($B$1:$B$272))+1,""), ROW()-31)),"")} | AB32: {=IFERROR(INDEX($B$1:$B$272,SMALL(IF($O$18=$C$1:$C$272,ROW($C$1:$C$272)-MIN(ROW($B$1:$B$272))+1,""), ROW()-31)),"")} -> Hector Rocha | AC32: {=IFERROR(INDEX($B$1:$B$272,SMALL(IF($O$33=$C$1:$C$272,ROW($C$1:$C$272)-MIN(ROW($B$1:$B$272))+1,""), ROW()-26)),"")} | AE32: {=IFERROR(INDEX($B$1:$B$272,SMALL(IF($O$20=$C$1:$C$272,ROW($C$1:$C$272)-MIN(ROW($B$1:$B$272))+1,""), ROW()-20)),"")} | AF32: {=IFERROR(INDEX($B$1:$B$272,SMALL(IF($O$23=$C$1:$C$272,ROW($C$1:$C$272)-MIN(ROW($B$1:$B$272))+1,""), ROW()-26)),"")} | AG32: {=IFERROR(INDEX($B$1:$B$272,SMALL(IF($O$25=$C$1:$C$272,ROW($C$1:$C$272)-MIN(ROW($B$1:$B$272))+1,""), ROW()-17)),"")} | AH32: {=IFERROR(INDEX($B$1:$B$272,SMALL(IF($O$32=$C$1:$C$272,ROW($C$1:$C$272)-MIN(ROW($B$1:$B$272))+1,""), ROW()-12)),"")} | AI32: {=IFERROR(INDEX($B$1:$B$30,SMALL(IF($O$4=$C$1:$C$30,ROW($C$1:$C$30)-MIN(ROW($B$1:$B$30))+1,""), ROW()-1)),"")} | AJ32: {=IFERROR(INDEX($B$30:$B$646,SMALL(IF($O$4=$C$30:$C$646,ROW($C$30:$C$646)-MIN(ROW($B$30:$B$646))+1,""), ROW()-1)),"")}
B33: {=IFERROR(_xlfn.IFS(G7=0,"",G7>0,G7),"")} -> Jose Posse | C33: {=IFERROR(_xlfn.IFS(I7=0,"",I7>0,I7),"")} -> PTO | O33: W | P33: Warehouse Cleaning | Q33: =COUNTIFS($F$5:$F$664,O33)+COUNTIFS($I$5:$I$664,O33) -> 0 | S33: =LOOKUP(U1,'Deployment needs'!$2:$2,'Deployment needs'!77:77) -> 1 | U33: region / hrs | V33: # pickers | W33: UPH | X33: estimate | AA33: {=IFERROR(INDEX($B$1:$B$272,SMALL(IF($O$17=$C$1:$C$272,ROW($C$1:$C$272)-MIN(ROW($B$1:$B$272))+1,""), ROW()-31)),"")} | AB33: {=IFERROR(INDEX($B$1:$B$272,SMALL(IF($O$18=$C$1:$C$272,ROW($C$1:$C$272)-MIN(ROW($B$1:$B$272))+1,""), ROW()-31)),"")} | AC33: {=IFERROR(INDEX($B$1:$B$272,SMALL(IF($O$33=$C$1:$C$272,ROW($C$1:$C$272)-MIN(ROW($B$1:$B$272))+1,""), ROW()-26)),"")} | AE33: Warehouse Utility | AF33: {=IFERROR(INDEX($B$1:$B$272,SMALL(IF($O$23=$C$1:$C$272,ROW($C$1:$C$272)-MIN(ROW($B$1:$B$272))+1,""), ROW()-26)),"")} | AG33: {=IFERROR(INDEX($B$1:$B$272,SMALL(IF($O$25=$C$1:$C$272,ROW($C$1:$C$272)-MIN(ROW($B$1:$B$272))+1,""), ROW()-17)),"")} | AH33: {=IFERROR(INDEX($B$1:$B$272,SMALL(IF($O$32=$C$1:$C$272,ROW($C$1:$C$272)-MIN(ROW($B$1:$B$272))+1,""), ROW()-12)),"")} | AI33: {=IFERROR(INDEX($B$1:$B$30,SMALL(IF($O$4=$C$1:$C$30,ROW($C$1:$C$30)-MIN(ROW($B$1:$B$30))+1,""), ROW()-1)),"")} | AJ33: {=IFERROR(INDEX($B$30:$B$646,SMALL(IF($O$4=$C$30:$C$646,ROW($C$30:$C$646)-MIN(ROW($B$30:$B$646))+1,""), ROW()-1)),"")}
B34: {=IFERROR(_xlfn.IFS(G8=0,"",G8>0,G8),"")} -> Hector Rocha | C34: {=IFERROR(_xlfn.IFS(I8=0,"",I8>0,I8),"")} -> O | P34: Total | Q34: =F39 -> 20 | S34: =SUM(S3:S33) -> 23.431665 | U34: Picking- Bulk (5) | V34: 14 | W34: 175 | X34: =W34*V34*$W$32 -> 9800 | AA34: {=IFERROR(INDEX($B$1:$B$272,SMALL(IF($O$17=$C$1:$C$272,ROW($C$1:$C$272)-MIN(ROW($B$1:$B$272))+1,""), ROW()-31)),"")} | AB34: {=IFERROR(INDEX($B$1:$B$272,SMALL(IF($O$18=$C$1:$C$272,ROW($C$1:$C$272)-MIN(ROW($B$1:$B$272))+1,""), ROW()-31)),"")} | AC34: {=IFERROR(INDEX($B$1:$B$272,SMALL(IF($O$33=$C$1:$C$272,ROW($C$1:$C$272)-MIN(ROW($B$1:$B$272))+1,""), ROW()-26)),"")} | AE34: {=IFERROR(INDEX($B$1:$B$272,SMALL(IF($O$29=$C$1:$C$272,ROW($C$1:$C$272)-MIN(ROW($B$1:$B$272))+1,""), ROW()-33)),"")} | AF34: {=IFERROR(INDEX($B$1:$B$272,SMALL(IF($O$23=$C$1:$C$272,ROW($C$1:$C$272)-MIN(ROW($B$1:$B$272))+1,""), ROW()-26)),"")} | AG34: {=IFERROR(INDEX($B$1:$B$272,SMALL(IF($O$25=$C$1:$C$272,ROW($C$1:$C$272)-MIN(ROW($B$1:$B$272))+1,""), ROW()-17)),"")} | AH34: {=IFERROR(INDEX($B$1:$B$272,SMALL(IF($O$32=$C$1:$C$272,ROW($C$1:$C$272)-MIN(ROW($B$1:$B$272))+1,""), ROW()-12)),"")} | AI34: {=IFERROR(INDEX($B$1:$B$30,SMALL(IF($O$4=$C$1:$C$30,ROW($C$1:$C$30)-MIN(ROW($B$1:$B$30))+1,""), ROW()-1)),"")} | AJ34: {=IFERROR(INDEX($B$30:$B$646,SMALL(IF($O$4=$C$30:$C$646,ROW($C$30:$C$646)-MIN(ROW($B$30:$B$646))+1,""), ROW()-1)),"")}
B35: {=IFERROR(_xlfn.IFS(G9=0,"",G9>0,G9),"")} -> John Franco Morenos Rosales | C35: {=IFERROR(_xlfn.IFS(I9=0,"",I9>0,I9),"")} -> t | P35: Plan staffing | Q35: =F41 -> 23 | S35: =LOOKUP(U1,'Deployment needs'!$2:$2,'Deployment needs'!52:52) -> 23.431665 | U35: Redeployed -bulk (3.5) | V35: 4 | W35: 170 | X35: =W35*V35*$X$32 -> 1360 | AA35: {=IFERROR(INDEX($B$1:$B$272,SMALL(IF($O$17=$C$1:$C$272,ROW($C$1:$C$272)-MIN(ROW($B$1:$B$272))+1,""), ROW()-31)),"")} | AB35: {=IFERROR(INDEX($B$1:$B$272,SMALL(IF($O$18=$C$1:$C$272,ROW($C$1:$C$272)-MIN(ROW($B$1:$B$272))+1,""), ROW()-31)),"")} | AC35: {=IFERROR(INDEX($B$1:$B$272,SMALL(IF($O$33=$C$1:$C$272,ROW($C$1:$C$272)-MIN(ROW($B$1:$B$272))+1,""), ROW()-26)),"")} | AE35: {=IFERROR(INDEX($B$1:$B$272,SMALL(IF($O$29=$C$1:$C$272,ROW($C$1:$C$272)-MIN(ROW($B$1:$B$272))+1,""), ROW()-33)),"")} | AF35: {=IFERROR(INDEX($B$1:$B$272,SMALL(IF($O$23=$C$1:$C$272,ROW($C$1:$C$272)-MIN(ROW($B$1:$B$272))+1,""), ROW()-26)),"")} | AG35: {=IFERROR(INDEX($B$1:$B$272,SMALL(IF($O$25=$C$1:$C$272,ROW($C$1:$C$272)-MIN(ROW($B$1:$B$272))+1,""), ROW()-17)),"")} | AH35: {=IFERROR(INDEX($B$1:$B$272,SMALL(IF($O$32=$C$1:$C$272,ROW($C$1:$C$272)-MIN(ROW($B$1:$B$272))+1,""), ROW()-12)),"")} | AI35: {=IFERROR(INDEX($B$1:$B$30,SMALL(IF($O$4=$C$1:$C$30,ROW($C$1:$C$30)-MIN(ROW($B$1:$B$30))+1,""), ROW()-1)),"")} | AJ35: {=IFERROR(INDEX($B$30:$B$646,SMALL(IF($O$4=$C$30:$C$646,ROW($C$30:$C$646)-MIN(ROW($B$30:$B$646))+1,""), ROW()-1)),"")}
B36: {=IFERROR(_xlfn.IFS(G10=0,"",G10>0,G10),"")} -> David Almaguer-Benitez | C36: {=IFERROR(_xlfn.IFS(I10=0,"",I10>0,I10),"")} -> tr | P36: Total Absent | Q36: =Q35-Q34 -> 3 | U36: Picking- Singles | V36: 1 | W36: 200 | X36: =W36*V36*$V$32 -> 200 | AA36: {=IFERROR(INDEX($B$1:$B$272,SMALL(IF($O$17=$C$1:$C$272,ROW($C$1:$C$272)-MIN(ROW($B$1:$B$272))+1,""), ROW()-31)),"")} | AB36: {=IFERROR(INDEX($B$1:$B$272,SMALL(IF($O$18=$C$1:$C$272,ROW($C$1:$C$272)-MIN(ROW($B$1:$B$272))+1,""), ROW()-31)),"")} | AC36: {=IFERROR(INDEX($B$1:$B$272,SMALL(IF($O$33=$C$1:$C$272,ROW($C$1:$C$272)-MIN(ROW($B$1:$B$272))+1,""), ROW()-26)),"")} | AE36: {=IFERROR(INDEX($B$1:$B$272,SMALL(IF($O$29=$C$1:$C$272,ROW($C$1:$C$272)-MIN(ROW($B$1:$B$272))+1,""), ROW()-33)),"")} | AF36: {=IFERROR(INDEX($B$1:$B$272,SMALL(IF($O$23=$C$1:$C$272,ROW($C$1:$C$272)-MIN(ROW($B$1:$B$272))+1,""), ROW()-26)),"")} | AG36: {=IFERROR(INDEX($B$1:$B$272,SMALL(IF($O$25=$C$1:$C$272,ROW($C$1:$C$272)-MIN(ROW($B$1:$B$272))+1,""), ROW()-17)),"")} | AH36: {=IFERROR(INDEX($B$1:$B$272,SMALL(IF($O$32=$C$1:$C$272,ROW($C$1:$C$272)-MIN(ROW($B$1:$B$272))+1,""), ROW()-12)),"")} | AI36: {=IFERROR(INDEX($B$1:$B$30,SMALL(IF($O$4=$C$1:$C$30,ROW($C$1:$C$30)-MIN(ROW($B$1:$B$30))+1,""), ROW()-1)),"")} | AJ36: {=IFERROR(INDEX($B$30:$B$646,SMALL(IF($O$4=$C$30:$C$646,ROW($C$30:$C$646)-MIN(ROW($B$30:$B$646))+1,""), ROW()-1)),"")} | AL36: Rotationreturns putaway
B37: {=IFERROR(_xlfn.IFS(G11=0,"",G11>0,G11),"")} | C37: {=IFERROR(_xlfn.IFS(I11=0,"",I11>0,I11),"")} | E37: =COUNTIFS(E5:E35,"*") -> 17 | F37: =COUNTIFS(F5:F35,$O$38)+COUNTIFS(F5:F35,$O$39)+COUNTIFS(F5:F35,$O$40)+COUNTIFS(F5:F35,$O$41)+COUNTIFS(F5:F35,$O$42)+COUNTIFS(F5:F35,$O$43)+COUNTIFS(F5:F35,$O$44)+COUNTIFS(F5:F35,$O$45)+COUNTIFS(F5:F35,$O$199) -> 2 | G37: =COUNTIFS(G5:G35,"*") -> 6 | I37: =COUNTIFS(I5:I35,$O$38)+COUNTIFS(I5:I35,$O$39)+COUNTIFS(I5:I35,$O$40)+COUNTIFS(I5:I35,$O$41)+COUNTIFS(I5:I35,$O$42)+COUNTIFS(I5:I35,$O$43)+COUNTIFS(I5:I35,$O$44)+COUNTIFS(I5:I35,$O$45)+COUNTIFS(F5:I35,$O$199) -> 1 | J37: =COUNTIFS(L5:L36,"*") -> 0 | L37: =COUNTIFS(L5:L37,$O$78)+COUNTIFS(L5:L37,$O$79)+COUNTIFS(L5:L37,$O$195)+COUNTIFS(L5:L37,$O$196)+COUNTIFS(L5:L37,$O$197)+COUNTIFS(L5:L37,$O$198)+COUNTIFS(L5:L37,$O$200)+COUNTIFS(L5:L37,$O$201) -> 0 | P37: Attendance % | Q37: p | AA37: {=IFERROR(INDEX($B$1:$B$272,SMALL(IF($O$17=$C$1:$C$272,ROW($C$1:$C$272)-MIN(ROW($B$1:$B$272))+1,""), ROW()-31)),"")} | AB37: {=IFERROR(INDEX($B$1:$B$272,SMALL(IF($O$18=$C$1:$C$272,ROW($C$1:$C$272)-MIN(ROW($B$1:$B$272))+1,""), ROW()-31)),"")} | AC37: {=IFERROR(INDEX($B$1:$B$272,SMALL(IF($O$33=$C$1:$C$272,ROW($C$1:$C$272)-MIN(ROW($B$1:$B$272))+1,""), ROW()-26)),"")} | AE37: {=IFERROR(INDEX($B$1:$B$272,SMALL(IF($O$29=$C$1:$C$272,ROW($C$1:$C$272)-MIN(ROW($B$1:$B$272))+1,""), ROW()-33)),"")} | AF37: {=IFERROR(INDEX($B$1:$B$272,SMALL(IF($O$23=$C$1:$C$272,ROW($C$1:$C$272)-MIN(ROW($B$1:$B$272))+1,""), ROW()-26)),"")} | AG37: {=IFERROR(INDEX($B$1:$B$272,SMALL(IF($O$25=$C$1:$C$272,ROW($C$1:$C$272)-MIN(ROW($B$1:$B$272))+1,""), ROW()-17)),"")} | AH37: {=IFERROR(INDEX($B$1:$B$272,SMALL(IF($O$32=$C$1:$C$272,ROW($C$1:$C$272)-MIN(ROW($B$1:$B$272))+1,""), ROW()-12)),"")} | AI37: {=IFERROR(INDEX($B$1:$B$30,SMALL(IF($O$4=$C$1:$C$30,ROW($C$1:$C$30)-MIN(ROW($B$1:$B$30))+1,""), ROW()-1)),"")} | AJ37: {=IFERROR(INDEX($B$30:$B$646,SMALL(IF($O$4=$C$30:$C$646,ROW($C$30:$C$646)-MIN(ROW($B$30:$B$646))+1,""), ROW()-1)),"")} | AL37: Groups | AM37: Sunday | AN37: Monday | AO37: Tuesday | AP37: Wednesday | AQ37: Thursday | AR37: Friday | AS37: Saturday
B38: {=IFERROR(_xlfn.IFS(G12=0,"",G12>0,G12),"")} | C38: {=IFERROR(_xlfn.IFS(I12=0,"",I12>0,I12),"")} | O38: NC | P38: NC/NS | Q38: =COUNTIFS($F$5:$M$31,O38) -> 0 | U38: TOTAL | X38: =SUM(X34:X37) -> 11360 | AL38: 1st
B39: {=IFERROR(_xlfn.IFS(G13=0,"",G13>0,G13),"")} | C39: {=IFERROR(_xlfn.IFS(I13=0,"",I13>0,I13),"")} | E39: Headcount | F39: =E37+G37-F37-I37 -> 20 | O39: Call | P39: Call in | Q39: =COUNTIFS($F$5:$M$31,O39) -> 0
B40: {=IFERROR(_xlfn.IFS(G14=0,"",G14>0,G14),"")} | C40: {=IFERROR(_xlfn.IFS(I14=0,"",I14>0,I14),"")} | E40: FTE | F40: =E37+G37 -> 23 | O40: VTO | P40: VTO | Q40: =COUNTIFS($F$5:$M$31,O40) -> 0
B41: {=IFERROR(_xlfn.IFS(G15=0,"",G15>0,G15),"")} | C41: {=IFERROR(_xlfn.IFS(I15=0,"",I15>0,I15),"")} | E41: Actual | F41: =E37+G37 -> 23 | O41: PTO | P41: PTO | Q41: =COUNTIFS($F$5:$M$31,O41) -> 3 | U41: SLA other areas
B42: {=IFERROR(_xlfn.IFS(G16=0,"",G16>0,G16),"")} | C42: {=IFERROR(_xlfn.IFS(I16=0,"",I16>0,I16),"")} | O42: Vol | P42: Volunteer | Q42: =COUNTIFS($F$5:$M$31,O42) -> 0 | U42: Area | V42: # folks | W42: UPH | X42: SLA | AA42: NCNS | AB42: Call in | AC42: FMLA | AE42: PTO | AF42: VTO | AG42: Leave Early | AH42: Not Schedule to Work | AI42: Volunteer
B43: {=IFERROR(_xlfn.IFS(G17=0,"",G17>0,G17),"")} | C43: {=IFERROR(_xlfn.IFS(I17=0,"",I17>0,I17),"")} | K43: Potencial deployment GIG | O43: L | P43: leave early/late arrival | Q43: =COUNTIFS($F$5:$M$31,O43) -> 0 | U43: Returns Processing | V43: =Q22-0.5 -> 2.5 | W43: =Narvar -> 34 | X43: =(W43*V43*$Y$27) -> 0 | Z43: 1 | AA43: {=_xlfn._xlws.FILTER($B$1:$B$107, $C$1:$C$107=$O$38, "")} | AB43: {=_xlfn._xlws.FILTER($B$1:$B$107, $C$1:$C$107=$O$39, "")} | AC43: {=_xlfn._xlws.FILTER($B$1:$B$107, $C$1:$C$107=$O$44, "")} | AE43: {=_xlfn._xlws.FILTER($B$1:$B$107, $C$1:$C$107=$O$41, "")} -> Esther Fonseca | AF43: {=_xlfn._xlws.FILTER($B$1:$B$107, $C$1:$C$107=$O$40, "")} | AG43: {=_xlfn._xlws.FILTER($B$1:$B$107, $C$1:$C$107=$O$43, "")} | AH43: {=_xlfn._xlws.FILTER($B$1:$B$107, $C$1:$C$107=$O$45, "")} | AI43: {=_xlfn._xlws.FILTER($B$1:$B$107, $C$1:$C$107=$O$42, "")}
B44: {=IFERROR(_xlfn.IFS(G18=0,"",G18>0,G18),"")} | C44: {=IFERROR(_xlfn.IFS(I18=0,"",I18>0,I18),"")} | K44: Compactor | L44: 0 | O44: FMLA | P44: FMLA | Q44: =COUNTIFS($F$5:$M$31,O44) -> 0 | U44: Returns Exceptions | V44: =Q23 -> 0 | W44: =Exceptions -> 25 | X44: =(W44*V44*(2)) -> 0 | Z44: 2 | AE44: Laura Gonzalez Bustamante
B45: {=IFERROR(_xlfn.IFS(G19=0,"",G19>0,G19),"")} | C45: {=IFERROR(_xlfn.IFS(I19=0,"",I19>0,I19),"")} | E45: A team | G45: B team | K45: Trash | L45: 0 | O45: x | P45: No Schedule to work | Q45: =COUNTIFS($F$5:$M$31,O45) -> 0 | U45: Returns put-away | V45: =Q25 -> 0 | W45: =Returns_put_away -> 100 | X45: =(W45*V45*($Y$27-1)) -> 0 | Z45: 3 | AE45: Jose Posse
B46: {=IFERROR(_xlfn.IFS(G20=0,"",G20>0,G20),"")} | C46: {=IFERROR(_xlfn.IFS(I20=0,"",I20>0,I20),"")} | E46: Hector Roacha | G46: Belisario Gonzalez Arevalo | K46: Cartbulding | L46: 0 | U46: Receiving | V46: =Q26 -> 0 | W46: =Receiving -> 75 | X46: =(W46*V46*$Y$27)/2.45 -> 0 | Z46: 4 | AL46: 2nd
B47: {=IFERROR(_xlfn.IFS(G21=0,"",G21>0,G21),"")} | C47: {=IFERROR(_xlfn.IFS(I21=0,"",I21>0,I21),"")} | E47: Arnolda Vega | G47: Chrissy Parisek | K47: Taper | L47: 0 | U47: Resets | V47: =Q11 -> 1 | W47: =Resets_per_hour -> 20 | X47: =(W47*V47*$Y$27) -> 0 | Z47: 5
B48: {=IFERROR(_xlfn.IFS(G22=0,"",G22>0,G22),"")} | C48: {=IFERROR(_xlfn.IFS(I22=0,"",I22>0,I22),"")} | E48: Yasmin Montero | G48: Jose Posse | K48: Truck | L48: 0 | U48: Bander | V48: =Q9 -> 5 | W48: =Autobagger_Bander -> 120 | X48: =(W48*V48*$Y$27)/2 -> 0 | Z48: 6
B49: {=IFERROR(_xlfn.IFS(G23=0,"",G23>0,G23),"")} | C49: {=IFERROR(_xlfn.IFS(I23=0,"",I23>0,I23),"")} | E49: Iraldo Rodriguez | G49: Esther Fonseca | K49: Bander | L49: 4 | U49: Autobagger | V49: =Q10 -> 1 | W49: =Autobagger_Operator -> 600 | X49: =(W49*V49*$Y$27) -> 0 | Z49: 7
B50: {=IFERROR(_xlfn.IFS(G24=0,"",G24>0,G24),"")} | C50: {=IFERROR(_xlfn.IFS(I24=0,"",I24>0,I24),"")} | E50: Dania Curbelo | G50: Annaliet Rodriguez Perez | K50: Total | L50: =SUM(L44:L49) -> 4 | U50: Overstock putaway | V50: =Q18 -> 1 | W50: =Overstock -> 50 | X50: =(W50*V50*$Y$27) -> 0 | Z50: 8
B51: {=IFERROR(_xlfn.IFS(G25=0,"",G25>0,G25),"")} | C51: {=IFERROR(_xlfn.IFS(I25=0,"",I25>0,I25),"")}
B52: {=IFERROR(_xlfn.IFS(G26=0,"",G26>0,G26),"")} | C52: {=IFERROR(_xlfn.IFS(I26=0,"",I26>0,I26),"")} | E52: Damaris Curbelo | G52: Madelayne Oduardo | U52: Replen Pull | V52: =Q19 -> 0 | W52: =Replenishment_pull -> 45 | X52: =(W52*V52*$Y$27) -> 0 | Z52: 9
B53: {=IFERROR(_xlfn.IFS(G27=0,"",G27>0,G27),"")} | C53: {=IFERROR(_xlfn.IFS(I27=0,"",I27>0,I27),"")} | E53: Roxana Lloret | G53: Brandee Foster | U53: Replen Throw | V53: =Q20 -> 0 | W53: =Replenishment_throw -> 35 | X53: =(W53*V53*$Y$27) -> 0 | Z53: 10
B54: {=IFERROR(_xlfn.IFS(G28=0,"",G28>0,G28),"")} | C54: {=IFERROR(_xlfn.IFS(I28=0,"",I28>0,I28),"")} | E54: Mercedes Carasco | G54: Mbaya Kapita | U54: region | V54: # pickers | W54: UPH | X54: estimate | Z54: 11
B55: {=IFERROR(_xlfn.IFS(G29=0,"",G29>0,G29),"")} | C55: {=IFERROR(_xlfn.IFS(I29=0,"",I29>0,I29),"")} | E55: Jose Miro Quintana | G55: Jackie Gomez | U55: Picking- Bulk | V55: =Q26 -> 0 | W55: 160 | X55: =W55*V55*$W$29 -> 0 | Y55: Projected 1st Shift | Z55: 12
B56: {=IFERROR(_xlfn.IFS(G30=0,"",G30>0,G30),"")} | C56: {=IFERROR(_xlfn.IFS(I30=0,"",I30>0,I30),"")} | E56: Yordanka Manzanares | G56: Shvodra Anderson | U56: Picking- Singles | V56: =Q27 -> 0 | W56: 200 | X56: =W56*V56*$Y$24/2 -> 0 | Y56: =V62*W62*X62 -> 0 | Z56: 13
B57: {=IFERROR(_xlfn.IFS(G31=0,"",G31>0,G31),"")} | C57: {=IFERROR(_xlfn.IFS(I31=0,"",I31>0,I31),"")} | E57: Laura Bustamante | Y57: =V63*W63*X63 -> 24000 | Z57: 14
B58: {=IFERROR(_xlfn.IFS(G32=0,"",G32>0,G32),"")} | C58: {=IFERROR(_xlfn.IFS(I32=0,"",I32>0,I32),"")} | U58: TOTAL | X58: =SUM(X55:X57) -> 0 | Y58: =SUM(Y56:Y57) -> 24000 | Z58: 15
B59: {=IFERROR(_xlfn.IFS(G33=0,"",G33>0,G33),"")} | C59: {=IFERROR(_xlfn.IFS(I33=0,"",I33>0,I33),"")} | Z59: 16
B60: {=IFERROR(_xlfn.IFS(G34=0,"",G34>0,G34),"")} | C60: {=IFERROR(_xlfn.IFS(I34=0,"",I34>0,I34),"")} | Y60: =V66*X66 -> 0
B61: {=IFERROR(_xlfn.IFS(G35=0,"",G35>0,G35),"")} | C61: {=IFERROR(_xlfn.IFS(I35=0,"",I35>0,I35),"")} | E61: Ongoing Projects | V61: Average UPH | W61: Employee count | X61: Expected hours | Y61: =V67*W67*X67 -> 8000
E62: Condensing Aisle 7 wholesale locations - Jose instructed on process and working last hour of 3/11 | U62: Veterans | V62: 180 | W62: 0 | X62: 0 | Y62: =V68*W68*X68 -> 0
E63: Manual Holiday item movements from picking to Overstock - In Process | U63: New Hires | V63: 150 | W63: 20 | X63: 8 | Y63: =SUM(Y60:Y62) -> 8000
X64: Total
Y65: =Y58-Y63 -> 16000
U66: Leave early | V66: 170 | W66: 0 | X66: 0
U67: Absents | V67: 160 | W67: 5 | X67: 10
U68: System Downtime
X69: Units Lost
X71: Total Units
T223: Veterans
T224: New Hires
T227: Leave early
T228: Absents | U228: Average UPH | V228: Employee count | W228: Expected hours | X228: Projected 1st Shift
T229: System Downtime | U229: 180 | V229: 0 | W229: 0 | X229: =U229*V229*W229 -> 0
U230: 150 | V230: 20 | W230: 8 | X230: =U230*V230*W230 -> 24000
W231: Total | X231: =SUM(X229:X230) -> 24000
U233: 170 | V233: 0 | W233: 0 | X233: =U233*W233 -> 0
U234: 160 | V234: 5 | W234: 10 | X234: =U234*V234*W234 -> 8000
X235: =U235*V235*W235 -> 0
W236: Units Lost | X236: =SUM(X233:X235) -> 8000
W238: Total Units | X238: =X231-X236 -> 16000
B275: {=IFERROR(_xlfn.IFS(K5=0,"",K5>0,K5),"")} | C275: {=IFERROR(_xlfn.IFS(L5=0,"",L5>0,L5),"")}
B276: {=IFERROR(_xlfn.IFS(L24=0,"",L24>0,L24),"")} | C276: {=IFERROR(_xlfn.IFS(L6=0,"",L6>0,L6),"")}
B277: {=IFERROR(_xlfn.IFS(K7=0,"",K7>0,K7),"")} | C277: {=IFERROR(_xlfn.IFS(L7=0,"",L7>0,L7),"")}
B278: {=IFERROR(_xlfn.IFS(K8=0,"",K8>0,K8),"")} | C278: {=IFERROR(_xlfn.IFS(L8=0,"",L8>0,L8),"")}
B279: {=IFERROR(_xlfn.IFS(K9=0,"",K9>0,K9),"")} | C279: {=IFERROR(_xlfn.IFS(L9=0,"",L9>0,L9),"")}
B280: {=IFERROR(_xlfn.IFS(K10=0,"",K10>0,K10),"")} | C280: {=IFERROR(_xlfn.IFS(L10=0,"",L10>0,L10),"")}
B281: {=IFERROR(_xlfn.IFS(K11=0,"",K11>0,K11),"")} | C281: {=IFERROR(_xlfn.IFS(L11=0,"",L11>0,L11),"")}
B282: {=IFERROR(_xlfn.IFS(K12=0,"",K12>0,K12),"")} | C282: {=IFERROR(_xlfn.IFS(L12=0,"",L12>0,L12),"")}
B283: {=IFERROR(_xlfn.IFS(K13=0,"",K13>0,K13),"")} | C283: {=IFERROR(_xlfn.IFS(L13=0,"",L13>0,L13),"")}
B284: {=IFERROR(_xlfn.IFS(K14=0,"",K14>0,K14),"")} | C284: {=IFERROR(_xlfn.IFS(L14=0,"",L14>0,L14),"")}
B285: {=IFERROR(_xlfn.IFS(K15=0,"",K15>0,K15),"")} | C285: {=IFERROR(_xlfn.IFS(L15=0,"",L15>0,L15),"")}
B286: {=IFERROR(_xlfn.IFS(K16=0,"",K16>0,K16),"")} | C286: {=IFERROR(_xlfn.IFS(L16=0,"",L16>0,L16),"")}
B287: {=IFERROR(_xlfn.IFS(#REF!=0,"",#REF!>0,#REF!),"")} | C287: {=IFERROR(_xlfn.IFS(L17=0,"",L17>0,L17),"")}
B288: {=IFERROR(_xlfn.IFS(K17=0,"",K17>0,K17),"")} | C288: {=IFERROR(_xlfn.IFS(L18=0,"",L18>0,L18),"")}
B289: {=IFERROR(_xlfn.IFS(K35=0,"",K35>0,K35),"")} | C289: {=IFERROR(_xlfn.IFS(L35=0,"",L35>0,L35),"")}
B290: {=IFERROR(_xlfn.IFS(K36=0,"",K36>0,K36),"")} | C290: {=IFERROR(_xlfn.IFS(L36=0,"",L36>0,L36),"")}
B320: ='Wknd Shift'!A16
B321: ='Wknd Shift'!A17
...

Sheet 2nd Shift
A1: {=_xlfn.IFS(C5=0,"",C5>0,C5)} -> Jonat Gordis | B1: {=_xlfn.IFS(F5=0,"",F5>0,F5)} -> i | C1: 2nd shift Deployment | J1: GIG / Temp Employees | P1: DC Daily Goal | Q1: =LOOKUP(R1,'Deployment needs'!$2:$2,'Deployment needs'!$5:$5) -> 13000 | R1: =TODAY() -> 46189 | X1: Units at SOS 4:30 | Z1: Outbound | AA1: Cart Building | AB1: AB Super User | AC1: AB Bander | AE1: Shipping | AF1: Taper | AG1: Special Projects | AH1: Training | AI1: {="Picking "&SUMPRODUCT(--(TRIM(AI2:AI37)<>""))} -> Picking 0 | AJ1: {="Picking "&SUMPRODUCT(--(TRIM(AJ2:AJ37)<>""))} -> Picking 30 | AK1: Rotation AB | AR1: EOM | AS1: Winner | AT1: Nominees | AU1: Production | AV1: Attendance ( call/ tardy/early exit) | AW1: Employees | AX1: Hire date | AY1: service
A2: {=_xlfn.IFS(C6=0,"",C6>0,C6)} -> Alma Mehic- IL | B2: {=_xlfn.IFS(F6=0,"",F6>0,F6)} -> i | P2: 2nd shift goal GM | Q2: =LOOKUP(R1,'Deployment needs'!$2:$2,'Deployment needs'!$101:$101) -> 5850 | U2: OB SNAP SHOT | W2: days out | X2: Available | Y2: 11109 | AA2: {=IFERROR(INDEX($A$1:$A$107,SMALL(IF($O$5=$B$1:$B$107,ROW($B$1:$B$107)-MIN(ROW($A$1:$A$107))+1,""), ROW()-1)),"")} -> Yulianela Gonzalez Sanchez | AB2: {=IFERROR(INDEX($A$1:$A$100,SMALL(IF($O$12=$B$1:$B$100,ROW($B$1:$B$100)-MIN(ROW($A$1:$A$100))+1,""), ROW()-1)),"")} -> Ana Maria Suarez | AC2: {=IFERROR(INDEX($A$1:$A$107,SMALL(IF($O$11=$B$1:$B$107,ROW($B$1:$B$107)-MIN(ROW($A$1:$A$107))+1,""), ROW()-1)),"")} -> Nolberto falcon | AE2: {=IFERROR(INDEX($A$1:$A$107,SMALL(IF($O$8=$B$1:$B$107,ROW($B$1:$B$107)-MIN(ROW($A$1:$A$107))+1,""), ROW()-1)),"")} | AF2: {=IFERROR(INDEX($A$1:$A$107,SMALL(IF($O$10=$B$1:$B$107,ROW($B$1:$B$107)-MIN(ROW($A$1:$A$107))+1,""), ROW()-1)),"")} | AG2: {=IFERROR(INDEX($A$1:$A$107,SMALL(IF($O$31=$B$1:$B$107,ROW($B$1:$B$107)-MIN(ROW($A$1:$A$107))+1,""), ROW()-1)),"")} | AH2: {=IFERROR(INDEX($A$1:$A$107,SMALL(IF($O$22=$B$1:$B$107,ROW($B$1:$B$107)-MIN(ROW($A$1:$A$107))+1,""), ROW()-1)),"")} | AI2: {=IFERROR(INDEX($A$1:$A$107,SMALL(IF($O$6=$B$1:$B$107,ROW($B$1:$B$107)-MIN(ROW($A$1:$A$107))+1,""), ROW()-1)),"")} | AJ2: {=IFERROR(INDEX($A$71:$A$100,SMALL(IF($M$6=$B$71:$B$100,ROW($B$71:$B$100)-MIN(ROW($A$71:$A$100))+1,""), ROW()-1)),"")} -> 0 | AK2: Groups | AL2: Sunday | AM2: Monday | AN2: Tuesday | AO2: Wednesday | AP2: Thursday | AR2: 45383 | AS2: Alma | AT2: Isabel
A3: {=_xlfn.IFS(C7=0,"",C7>0,C7)} -> Nolberto falcon | B3: {=_xlfn.IFS(F7=0,"",F7>0,F7)} -> b | C3: Hanna employees | J3: GIG / Temp Employees | P3: Succession Goal | Q3: ='2nd Shift'!U9-U11 -> 5348 | T3: * | U3: 62 | V3: Clustered Carts | X3: Open | Y3: 3018 | AA3: {=IFERROR(INDEX($A$1:$A$107,SMALL(IF($O$5=$B$1:$B$107,ROW($B$1:$B$107)-MIN(ROW($A$1:$A$107))+1,""), ROW()-1)),"")} -> Liudmila Gonzalez Caballero | AB3: {=IFERROR(INDEX($A$1:$A$100,SMALL(IF($O$12=$B$1:$B$100,ROW($B$1:$B$100)-MIN(ROW($A$1:$A$100))+1,""), ROW()-1)),"")} -> Leidy Laura Riera | AC3: {=IFERROR(INDEX($A$1:$A$107,SMALL(IF($O$11=$B$1:$B$107,ROW($B$1:$B$107)-MIN(ROW($A$1:$A$107))+1,""), ROW()-1)),"")} -> Lisbet Moro Valero | AE3: {=IFERROR(INDEX($A$1:$A$107,SMALL(IF($O$8=$B$1:$B$107,ROW($B$1:$B$107)-MIN(ROW($A$1:$A$107))+1,""), ROW()-1)),"")} | AF3: {=IFERROR(INDEX($A$1:$A$107,SMALL(IF($O$10=$B$1:$B$107,ROW($B$1:$B$107)-MIN(ROW($A$1:$A$107))+1,""), ROW()-1)),"")} | AG3: {=IFERROR(INDEX($A$1:$A$107,SMALL(IF($O$31=$B$1:$B$107,ROW($B$1:$B$107)-MIN(ROW($A$1:$A$107))+1,""), ROW()-1)),"")} | AH3: {=IFERROR(INDEX($A$1:$A$107,SMALL(IF($O$22=$B$1:$B$107,ROW($B$1:$B$107)-MIN(ROW($A$1:$A$107))+1,""), ROW()-1)),"")} | AI3: {=IFERROR(INDEX($A$1:$A$107,SMALL(IF($O$6=$B$1:$B$107,ROW($B$1:$B$107)-MIN(ROW($A$1:$A$107))+1,""), ROW()-1)),"")} | AJ3: {=IFERROR(INDEX($A$71:$A$100,SMALL(IF($M$6=$B$71:$B$100,ROW($B$71:$B$100)-MIN(ROW($A$71:$A$100))+1,""), ROW()-1)),"")} -> 0 | AL3: Juana | AM3: Marigeritte | AN3: Yulianela | AO3: Inima | AR3: 45413 | AS3: Kenia | AW3: Alma Mehic | AX3: 42666 | AY3: =DATEDIF(AX3, TODAY(), "Y") & " year(s) " & DATEDIF(AX3, TODAY(), "YM") & " month(s) " & DATEDIF(AX3, TODAY(), "MD") & " day(s)" -> 9 year(s) 7 month(s) 24 day(s)
A4: {=_xlfn.IFS(C8=0,"",C8>0,C8)} -> Yulianela Gonzalez Sanchez | B4: {=_xlfn.IFS(F8=0,"",F8>0,F8)} -> cb | C4: Hanna Names | F4: area | G4: Hanna Names | I4: area | J4: Names | L4: area | M4: dept | O4: Key | P4: DC Deployment | R4: Work | S4: GM Plan | T4: * | U4: 46188 | V4: Multi to pick | W4: 1 | X4: Unwaved | Y4: 335 | AA4: {=IFERROR(INDEX($A$1:$A$107,SMALL(IF($O$5=$B$1:$B$107,ROW($B$1:$B$107)-MIN(ROW($A$1:$A$107))+1,""), ROW()-1)),"")} | AB4: {=IFERROR(INDEX($A$1:$A$100,SMALL(IF($O$12=$B$1:$B$100,ROW($B$1:$B$100)-MIN(ROW($A$1:$A$100))+1,""), ROW()-1)),"")} | AC4: {=IFERROR(INDEX($A$1:$A$107,SMALL(IF($O$11=$B$1:$B$107,ROW($B$1:$B$107)-MIN(ROW($A$1:$A$107))+1,""), ROW()-1)),"")} -> Marigeritte Mugelanya | AE4: {=IFERROR(INDEX($A$1:$A$107,SMALL(IF($O$8=$B$1:$B$107,ROW($B$1:$B$107)-MIN(ROW($A$1:$A$107))+1,""), ROW()-1)),"")} | AF4: {=IFERROR(INDEX($A$1:$A$107,SMALL(IF($O$10=$B$1:$B$107,ROW($B$1:$B$107)-MIN(ROW($A$1:$A$107))+1,""), ROW()-1)),"")} | AG4: {=IFERROR(INDEX($A$1:$A$107,SMALL(IF($O$31=$B$1:$B$107,ROW($B$1:$B$107)-MIN(ROW($A$1:$A$107))+1,""), ROW()-1)),"")} | AH4: {=IFERROR(INDEX($A$1:$A$107,SMALL(IF($O$22=$B$1:$B$107,ROW($B$1:$B$107)-MIN(ROW($A$1:$A$107))+1,""), ROW()-1)),"")} | AI4: {=IFERROR(INDEX($A$1:$A$107,SMALL(IF($O$6=$B$1:$B$107,ROW($B$1:$B$107)-MIN(ROW($A$1:$A$107))+1,""), ROW()-1)),"")} | AJ4: {=IFERROR(INDEX($A$71:$A$100,SMALL(IF($M$6=$B$71:$B$100,ROW($B$71:$B$100)-MIN(ROW($A$71:$A$100))+1,""), ROW()-1)),"")} -> 0 | AL4: Aliuska | AM4: Adriana | AN4: Dayana | AO4: Juana | AR4: 45444 | AS4: Jonat | AW4: Alexcy Garcia | AX4: 43318 | AY4: =DATEDIF(AX4, TODAY(), "Y") & " year(s) " & DATEDIF(AX4, TODAY(), "YM") & " month(s) " & DATEDIF(AX4, TODAY(), "MD") & " day(s)" -> 7 year(s) 10 month(s) 10 day(s)
A5: {=_xlfn.IFS(C9=0,"",C9>0,C9)} -> Xiomara Castro Dominquez | B5: {=_xlfn.IFS(F9=0,"",F9>0,F9)} -> pto | C5: Jonat Gordis | E5: FT | F5: i | G5: Liudmila Gonzalez Caballero | H5: FT | I5: cb | J5: 4:30 team | O5: CB | P5: Cartbuilding | Q5: =COUNTIFS($F$5:$L$34,O5) -> 2 | R5: =Y3 -> 3018 | S5: =LOOKUP(R1,'Deployment needs'!$2:$2,'Deployment needs'!106:106) -> 0.39583333 | T5: * | U5: 46188 | V5: To cluster | W5: 1 | X5: Held/rep | Y5: 1349 | AA5: {=IFERROR(INDEX($A$1:$A$107,SMALL(IF($O$5=$B$1:$B$107,ROW($B$1:$B$107)-MIN(ROW($A$1:$A$107))+1,""), ROW()-1)),"")} | AB5: {=IFERROR(INDEX($A$1:$A$100,SMALL(IF($O$12=$B$1:$B$100,ROW($B$1:$B$100)-MIN(ROW($A$1:$A$100))+1,""), ROW()-1)),"")} | AC5: {=IFERROR(INDEX($A$1:$A$107,SMALL(IF($O$11=$B$1:$B$107,ROW($B$1:$B$107)-MIN(ROW($A$1:$A$107))+1,""), ROW()-1)),"")} -> Adrian Sanchez Avila | AE5: {=IFERROR(INDEX($A$1:$A$107,SMALL(IF($O$8=$B$1:$B$107,ROW($B$1:$B$107)-MIN(ROW($A$1:$A$107))+1,""), ROW()-1)),"")} | AF5: {=IFERROR(INDEX($A$1:$A$107,SMALL(IF($O$10=$B$1:$B$107,ROW($B$1:$B$107)-MIN(ROW($A$1:$A$107))+1,""), ROW()-1)),"")} | AG5: {=IFERROR(INDEX($A$1:$A$107,SMALL(IF($O$31=$B$1:$B$107,ROW($B$1:$B$107)-MIN(ROW($A$1:$A$107))+1,""), ROW()-1)),"")} | AH5: {=IFERROR(INDEX($A$1:$A$107,SMALL(IF($O$22=$B$1:$B$107,ROW($B$1:$B$107)-MIN(ROW($A$1:$A$107))+1,""), ROW()-1)),"")} | AI5: {=IFERROR(INDEX($A$1:$A$107,SMALL(IF($O$6=$B$1:$B$107,ROW($B$1:$B$107)-MIN(ROW($A$1:$A$107))+1,""), ROW()-1)),"")} | AJ5: {=IFERROR(INDEX($A$71:$A$100,SMALL(IF($M$6=$B$71:$B$100,ROW($B$71:$B$100)-MIN(ROW($A$71:$A$100))+1,""), ROW()-1)),"")} -> 0 | AR5: 45474 | AS5: Jonathan | AT5: Jonat | AW5: Aliuska Almira Mateo | AX5: 43340 | AY5: =DATEDIF(AX5, TODAY(), "Y") & " year(s) " & DATEDIF(AX5, TODAY(), "YM") & " month(s) " & DATEDIF(AX5, TODAY(), "MD") & " day(s)" -> 7 year(s) 9 month(s) 19 day(s)
A6: {=_xlfn.IFS(C10=0,"",C10>0,C10)} -> Aliuska Almira Mateo | B6: {=_xlfn.IFS(F10=0,"",F10>0,F10)} -> rn | C6: Alma Mehic- IL | E6: FT | F6: i | G6: Adrian Sanchez Avila | H6: FT | I6: b | O6: P | P6: Picking- Bulk | Q6: =COUNTIFS($F$5:$L$34,O6) -> 0 | R6: =Y2 -> 11109 | S6: =LOOKUP(R1,'Deployment needs'!$2:$2,'Deployment needs'!102:102) -> 3.1666667 | T6: * | U6: 46188 | V6: Singles to pick | W6: 1 | X6: In process | Y6: 232 | AA6: {=IFERROR(INDEX($A$1:$A$107,SMALL(IF($O$5=$B$1:$B$107,ROW($B$1:$B$107)-MIN(ROW($A$1:$A$107))+1,""), ROW()-1)),"")} | AB6: {=IFERROR(INDEX($A$1:$A$100,SMALL(IF($O$12=$B$1:$B$100,ROW($B$1:$B$100)-MIN(ROW($A$1:$A$100))+1,""), ROW()-1)),"")} | AC6: {=IFERROR(INDEX($A$1:$A$107,SMALL(IF($O$11=$B$1:$B$107,ROW($B$1:$B$107)-MIN(ROW($A$1:$A$107))+1,""), ROW()-1)),"")} | AE6: {=IFERROR(INDEX($A$1:$A$107,SMALL(IF($O$8=$B$1:$B$107,ROW($B$1:$B$107)-MIN(ROW($A$1:$A$107))+1,""), ROW()-1)),"")} | AF6: Truck | AG6: Baby Bundle Project | AH6: {=IFERROR(INDEX($A$1:$A$107,SMALL(IF($O$22=$B$1:$B$107,ROW($B$1:$B$107)-MIN(ROW($A$1:$A$107))+1,""), ROW()-1)),"")} | AI6: {=IFERROR(INDEX($A$1:$A$107,SMALL(IF($O$6=$B$1:$B$107,ROW($B$1:$B$107)-MIN(ROW($A$1:$A$107))+1,""), ROW()-1)),"")} | AJ6: {=IFERROR(INDEX($A$71:$A$100,SMALL(IF($M$6=$B$71:$B$100,ROW($B$71:$B$100)-MIN(ROW($A$71:$A$100))+1,""), ROW()-1)),"")} -> 0 | AR6: 45505 | AS6: Xiomara | AT6: Jonathan | AW6: Kenia Rodriguez Gonzalez | AX6: 43762 | AY6: =DATEDIF(AX6, TODAY(), "Y") & " year(s) " & DATEDIF(AX6, TODAY(), "YM") & " month(s) " & DATEDIF(AX6, TODAY(), "MD") & " day(s)" -> 6 year(s) 7 month(s) 23 day(s)
A7: {=_xlfn.IFS(C11=0,"",C11>0,C11)} -> Ana Maria Suarez | B7: {=_xlfn.IFS(F11=0,"",F11>0,F11)} -> ab | C7: Nolberto falcon | E7: 03/15/2026 AG | F7: b | G7: Carlos Agramonte Mendoza | I7: i | O7: SN | P7: Picking- Singles | Q7: =COUNTIFS($F$5:$L$34,O7) -> 1 | R7: =COUNTIFS($F$5:$L$52,P7) -> 0 | S7: =LOOKUP(R1,'Deployment needs'!$2:$2,'Deployment needs'!103:103) -> 0.1625 | T7: * | U7: 46188 | V7: Singles to Ship | W7: 1 | X7: Bander 4:30 | Y7: 2486 | AA7: {=IFERROR(INDEX($A$1:$A$107,SMALL(IF($O$5=$B$1:$B$107,ROW($B$1:$B$107)-MIN(ROW($A$1:$A$107))+1,""), ROW()-1)),"")} | AB7: Pick Singles | AC7: {=IFERROR(INDEX($A$1:$A$107,SMALL(IF($O$11=$B$1:$B$107,ROW($B$1:$B$107)-MIN(ROW($A$1:$A$107))+1,""), ROW()-1)),"")} | AE7: {=IFERROR(INDEX($A$1:$A$107,SMALL(IF($O$8=$B$1:$B$107,ROW($B$1:$B$107)-MIN(ROW($A$1:$A$107))+1,""), ROW()-1)),"")} | AF7: {=IFERROR(INDEX($A$1:$A$107,SMALL(IF($O$9=$B$1:$B$107,ROW($B$1:$B$107)-MIN(ROW($A$1:$A$107))+1,""), ROW()-6)),"")} -> Jonathan Koerner | AG7: {=IFERROR(INDEX($A$1:$A$107,SMALL(IF($O$28=$B$1:$B$107,ROW($B$1:$B$107)-MIN(ROW($A$1:$A$107))+1,""), ROW()-6)),"")} | AH7: {=IFERROR(INDEX($A$1:$A$107,SMALL(IF($O$22=$B$1:$B$107,ROW($B$1:$B$107)-MIN(ROW($A$1:$A$107))+1,""), ROW()-1)),"")} | AI7: {=IFERROR(INDEX($A$1:$A$107,SMALL(IF($O$6=$B$1:$B$107,ROW($B$1:$B$107)-MIN(ROW($A$1:$A$107))+1,""), ROW()-1)),"")} | AJ7: {=IFERROR(INDEX($A$71:$A$100,SMALL(IF($M$6=$B$71:$B$100,ROW($B$71:$B$100)-MIN(ROW($A$71:$A$100))+1,""), ROW()-1)),"")} -> 0 | AK7: 2nd | AL7: idelmis | AM7: Arlyn | AN7: Jacqueline | AO7: Idelmidis | AR7: 45536 | AS7: Freddy | AT7: Xiomara | AW7: Jonat Gordis Pino | AX7: 43780 | AY7: =DATEDIF(AX7, TODAY(), "Y") & " year(s) " & DATEDIF(AX7, TODAY(), "YM") & " month(s) " & DATEDIF(AX7, TODAY(), "MD") & " day(s)" -> 6 year(s) 7 month(s) 5 day(s)
A8: {=_xlfn.IFS(C12=0,"",C12>0,C12)} -> Freddy Sossa | B8: {=_xlfn.IFS(F12=0,"",F12>0,F12)} -> rt | C8: Yulianela Gonzalez Sanchez | E8: FT | F8: cb | G8: Sandy Menoya | I8: b | O8: S | P8: Shipping | Q8: =COUNTIFS($F$5:$L$34,O8) -> 0 | S8: {=LOOKUP(R1,'Deployment needs'!$2:$2,('Deployment needs'!105:105+'Deployment needs'!104:104))} -> 0.88833333 | T8: * | U8: 3.9 | V8: UPP | X8: Total units | Y8: =SUM(Y2:Y7) -> 18529 | AA8: Lead - Support/Trainer | AB8: {=IFERROR(INDEX($A$1:$A$107,SMALL(IF($O$7=$B$1:$B$107,ROW($B$1:$B$107)-MIN(ROW($A$1:$A$107))+1,""), ROW()-7)),"")} -> Isabel Hernandez Garcia | AC8: {=IFERROR(INDEX($A$1:$A$107,SMALL(IF($O$11=$B$1:$B$107,ROW($B$1:$B$107)-MIN(ROW($A$1:$A$107))+1,""), ROW()-1)),"")} | AE8: {=IFERROR(INDEX($A$1:$A$107,SMALL(IF($O$8=$B$1:$B$107,ROW($B$1:$B$107)-MIN(ROW($A$1:$A$107))+1,""), ROW()-1)),"")} | AF8: {=IFERROR(INDEX($A$1:$A$107,SMALL(IF($O$9=$B$1:$B$107,ROW($B$1:$B$107)-MIN(ROW($A$1:$A$107))+1,""), ROW()-6)),"")} | AG8: {=IFERROR(INDEX($A$1:$A$107,SMALL(IF($O$28=$B$1:$B$107,ROW($B$1:$B$107)-MIN(ROW($A$1:$A$107))+1,""), ROW()-6)),"")} | AH8: {=IFERROR(INDEX($A$1:$A$107,SMALL(IF($O$22=$B$1:$B$107,ROW($B$1:$B$107)-MIN(ROW($A$1:$A$107))+1,""), ROW()-1)),"")} | AI8: {=IFERROR(INDEX($A$1:$A$107,SMALL(IF($O$6=$B$1:$B$107,ROW($B$1:$B$107)-MIN(ROW($A$1:$A$107))+1,""), ROW()-1)),"")} | AJ8: {=IFERROR(INDEX($A$71:$A$100,SMALL(IF($M$6=$B$71:$B$100,ROW($B$71:$B$100)-MIN(ROW($A$71:$A$100))+1,""), ROW()-1)),"")} -> 0 | AL8: Xiomara | AM8: Lisandra | AN8: Yulemis | AO8: Aliuska | AR8: 45566 | AS8: Elian | AT8: Freddy | AW8: Isabel Hernandez Garcia | AX8: 43796 | AY8: =DATEDIF(AX8, TODAY(), "Y") & " year(s) " & DATEDIF(AX8, TODAY(), "YM") & " month(s) " & DATEDIF(AX8, TODAY(), "MD") & " day(s)" -> 6 year(s) 6 month(s) 20 day(s)
A9: {=_xlfn.IFS(C13=0,"",C13>0,C13)} -> Idelmis Infante Silva | B9: {=_xlfn.IFS(F13=0,"",F13>0,F13)} -> LOA | C9: Xiomara Castro Dominquez | E9: 03/15/2026 AG | F9: pto | G9: Eunice Ramires Fernandez | I9: b | O9: TR | P9: Truck loading | Q9: =COUNTIFS($F$5:$L$34,O9) -> 1 | S9: =LOOKUP(R1,'Deployment needs'!$2:$2,'Deployment needs'!108:108) -> 0.154375 | U9: 20000 | V9: DC Daily Goal | X9: +/-DC goal | Y9: =(U10-U9)+Y7 -> 5534 | AA9: {=IFERROR(INDEX($A$1:$A$107,SMALL(IF($O$30=$B$1:$B$107,ROW($B$1:$B$107)-MIN(ROW($A$1:$A$107))+1,""),ROW()-8)),"")} | AB9: {=IFERROR(INDEX($A$1:$A$107,SMALL(IF($O$7=$B$1:$B$107,ROW($B$1:$B$107)-MIN(ROW($A$1:$A$107))+1,""), ROW()-7)),"")} | AC9: {=IFERROR(INDEX($A$1:$A$107,SMALL(IF($O$11=$B$1:$B$107,ROW($B$1:$B$107)-MIN(ROW($A$1:$A$107))+1,""), ROW()-1)),"")} | AE9: {=IFERROR(INDEX($A$1:$A$107,SMALL(IF($O$8=$B$1:$B$107,ROW($B$1:$B$107)-MIN(ROW($A$1:$A$107))+1,""), ROW()-1)),"")} | AF9: {=IFERROR(INDEX($A$1:$A$107,SMALL(IF($O$9=$B$1:$B$107,ROW($B$1:$B$107)-MIN(ROW($A$1:$A$107))+1,""), ROW()-6)),"")} | AG9: {=IFERROR(INDEX($A$1:$A$107,SMALL(IF($O$28=$B$1:$B$107,ROW($B$1:$B$107)-MIN(ROW($A$1:$A$107))+1,""), ROW()-6)),"")} | AH9: {=IFERROR(INDEX($A$1:$A$107,SMALL(IF($O$22=$B$1:$B$107,ROW($B$1:$B$107)-MIN(ROW($A$1:$A$107))+1,""), ROW()-1)),"")} | AI9: {=IFERROR(INDEX($A$1:$A$107,SMALL(IF($O$6=$B$1:$B$107,ROW($B$1:$B$107)-MIN(ROW($A$1:$A$107))+1,""), ROW()-1)),"")} | AJ9: {=IFERROR(INDEX($A$71:$A$100,SMALL(IF($M$6=$B$71:$B$100,ROW($B$71:$B$100)-MIN(ROW($A$71:$A$100))+1,""), ROW()-1)),"")} -> 0 | AR9: 45597 | AS9: Aliuska | AT9: Elian | AW9: Lisandra Parache | AX9: 43961 | AY9: =DATEDIF(AX9, TODAY(), "Y") & " year(s) " & DATEDIF(AX9, TODAY(), "YM") & " month(s) " & DATEDIF(AX9, TODAY(), "MD") & " day(s)" -> 6 year(s) 1 month(s) 6 day(s)
A10: {=_xlfn.IFS(C14=0,"",C14>0,C14)} -> Isabel Hernandez Garcia | B10: {=_xlfn.IFS(F14=0,"",F14>0,F14)} -> sn | C10: Aliuska Almira Mateo | E10: FT | F10: rn | O10: TP | P10: Taper/Downsize | Q10: =COUNTIFS($F$5:$L$34,O10) -> 0 | S10: {=LOOKUP(R1,'Deployment needs'!$2:$2,('Deployment needs'!107:107+'Deployment needs'!110:110))} -> 0.16175 | T10: * | U10: 23048 | V10: Total units Ship | AA10: {=IFERROR(INDEX($A$1:$A$107,SMALL(IF($O$30=$B$1:$B$107,ROW($B$1:$B$107)-MIN(ROW($A$1:$A$107))+1,""),ROW()-8)),"")} | AB10: {=IFERROR(INDEX($A$1:$A$107,SMALL(IF($O$7=$B$1:$B$107,ROW($B$1:$B$107)-MIN(ROW($A$1:$A$107))+1,""), ROW()-7)),"")} | AC10: {=IFERROR(INDEX($A$1:$A$107,SMALL(IF($O$11=$B$1:$B$107,ROW($B$1:$B$107)-MIN(ROW($A$1:$A$107))+1,""), ROW()-1)),"")} | AE10: {=IFERROR(INDEX($A$1:$A$107,SMALL(IF($O$8=$B$1:$B$107,ROW($B$1:$B$107)-MIN(ROW($A$1:$A$107))+1,""), ROW()-1)),"")} | AF10: {=IFERROR(INDEX($A$1:$A$107,SMALL(IF($O$9=$B$1:$B$107,ROW($B$1:$B$107)-MIN(ROW($A$1:$A$107))+1,""), ROW()-6)),"")} | AG10: {=IFERROR(INDEX($A$1:$A$107,SMALL(IF($O$28=$B$1:$B$107,ROW($B$1:$B$107)-MIN(ROW($A$1:$A$107))+1,""), ROW()-6)),"")} | AH10: {=IFERROR(INDEX($A$1:$A$107,SMALL(IF($O$22=$B$1:$B$107,ROW($B$1:$B$107)-MIN(ROW($A$1:$A$107))+1,""), ROW()-1)),"")} | AI10: {=IFERROR(INDEX($A$1:$A$107,SMALL(IF($O$6=$B$1:$B$107,ROW($B$1:$B$107)-MIN(ROW($A$1:$A$107))+1,""), ROW()-1)),"")} | AJ10: {=IFERROR(INDEX($A$71:$A$100,SMALL(IF($M$6=$B$71:$B$100,ROW($B$71:$B$100)-MIN(ROW($A$71:$A$100))+1,""), ROW()-1)),"")} -> 0 | AR10: 45627 | AS10: Juana | AT10: Aliuska | AW10: Jonathan Koerner | AX10: 44159 | AY10: =DATEDIF(AX10, TODAY(), "Y") & " year(s) " & DATEDIF(AX10, TODAY(), "YM") & " month(s) " & DATEDIF(AX10, TODAY(), "MD") & " day(s)" -> 5 year(s) 6 month(s) 23 day(s)
A11: {=_xlfn.IFS(C15=0,"",C15>0,C15)} -> Jacqueline Macias | B11: {=_xlfn.IFS(F15=0,"",F15>0,F15)} -> pto | C11: Ana Maria Suarez | E11: FT | F11: ab | O11: B | P11: Bander | Q11: =COUNTIFS($F$5:$L$34,O11) -> 6 | S11: =LOOKUP(R1,'Deployment needs'!$2:$2,'Deployment needs'!111:111) -> 0.94791667 | U11: 14652 | V11: 1st shift ship | AA11: {=IFERROR(INDEX($A$1:$A$107,SMALL(IF($O$30=$B$1:$B$107,ROW($B$1:$B$107)-MIN(ROW($A$1:$A$107))+1,""),ROW()-8)),"")} | AB11: {=IFERROR(INDEX($A$1:$A$107,SMALL(IF($O$7=$B$1:$B$107,ROW($B$1:$B$107)-MIN(ROW($A$1:$A$107))+1,""), ROW()-7)),"")} | AC11: {=IFERROR(INDEX($A$1:$A$107,SMALL(IF($O$11=$B$1:$B$107,ROW($B$1:$B$107)-MIN(ROW($A$1:$A$107))+1,""), ROW()-1)),"")} | AE11: {=IFERROR(INDEX($A$1:$A$107,SMALL(IF($O$8=$B$1:$B$107,ROW($B$1:$B$107)-MIN(ROW($A$1:$A$107))+1,""), ROW()-1)),"")} | AF11: {=IFERROR(INDEX($A$1:$A$107,SMALL(IF($O$9=$B$1:$B$107,ROW($B$1:$B$107)-MIN(ROW($A$1:$A$107))+1,""), ROW()-6)),"")} | AG11: {=IFERROR(INDEX($A$1:$A$107,SMALL(IF($O$28=$B$1:$B$107,ROW($B$1:$B$107)-MIN(ROW($A$1:$A$107))+1,""), ROW()-6)),"")} | AH11: {=IFERROR(INDEX($A$1:$A$107,SMALL(IF($O$22=$B$1:$B$107,ROW($B$1:$B$107)-MIN(ROW($A$1:$A$107))+1,""), ROW()-1)),"")} | AI11: {=IFERROR(INDEX($A$1:$A$107,SMALL(IF($O$6=$B$1:$B$107,ROW($B$1:$B$107)-MIN(ROW($A$1:$A$107))+1,""), ROW()-1)),"")} | AJ11: {=IFERROR(INDEX($A$71:$A$100,SMALL(IF($M$6=$B$71:$B$100,ROW($B$71:$B$100)-MIN(ROW($A$71:$A$100))+1,""), ROW()-1)),"")} -> 0 | AR11: 45658 | AS11: Ana | AT11: Juana | AW11: Marigeritte Mugelanya | AX11: 44221 | AY11: =DATEDIF(AX11, TODAY(), "Y") & " year(s) " & DATEDIF(AX11, TODAY(), "YM") & " month(s) " & DATEDIF(AX11, TODAY(), "MD") & " day(s)" -> 5 year(s) 4 month(s) 22 day(s)
A12: {=_xlfn.IFS(C16=0,"",C16>0,C16)} -> Jonathan Koerner | B12: {=_xlfn.IFS(F16=0,"",F16>0,F16)} -> tr | C12: Freddy Sossa | E12: FT | F12: rt | O12: AB | P12: Autobagger | Q12: =COUNTIFS($F$5:$L$34,O12) -> 2 | S12: =LOOKUP(R1,'Deployment needs'!$2:$2,'Deployment needs'!112:112) -> 1 | U12: 8000 | V12: 2nd shift Goal | X12: +/-Shift goal | Y12: =U12-Y7 -> 5514 | AA12: Resets | AB12: Picking Cycle Counts / Spot Count | AC12: Outbound Exception | AE12: Tasks | AF12: ="Returns"&" "&R24&" "&"orders"&" "&COUNTA(AF13:AF25)-COUNTBLANK(AF13:AF25) -> Returns 0 orders 1 | AG12: Sort Returns Putaway | AH12: Inventory & CC Reconcile | AI12: {=IFERROR(INDEX($A$1:$A$107,SMALL(IF($O$6=$B$1:$B$107,ROW($B$1:$B$107)-MIN(ROW($A$1:$A$107))+1,""), ROW()-1)),"")} | AJ12: {=IFERROR(INDEX($A$71:$A$100,SMALL(IF($M$6=$B$71:$B$100,ROW($B$71:$B$100)-MIN(ROW($A$71:$A$100))+1,""), ROW()-1)),"")} -> 0 | AR12: 45689 | AS12: Yulianela | AT12: Ana | AW12: Ana Maria Suarez | AX12: 44034 | AY12: =DATEDIF(AX12, TODAY(), "Y") & " year(s) " & DATEDIF(AX12, TODAY(), "YM") & " month(s) " & DATEDIF(AX12, TODAY(), "MD") & " day(s)" -> 5 year(s) 10 month(s) 25 day(s)
A13: {=_xlfn.IFS(C17=0,"",C17>0,C17)} -> Leidy Laura Riera | B13: {=_xlfn.IFS(F17=0,"",F17>0,F17)} -> ab | C13: Idelmis Infante Silva | E13: FT | F13: LOA | O13: R | P13: Resets | Q13: =COUNTIFS($F$5:$L$34,O13) -> 1 | S13: =LOOKUP(R1,'Deployment needs'!$2:$2,'Deployment needs'!141:141) -> 0.18055556 | T13: * | U13: 8394 | V13: 2nd shift Ship | X13: Avail/open | Y13: =Y2+Y3 -> 14127 | AA13: {=IFERROR(INDEX($A$1:$A$107,SMALL(IF($O$13=$B$1:$B$107,ROW($B$1:$B$107)-MIN(ROW($A$1:$A$107))+1,""), ROW()-12)),"")} -> Lisandra Parache | AB13: {=IFERROR(INDEX($A$1:$A$107,SMALL(IF(O$17=$B$1:$B$107,ROW($B$1:$B$107)-MIN(ROW($A$1:$A$107))+1,""), ROW()-12)),"")} | AC13: {=IFERROR(INDEX($A$1:$A$107,SMALL(IF($O$15=$B$1:$B$107,ROW($B$1:$B$107)-MIN(ROW($A$1:$A$107))+1,""), ROW()-12)),"")} | AE13: Rush | AF13: {=IFERROR(INDEX($A$1:$A$107,SMALL(IF($O$23=$B$1:$B$107,ROW($B$1:$B$107)-MIN(ROW($A$1:$A$107))+1,""), ROW()-12)),"")} -> Aliuska Almira Mateo | AG13: {=IFERROR(INDEX($A$1:$A$107,SMALL(IF($O$25=$B$1:$B$107,ROW($B$1:$B$107)-MIN(ROW($A$1:$A$107))+1,""), ROW()-12)),"")} | AH13: {=IFERROR(INDEX($A$1:$A$107,SMALL(IF($O$32=$B$1:$B$107,ROW($B$1:$B$107)-MIN(ROW($A$1:$A$107))+1,""), ROW()-12)),"")} -> Jonat Gordis | AI13: {=IFERROR(INDEX($A$1:$A$107,SMALL(IF($O$6=$B$1:$B$107,ROW($B$1:$B$107)-MIN(ROW($A$1:$A$107))+1,""), ROW()-1)),"")} | AJ13: {=IFERROR(INDEX($A$71:$A$100,SMALL(IF($M$6=$B$71:$B$100,ROW($B$71:$B$100)-MIN(ROW($A$71:$A$100))+1,""), ROW()-1)),"")} -> 0 | AR13: 45717 | AS13: Yoel | AT13: Yulianela | AW13: Xiomara Castro Dominquez | AX13: 44503 | AY13: =DATEDIF(AX13, TODAY(), "Y") & " year(s) " & DATEDIF(AX13, TODAY(), "YM") & " month(s) " & DATEDIF(AX13, TODAY(), "MD") & " day(s)" -> 4 year(s) 7 month(s) 13 day(s)
A14: {=_xlfn.IFS(C18=0,"",C18>0,C18)} -> Lisbet Moro Valero | B14: {=_xlfn.IFS(F18=0,"",F18>0,F18)} -> b | C14: Isabel Hernandez Garcia | E14: FT | F14: sn | J14: 8:30 team | O14: e | P14: Resets Exceptions | Q14: =COUNTIFS($F$5:$L$34,O14) -> 0 | S14: {=LOOKUP(R1,'Deployment needs'!$2:$2,('Deployment needs'!109:109+'Deployment needs'!139:139+'Deployment needs'!140:140))} -> 0.55416667 | Y14: =Y13-Y12 -> 8613 | AA14: {=IFERROR(INDEX($A$1:$A$107,SMALL(IF($O$13=$B$1:$B$107,ROW($B$1:$B$107)-MIN(ROW($A$1:$A$107))+1,""), ROW()-12)),"")} | AB14: {=IFERROR(INDEX($A$1:$A$107,SMALL(IF(O$17=$B$1:$B$107,ROW($B$1:$B$107)-MIN(ROW($A$1:$A$107))+1,""), ROW()-12)),"")} | AC14: {=IFERROR(INDEX($A$1:$A$107,SMALL(IF($O$15=$B$1:$B$107,ROW($B$1:$B$107)-MIN(ROW($A$1:$A$107))+1,""), ROW()-12)),"")} | AE14: Aged orders/Emails | AF14: {=IFERROR(INDEX($A$1:$A$107,SMALL(IF($O$23=$B$1:$B$107,ROW($B$1:$B$107)-MIN(ROW($A$1:$A$107))+1,""), ROW()-12)),"")} | AG14: {=IFERROR(INDEX($A$1:$A$107,SMALL(IF($O$25=$B$1:$B$107,ROW($B$1:$B$107)-MIN(ROW($A$1:$A$107))+1,""), ROW()-12)),"")} | AH14: {=IFERROR(INDEX($A$1:$A$107,SMALL(IF($O$32=$B$1:$B$107,ROW($B$1:$B$107)-MIN(ROW($A$1:$A$107))+1,""), ROW()-12)),"")} -> Alma Mehic- IL | AI14: {=IFERROR(INDEX($A$1:$A$107,SMALL(IF($O$6=$B$1:$B$107,ROW($B$1:$B$107)-MIN(ROW($A$1:$A$107))+1,""), ROW()-1)),"")} | AJ14: {=IFERROR(INDEX($A$71:$A$100,SMALL(IF($M$6=$B$71:$B$100,ROW($B$71:$B$100)-MIN(ROW($A$71:$A$100))+1,""), ROW()-1)),"")} -> 0 | AR14: 45748 | AS14: Jennifer | AW14: Elian Parra | AX14: 44441 | AY14: =DATEDIF(AX14, TODAY(), "Y") & " year(s) " & DATEDIF(AX14, TODAY(), "YM") & " month(s) " & DATEDIF(AX14, TODAY(), "MD") & " day(s)" -> 4 year(s) 9 month(s) 14 day(s)
A15: {=_xlfn.IFS(C19=0,"",C19>0,C19)} -> Lisandra Parache | B15: {=_xlfn.IFS(F19=0,"",F19>0,F19)} -> r | C15: Jacqueline Macias | E15: FT | F15: pto | O15: DS | P15: Outbound Exception | Q15: =COUNTIFS($F$5:$L$34,O15) -> 0 | S15: =LOOKUP(R1,'Deployment needs'!$2:$2,'Deployment needs'!95:95) -> 0.25 | AA15: {=IFERROR(INDEX($A$1:$A$107,SMALL(IF($O$13=$B$1:$B$107,ROW($B$1:$B$107)-MIN(ROW($A$1:$A$107))+1,""), ROW()-12)),"")} | AB15: {=IFERROR(INDEX($A$1:$A$107,SMALL(IF(O$17=$B$1:$B$107,ROW($B$1:$B$107)-MIN(ROW($A$1:$A$107))+1,""), ROW()-12)),"")} | AC15: {=IFERROR(INDEX($A$1:$A$107,SMALL(IF($O$15=$B$1:$B$107,ROW($B$1:$B$107)-MIN(ROW($A$1:$A$107))+1,""), ROW()-12)),"")} | AF15: {=IFERROR(INDEX($A$1:$A$107,SMALL(IF($O$23=$B$1:$B$107,ROW($B$1:$B$107)-MIN(ROW($A$1:$A$107))+1,""), ROW()-12)),"")} | AG15: {=IFERROR(INDEX($A$1:$A$107,SMALL(IF($O$25=$B$1:$B$107,ROW($B$1:$B$107)-MIN(ROW($A$1:$A$107))+1,""), ROW()-12)),"")} | AH15: {=IFERROR(INDEX($A$1:$A$107,SMALL(IF($O$32=$B$1:$B$107,ROW($B$1:$B$107)-MIN(ROW($A$1:$A$107))+1,""), ROW()-12)),"")} -> Carlos Agramonte Mendoza | AI15: {=IFERROR(INDEX($A$1:$A$107,SMALL(IF($O$6=$B$1:$B$107,ROW($B$1:$B$107)-MIN(ROW($A$1:$A$107))+1,""), ROW()-1)),"")} | AJ15: {=IFERROR(INDEX($A$71:$A$100,SMALL(IF($M$6=$B$71:$B$100,ROW($B$71:$B$100)-MIN(ROW($A$71:$A$100))+1,""), ROW()-1)),"")} -> 0 | AR15: 45778 | AS15: Idalmis | AT15: Jennifer | AW15: Idelmis Infante Silva | AX15: 44815 | AY15: =DATEDIF(AX15, TODAY(), "Y") & " year(s) " & DATEDIF(AX15, TODAY(), "YM") & " month(s) " & DATEDIF(AX15, TODAY(), "MD") & " day(s)" -> 3 year(s) 9 month(s) 5 day(s)
A16: {=_xlfn.IFS(C20=0,"",C20>0,C20)} -> Marigeritte Mugelanya | B16: {=_xlfn.IFS(F20=0,"",F20>0,F20)} -> b | C16: Jonathan Koerner | E16: FT | F16: tr | O16: MP | P16: DTC Putaway | Q16: =COUNTIFS($F$5:$L$34,O16) -> 0 | S16: =LOOKUP(R1,'Deployment needs'!$2:$2,'Deployment needs'!75:75) -> 1.0126111 | AA16: {=IFERROR(INDEX($A$1:$A$107,SMALL(IF($O$13=$B$1:$B$107,ROW($B$1:$B$107)-MIN(ROW($A$1:$A$107))+1,""), ROW()-12)),"")} | AB16: {=IFERROR(INDEX($A$1:$A$107,SMALL(IF(O$17=$B$1:$B$107,ROW($B$1:$B$107)-MIN(ROW($A$1:$A$107))+1,""), ROW()-12)),"")} | AC16: ="CubiScan - in / out"&" "&R30 -> CubiScan - in / out | AE16: Misspicks/DTC Putaway | AF16: {=IFERROR(INDEX($A$1:$A$107,SMALL(IF($O$23=$B$1:$B$107,ROW($B$1:$B$107)-MIN(ROW($A$1:$A$107))+1,""), ROW()-12)),"")} | AG16: {=IFERROR(INDEX($A$1:$A$107,SMALL(IF($O$25=$B$1:$B$107,ROW($B$1:$B$107)-MIN(ROW($A$1:$A$107))+1,""), ROW()-12)),"")} | AH16: {=IFERROR(INDEX($A$1:$A$107,SMALL(IF($O$32=$B$1:$B$107,ROW($B$1:$B$107)-MIN(ROW($A$1:$A$107))+1,""), ROW()-12)),"")} | AI16: {=IFERROR(INDEX($A$1:$A$107,SMALL(IF($O$6=$B$1:$B$107,ROW($B$1:$B$107)-MIN(ROW($A$1:$A$107))+1,""), ROW()-1)),"")} | AJ16: {=IFERROR(INDEX($A$71:$A$100,SMALL(IF($M$6=$B$71:$B$100,ROW($B$71:$B$100)-MIN(ROW($A$71:$A$100))+1,""), ROW()-1)),"")} -> 0 | AR16: 45809 | AS16: Margarite | AT16: Idalmis | AW16: Yulianela Gonzalez Sanchez | AX16: 45114 | AY16: =DATEDIF(AX16, TODAY(), "Y") & " year(s) " & DATEDIF(AX16, TODAY(), "YM") & " month(s) " & DATEDIF(AX16, TODAY(), "MD") & " day(s)" -> 2 year(s) 11 month(s) 9 day(s)
A17: {=_xlfn.IFS(C21=0,"",C21>0,C21)} -> Fabian Perez | B17: {=_xlfn.IFS(F21=0,"",F21>0,F21)} -> rp | C17: Leidy Laura Riera | E17: FT | F17: ab | O17: PC | P17: Picking CC/ spot count | Q17: =COUNTIFS($F$5:$L$34,O17) -> 0 | S17: =LOOKUP(R1,'Deployment needs'!$2:$2,'Deployment needs'!89:89) -> 0.25 | AA17: {=IFERROR(INDEX($A$1:$A$107,SMALL(IF($O$13=$B$1:$B$107,ROW($B$1:$B$107)-MIN(ROW($A$1:$A$107))+1,""), ROW()-12)),"")} | AB17: {=IFERROR(INDEX($A$1:$A$107,SMALL(IF(O$17=$B$1:$B$107,ROW($B$1:$B$107)-MIN(ROW($A$1:$A$107))+1,""), ROW()-12)),"")} | AC17: {=IFERROR(INDEX($A$1:$A$107,SMALL(IF($O$29=$B$1:$B$107,ROW($B$1:$B$107)-MIN(ROW($A$1:$A$107))+1,""), ROW()-16)),"")} | AE17: {=IFERROR(INDEX($A$1:$A$107,SMALL(IF($O$16=$B$1:$B$107,ROW($B$1:$B$107)-MIN(ROW($A$1:$A$107))+1,""), ROW()-16)),"")} | AF17: {=IFERROR(INDEX($A$1:$A$107,SMALL(IF($O$23=$B$1:$B$107,ROW($B$1:$B$107)-MIN(ROW($A$1:$A$107))+1,""), ROW()-12)),"")} | AG17: ="Returns Putaway"&" "&R26 -> Returns Putaway | AH17: {=IFERROR(INDEX($A$1:$A$107,SMALL(IF($O$32=$B$1:$B$107,ROW($B$1:$B$107)-MIN(ROW($A$1:$A$107))+1,""), ROW()-12)),"")} | AI17: {=IFERROR(INDEX($A$1:$A$107,SMALL(IF($O$6=$B$1:$B$107,ROW($B$1:$B$107)-MIN(ROW($A$1:$A$107))+1,""), ROW()-1)),"")} | AJ17: {=IFERROR(INDEX($A$71:$A$100,SMALL(IF($M$6=$B$71:$B$100,ROW($B$71:$B$100)-MIN(ROW($A$71:$A$100))+1,""), ROW()-1)),"")} -> 0 | AR17: 45839 | AS17: Arlin | AW17: Freddy Sossa | AX17: 45417 | AY17: =DATEDIF(AX17, TODAY(), "Y") & " year(s) " & DATEDIF(AX17, TODAY(), "YM") & " month(s) " & DATEDIF(AX17, TODAY(), "MD") & " day(s)" -> 2 year(s) 1 month(s) 11 day(s)
A18: {=_xlfn.IFS(G5=0,"",G5>0,G5)} -> Liudmila Gonzalez Caballero | B18: {=_xlfn.IFS(I5=0,"",I5>0,I5)} -> cb | C18: Lisbet Moro Valero | E18: FT | F18: b | O18: OC | P18: Overstock CC | Q18: =COUNTIFS($F$5:$L$34,O18) -> 0 | S18: =LOOKUP(R1,'Deployment needs'!$2:$2,'Deployment needs'!72:72) -> 4.4217778 | U18: ON SLA | V18: OUT SLA | AA18: {=IFERROR(INDEX($A$1:$A$107,SMALL(IF($O$13=$B$1:$B$107,ROW($B$1:$B$107)-MIN(ROW($A$1:$A$107))+1,""), ROW()-12)),"")} | AB18: {=IFERROR(INDEX($A$1:$A$107,SMALL(IF(O$17=$B$1:$B$107,ROW($B$1:$B$107)-MIN(ROW($A$1:$A$107))+1,""), ROW()-12)),"")} | AC18: {=IFERROR(INDEX($A$1:$A$107,SMALL(IF($O$29=$B$1:$B$107,ROW($B$1:$B$107)-MIN(ROW($A$1:$A$107))+1,""), ROW()-16)),"")} | AE18: {=IFERROR(INDEX($A$1:$A$107,SMALL(IF($O$16=$B$1:$B$107,ROW($B$1:$B$107)-MIN(ROW($A$1:$A$107))+1,""), ROW()-16)),"")} | AF18: {=IFERROR(INDEX($A$1:$A$107,SMALL(IF($O$23=$B$1:$B$107,ROW($B$1:$B$107)-MIN(ROW($A$1:$A$107))+1,""), ROW()-12)),"")} | AG18: {=IFERROR(INDEX($A$1:$A$107,SMALL(IF($O$26=$B$1:$B$107,ROW($B$1:$B$107)-MIN(ROW($A$1:$A$107))+1,""), ROW()-17)),"")} | AH18: {=IFERROR(INDEX($A$1:$A$107,SMALL(IF($O$32=$B$1:$B$107,ROW($B$1:$B$107)-MIN(ROW($A$1:$A$107))+1,""), ROW()-12)),"")} | AI18: {=IFERROR(INDEX($A$1:$A$107,SMALL(IF($O$6=$B$1:$B$107,ROW($B$1:$B$107)-MIN(ROW($A$1:$A$107))+1,""), ROW()-1)),"")} | AJ18: {=IFERROR(INDEX($A$71:$A$100,SMALL(IF($M$6=$B$71:$B$100,ROW($B$71:$B$100)-MIN(ROW($A$71:$A$100))+1,""), ROW()-1)),"")} -> 0 | AR18: 45870 | AS18: Laura | AW18: Arlin Perez Bles | AX18: 45124 | AY18: =DATEDIF(AX18, TODAY(), "Y") & " year(s) " & DATEDIF(AX18, TODAY(), "YM") & " month(s) " & DATEDIF(AX18, TODAY(), "MD") & " day(s)" -> 2 year(s) 10 month(s) 30 day(s)
A19: {=_xlfn.IFS(G6=0,"",G6>0,G6)} -> Adrian Sanchez Avila | B19: {=_xlfn.IFS(I6=0,"",I6>0,I6)} -> b | C19: Lisandra Parache | E19: FT | F19: r | O19: O | P19: Overstock putaway | Q19: =COUNTIFS($F$5:$L$34,O19) -> 0 | R19: =_xlfn.IFNA(LOOKUP(TODAY(),'Inbound SOS & EOD'!1:1,'Inbound SOS & EOD'!51:51),0) -> 0 | S19: =LOOKUP(R1,'Deployment needs'!$2:$2,'Deployment needs'!70:70) -> 0.30895062 | U19: Meet | V19: No Meet | Z19: Inbound | AA19: Reset Exceptions | AB19: {=IFERROR(INDEX($A$1:$A$107,SMALL(IF(O$17=$B$1:$B$107,ROW($B$1:$B$107)-MIN(ROW($A$1:$A$107))+1,""), ROW()-12)),"")} | AC19: {=IFERROR(INDEX($A$1:$A$107,SMALL(IF($O$29=$B$1:$B$107,ROW($B$1:$B$107)-MIN(ROW($A$1:$A$107))+1,""), ROW()-16)),"")} | AE19: {=IFERROR(INDEX($A$1:$A$107,SMALL(IF($O$16=$B$1:$B$107,ROW($B$1:$B$107)-MIN(ROW($A$1:$A$107))+1,""), ROW()-16)),"")} | AF19: {=IFERROR(INDEX($A$1:$A$107,SMALL(IF($O$23=$B$1:$B$107,ROW($B$1:$B$107)-MIN(ROW($A$1:$A$107))+1,""), ROW()-12)),"")} | AG19: {=IFERROR(INDEX($A$1:$A$107,SMALL(IF($O$26=$B$1:$B$107,ROW($B$1:$B$107)-MIN(ROW($A$1:$A$107))+1,""), ROW()-17)),"")} | AH19: {=IFERROR(INDEX($A$1:$A$107,SMALL(IF($O$32=$B$1:$B$107,ROW($B$1:$B$107)-MIN(ROW($A$1:$A$107))+1,""), ROW()-12)),"")} | AI19: {=IFERROR(INDEX($A$1:$A$107,SMALL(IF($O$6=$B$1:$B$107,ROW($B$1:$B$107)-MIN(ROW($A$1:$A$107))+1,""), ROW()-1)),"")} | AJ19: {=IFERROR(INDEX($A$71:$A$100,SMALL(IF($M$6=$B$71:$B$100,ROW($B$71:$B$100)-MIN(ROW($A$71:$A$100))+1,""), ROW()-1)),"")} -> 0 | AR19: 45901 | AS19: Lisandra | AW19: Leidy Laura Riera | AX19: 45558 | AY19: =DATEDIF(AX19, TODAY(), "Y") & " year(s) " & DATEDIF(AX19, TODAY(), "YM") & " month(s) " & DATEDIF(AX19, TODAY(), "MD") & " day(s)" -> 1 year(s) 8 month(s) 24 day(s)
A20: {=_xlfn.IFS(G7=0,"",G7>0,G7)} -> Carlos Agramonte Mendoza | B20: {=_xlfn.IFS(I7=0,"",I7>0,I7)} -> i | C20: Marigeritte Mugelanya | E20: FT | F20: b | O20: RP | P20: Replen Pull | Q20: =COUNTIFS($F$5:$L$34,O20) -> 1 | R20: =_xlfn.IFNA(LOOKUP(TODAY(),'Inbound SOS & EOD'!1:1,'Inbound SOS & EOD'!61:61),0) -> 0 | S20: =LOOKUP(R1,'Deployment needs'!$2:$2,'Deployment needs'!71:71) -> 0.39722222 | AA20: {=IFERROR(INDEX($A$1:$A$107,SMALL(IF($O$14=$B$1:$B$107,ROW($B$1:$B$107)-MIN(ROW($A$1:$A$107))+1,""), ROW()-19)),"")} | AB20: {=IFERROR(INDEX($A$1:$A$107,SMALL(IF(O$17=$B$1:$B$107,ROW($B$1:$B$107)-MIN(ROW($A$1:$A$107))+1,""), ROW()-12)),"")} | AC20: ="Pull"&" "&R21 -> Pull 0 | AD20: Priority | AE20: ="Throw"&" "&R22 -> Throw 0 | AF20: {=IFERROR(INDEX($A$1:$A$107,SMALL(IF($O$23=$B$1:$B$107,ROW($B$1:$B$107)-MIN(ROW($A$1:$A$107))+1,""), ROW()-12)),"")} | AG20: {=IFERROR(INDEX($A$1:$A$107,SMALL(IF($O$26=$B$1:$B$107,ROW($B$1:$B$107)-MIN(ROW($A$1:$A$107))+1,""), ROW()-17)),"")} | AH20: {=IFERROR(INDEX($A$1:$A$107,SMALL(IF($O$32=$B$1:$B$107,ROW($B$1:$B$107)-MIN(ROW($A$1:$A$107))+1,""), ROW()-12)),"")} | AI20: {=IFERROR(INDEX($A$1:$A$107,SMALL(IF($O$6=$B$1:$B$107,ROW($B$1:$B$107)-MIN(ROW($A$1:$A$107))+1,""), ROW()-1)),"")} | AJ20: {=IFERROR(INDEX($A$71:$A$100,SMALL(IF($M$6=$B$71:$B$100,ROW($B$71:$B$100)-MIN(ROW($A$71:$A$100))+1,""), ROW()-1)),"")} -> 0 | AR20: 45931 | AS20: Lisbet | AW20: Jacqueline Macias | AX20: 45568 | AY20: =DATEDIF(AX20, TODAY(), "Y") & " year(s) " & DATEDIF(AX20, TODAY(), "YM") & " month(s) " & DATEDIF(AX20, TODAY(), "MD") & " day(s)" -> 1 year(s) 8 month(s) 13 day(s)
C21: Fabian Perez | E21: FT | F21: rp | O21: RT | P21: Replen Throw | Q21: =COUNTIFS($F$5:$L$34,O21) -> 1 | R21: =_xlfn.IFNA(LOOKUP(TODAY(),'Inbound SOS & EOD'!1:1,'Inbound SOS & EOD'!62:62),0)+R22 -> 0 | S21: =LOOKUP(R1,'Deployment needs'!$2:$2,'Deployment needs'!94:94) -> 0 | AA21: {=IFERROR(INDEX($A$1:$A$107,SMALL(IF($O$14=$B$1:$B$107,ROW($B$1:$B$107)-MIN(ROW($A$1:$A$107))+1,""), ROW()-19)),"")} | AB21: {=IFERROR(INDEX($A$1:$A$107,SMALL(IF(O$17=$B$1:$B$107,ROW($B$1:$B$107)-MIN(ROW($A$1:$A$107))+1,""), ROW()-12)),"")} | AC21: {=IFERROR(INDEX($A$1:$A$107,SMALL(IF($O$20=$B$1:$B$107,ROW($B$1:$B$107)-MIN(ROW($A$1:$A$107))+1,""), ROW()-20)),"")} -> Fabian Perez | AD21: All | AE21: {=IFERROR(INDEX($A$1:$A$107,SMALL(IF($O$21=$B$1:$B$107,ROW($B$1:$B$107)-MIN(ROW($A$1:$A$107))+1,""), ROW()-20)),"")} -> Freddy Sossa | AF21: {=IFERROR(INDEX($A$1:$A$107,SMALL(IF($O$23=$B$1:$B$107,ROW($B$1:$B$107)-MIN(ROW($A$1:$A$107))+1,""), ROW()-12)),"")} | AG21: {=IFERROR(INDEX($A$1:$A$107,SMALL(IF($O$26=$B$1:$B$107,ROW($B$1:$B$107)-MIN(ROW($A$1:$A$107))+1,""), ROW()-17)),"")} | AH21: {=IFERROR(INDEX($A$1:$A$107,SMALL(IF($O$32=$B$1:$B$107,ROW($B$1:$B$107)-MIN(ROW($A$1:$A$107))+1,""), ROW()-12)),"")} | AI21: {=IFERROR(INDEX($A$1:$A$107,SMALL(IF($O$6=$B$1:$B$107,ROW($B$1:$B$107)-MIN(ROW($A$1:$A$107))+1,""), ROW()-1)),"")} | AJ21: {=IFERROR(INDEX($A$71:$A$100,SMALL(IF($M$6=$B$71:$B$100,ROW($B$71:$B$100)-MIN(ROW($A$71:$A$100))+1,""), ROW()-1)),"")} -> 0 | AR21: 45962 | AS21: Jacqueline | AW21: Lisbet Moro Valero | AX21: 45520 | AY21: =DATEDIF(AX21, TODAY(), "Y") & " year(s) " & DATEDIF(AX21, TODAY(), "YM") & " month(s) " & DATEDIF(AX21, TODAY(), "MD") & " day(s)" -> 1 year(s) 10 month(s) 0 day(s)
O22: T | P22: Training | Q22: =COUNTIFS($F$5:$L$34,O22) -> 0 | R22: =_xlfn.IFNA(LOOKUP(TODAY(),'Inbound SOS & EOD'!1:1,'Inbound SOS & EOD'!52:52),0) -> 0 | S22: =LOOKUP(R1,'Deployment needs'!$2:$2,'Deployment needs'!81:81) -> 0.7027134 | U22: Potential outcomes | V22: Singles HRS | W22: 2 | X22: =Q2 -> 5850 | AA22: {=IFERROR(INDEX($A$1:$A$107,SMALL(IF($O$14=$B$1:$B$107,ROW($B$1:$B$107)-MIN(ROW($A$1:$A$107))+1,""), ROW()-19)),"")} | AB22: {=IFERROR(INDEX($A$1:$A$107,SMALL(IF(O$17=$B$1:$B$107,ROW($B$1:$B$107)-MIN(ROW($A$1:$A$107))+1,""), ROW()-12)),"")} | AC22: {=IFERROR(INDEX($A$1:$A$107,SMALL(IF($O$20=$B$1:$B$107,ROW($B$1:$B$107)-MIN(ROW($A$1:$A$107))+1,""), ROW()-20)),"")} | AE22: {=IFERROR(INDEX($A$1:$A$107,SMALL(IF($O$21=$B$1:$B$107,ROW($B$1:$B$107)-MIN(ROW($A$1:$A$107))+1,""), ROW()-20)),"")} | AF22: {=IFERROR(INDEX($A$1:$A$107,SMALL(IF($O$23=$B$1:$B$107,ROW($B$1:$B$107)-MIN(ROW($A$1:$A$107))+1,""), ROW()-12)),"")} | AG22: {=IFERROR(INDEX($A$1:$A$107,SMALL(IF($O$26=$B$1:$B$107,ROW($B$1:$B$107)-MIN(ROW($A$1:$A$107))+1,""), ROW()-17)),"")} | AH22: {=IFERROR(INDEX($A$1:$A$107,SMALL(IF($O$32=$B$1:$B$107,ROW($B$1:$B$107)-MIN(ROW($A$1:$A$107))+1,""), ROW()-12)),"")} | AI22: {=IFERROR(INDEX($A$1:$A$107,SMALL(IF($O$6=$B$1:$B$107,ROW($B$1:$B$107)-MIN(ROW($A$1:$A$107))+1,""), ROW()-1)),"")} | AJ22: {=IFERROR(INDEX($A$71:$A$100,SMALL(IF($M$6=$B$71:$B$100,ROW($B$71:$B$100)-MIN(ROW($A$71:$A$100))+1,""), ROW()-1)),"")} -> 0 | AR22: 45992 | AS22: Alexcy
O23: RN | P23: Returns Processing | Q23: =COUNTIFS($F$5:$L$34,O23) -> 1 | R23: =_xlfn.IFNA(LOOKUP(TODAY(),'Inbound SOS & EOD'!$1:$1,'Inbound SOS & EOD'!41:41),0) -> 746 | S23: =LOOKUP(R1,'Deployment needs'!$2:$2,'Deployment needs'!82:82) -> 0.062215434 | U23: hours | V23: 3.5 | W23: 2 | X23: 8 | AA23: ="Receiving"&" "&R35 -> Receiving | AB23: Task | AC23: {=IFERROR(INDEX($A$1:$A$107,SMALL(IF($O$20=$B$1:$B$107,ROW($B$1:$B$107)-MIN(ROW($A$1:$A$107))+1,""), ROW()-20)),"")} | AE23: {=IFERROR(INDEX($A$1:$A$107,SMALL(IF($O$21=$B$1:$B$107,ROW($B$1:$B$107)-MIN(ROW($A$1:$A$107))+1,""), ROW()-20)),"")} | AF23: {=IFERROR(INDEX($A$1:$A$107,SMALL(IF($O$23=$B$1:$B$107,ROW($B$1:$B$107)-MIN(ROW($A$1:$A$107))+1,""), ROW()-12)),"")} | AG23: {=IFERROR(INDEX($A$1:$A$107,SMALL(IF($O$26=$B$1:$B$107,ROW($B$1:$B$107)-MIN(ROW($A$1:$A$107))+1,""), ROW()-17)),"")} | AH23: {=IFERROR(INDEX($A$1:$A$107,SMALL(IF($O$32=$B$1:$B$107,ROW($B$1:$B$107)-MIN(ROW($A$1:$A$107))+1,""), ROW()-12)),"")} | AI23: {=IFERROR(INDEX($A$1:$A$107,SMALL(IF($O$6=$B$1:$B$107,ROW($B$1:$B$107)-MIN(ROW($A$1:$A$107))+1,""), ROW()-1)),"")} | AJ23: {=IFERROR(INDEX($A$71:$A$100,SMALL(IF($M$6=$B$71:$B$100,ROW($B$71:$B$100)-MIN(ROW($A$71:$A$100))+1,""), ROW()-1)),"")} -> 0 | AR23: 46023 | AS23: Alma
O24: RE | P24: Returns Exceptions | Q24: =COUNTIFS($F$5:$L$34,O24) -> 0 | R24: =_xlfn.IFNA(LOOKUP(TODAY()+1,'Inbound SOS & EOD'!$1:$1,'Inbound SOS & EOD'!42:42),0) -> 0 | S24: =LOOKUP(R1,'Deployment needs'!$2:$2,'Deployment needs'!83:83)*0.25 -> 0.055549494 | U24: region | V24: 1 | W24: UPH | X24: estimate | AA24: {=IFERROR(INDEX($A$1:$A$107,SMALL(IF($O$27=$B$1:$B$107,ROW($B$1:$B$107)-MIN(ROW($A$1:$A$107))+1,""), ROW()-23)),"")} | AC24: {=IFERROR(INDEX($A$1:$A$107,SMALL(IF($O$20=$B$1:$B$107,ROW($B$1:$B$107)-MIN(ROW($A$1:$A$107))+1,""), ROW()-20)),"")} | AE24: {=IFERROR(INDEX($A$1:$A$107,SMALL(IF($O$21=$B$1:$B$107,ROW($B$1:$B$107)-MIN(ROW($A$1:$A$107))+1,""), ROW()-20)),"")} | AF24: {=IFERROR(INDEX($A$1:$A$107,SMALL(IF($O$23=$B$1:$B$107,ROW($B$1:$B$107)-MIN(ROW($A$1:$A$107))+1,""), ROW()-12)),"")} | AG24: {=IFERROR(INDEX($A$1:$A$107,SMALL(IF($O$26=$B$1:$B$107,ROW($B$1:$B$107)-MIN(ROW($A$1:$A$107))+1,""), ROW()-17)),"")} | AH24: {=IFERROR(INDEX($A$1:$A$107,SMALL(IF($O$32=$B$1:$B$107,ROW($B$1:$B$107)-MIN(ROW($A$1:$A$107))+1,""), ROW()-12)),"")} | AI24: {=IFERROR(INDEX($A$1:$A$107,SMALL(IF($O$6=$B$1:$B$107,ROW($B$1:$B$107)-MIN(ROW($A$1:$A$107))+1,""), ROW()-1)),"")} | AJ24: {=IFERROR(INDEX($A$71:$A$100,SMALL(IF($M$6=$B$71:$B$100,ROW($B$71:$B$100)-MIN(ROW($A$71:$A$100))+1,""), ROW()-1)),"")} -> 0 | AR24: 46054 | AS24: Koerner
O25: RS | P25: Returns Sorting | Q25: =COUNTIFS($F$5:$L$34,O25) -> 0 | R25: =_xlfn.IFNA(LOOKUP(TODAY(),'Inbound SOS & EOD'!$1:$1,'Inbound SOS & EOD'!59:59),0) -> 0 | S25: =LOOKUP(R1,'Deployment needs'!$2:$2,'Deployment needs'!83:83) -> 0.22219798 | U25: Picking- Bulk | V25: 12 | W25: 165 | X25: =W25*V25*$V$23 -> 6930 | AA25: {=IFERROR(INDEX($A$1:$A$107,SMALL(IF($O$27=$B$1:$B$107,ROW($B$1:$B$107)-MIN(ROW($A$1:$A$107))+1,""), ROW()-23)),"")} | AC25: {=IFERROR(INDEX($A$1:$A$107,SMALL(IF($O$20=$B$1:$B$107,ROW($B$1:$B$107)-MIN(ROW($A$1:$A$107))+1,""), ROW()-20)),"")} | AE25: {=IFERROR(INDEX($A$1:$A$107,SMALL(IF($O$21=$B$1:$B$107,ROW($B$1:$B$107)-MIN(ROW($A$1:$A$107))+1,""), ROW()-20)),"")} | AF25: {=IFERROR(INDEX($A$1:$A$107,SMALL(IF($O$23=$B$1:$B$107,ROW($B$1:$B$107)-MIN(ROW($A$1:$A$107))+1,""), ROW()-12)),"")} | AG25: {=IFERROR(INDEX($A$1:$A$107,SMALL(IF($O$26=$B$1:$B$107,ROW($B$1:$B$107)-MIN(ROW($A$1:$A$107))+1,""), ROW()-17)),"")} | AH25: {=IFERROR(INDEX($A$1:$A$107,SMALL(IF($O$32=$B$1:$B$107,ROW($B$1:$B$107)-MIN(ROW($A$1:$A$107))+1,""), ROW()-12)),"")} | AI25: {=IFERROR(INDEX($A$1:$A$107,SMALL(IF($O$6=$B$1:$B$107,ROW($B$1:$B$107)-MIN(ROW($A$1:$A$107))+1,""), ROW()-1)),"")} | AJ25: {=IFERROR(INDEX($A$71:$A$100,SMALL(IF($M$6=$B$71:$B$100,ROW($B$71:$B$100)-MIN(ROW($A$71:$A$100))+1,""), ROW()-1)),"")} -> 0 | AR25: 46082 | AS25: Ernesto
O26: RPA | P26: Returns put-away | Q26: =COUNTIFS($F$5:$L$34,O26) -> 0 | S26: =LOOKUP(R1,'Deployment needs'!$2:$2,'Deployment needs'!73:73) -> 1.4739259 | U26: Picking- Singles | V26: 1 | W26: 200 | X26: =W26*V26*$W$22 -> 400 | AA26: {=IFERROR(INDEX($A$1:$A$107,SMALL(IF($O$27=$B$1:$B$107,ROW($B$1:$B$107)-MIN(ROW($A$1:$A$107))+1,""), ROW()-23)),"")} | AC26: Aisle & DC Cleanup | AE26: {=IFERROR(INDEX($A$1:$A$107,SMALL(IF($O$21=$B$1:$B$107,ROW($B$1:$B$107)-MIN(ROW($A$1:$A$107))+1,""), ROW()-20)),"")} | AF26: ="Returns Exceptions"&" "&$X$27 -> Returns Exceptions | AG26: {=IFERROR(INDEX($A$1:$A$107,SMALL(IF($O$26=$B$1:$B$107,ROW($B$1:$B$107)-MIN(ROW($A$1:$A$107))+1,""), ROW()-17)),"")} | AH26: {=IFERROR(INDEX($A$1:$A$107,SMALL(IF($O$32=$B$1:$B$107,ROW($B$1:$B$107)-MIN(ROW($A$1:$A$107))+1,""), ROW()-12)),"")} | AI26: {=IFERROR(INDEX($A$1:$A$107,SMALL(IF($O$6=$B$1:$B$107,ROW($B$1:$B$107)-MIN(ROW($A$1:$A$107))+1,""), ROW()-1)),"")} | AJ26: {=IFERROR(INDEX($A$71:$A$100,SMALL(IF($M$6=$B$71:$B$100,ROW($B$71:$B$100)-MIN(ROW($A$71:$A$100))+1,""), ROW()-1)),"")} -> 0 | AR26: 46113 | AS26: Nolberto
O27: RC | P27: Receiving | Q27: =COUNTIFS($F$5:$L$34,O27) -> 0 | R27: =_xlfn.IFNA(LOOKUP(TODAY(),'Inbound SOS & EOD'!$1:$1,'Inbound SOS & EOD'!56:56),0) -> 0 | S27: =LOOKUP(R1,'Deployment needs'!$2:$2,'Deployment needs'!74:74) -> 1.6581667 | AA27: {=IFERROR(INDEX($A$1:$A$107,SMALL(IF($O$27=$B$1:$B$107,ROW($B$1:$B$107)-MIN(ROW($A$1:$A$107))+1,""), ROW()-23)),"")} | AC27: {=IFERROR(INDEX($A$1:$A$107,SMALL(IF($O$33=$B$1:$B$107,ROW($B$1:$B$107)-MIN(ROW($A$1:$A$107))+1,""), ROW()-26)),"")} | AE27: {=IFERROR(INDEX($A$1:$A$107,SMALL(IF($O$21=$B$1:$B$107,ROW($B$1:$B$107)-MIN(ROW($A$1:$A$107))+1,""), ROW()-20)),"")} | AF27: {=IFERROR(INDEX($A$1:$A$107,SMALL(IF($O$24=$B$1:$B$107,ROW($B$1:$B$107)-MIN(ROW($A$1:$A$107))+1,""), ROW()-26)),"")} | AG27: {=IFERROR(INDEX($A$1:$A$107,SMALL(IF($O$26=$B$1:$B$107,ROW($B$1:$B$107)-MIN(ROW($A$1:$A$107))+1,""), ROW()-17)),"")} | AH27: {=IFERROR(INDEX($A$1:$A$107,SMALL(IF($O$32=$B$1:$B$107,ROW($B$1:$B$107)-MIN(ROW($A$1:$A$107))+1,""), ROW()-12)),"")} | AI27: {=IFERROR(INDEX($A$1:$A$107,SMALL(IF($O$6=$B$1:$B$107,ROW($B$1:$B$107)-MIN(ROW($A$1:$A$107))+1,""), ROW()-1)),"")} | AJ27: {=IFERROR(INDEX($A$71:$A$100,SMALL(IF($M$6=$B$71:$B$100,ROW($B$71:$B$100)-MIN(ROW($A$71:$A$100))+1,""), ROW()-1)),"")} -> 0 | AR27: 46143 | AS27: Liudmila
O28: BB | P28: Baby Bundle | Q28: =COUNTIFS($F$5:$L$34,O28) -> 0 | U28: TOTAL | X28: =SUM(X25:X27) -> 7330 | AA28: {=IFERROR(INDEX($A$1:$A$107,SMALL(IF($O$27=$B$1:$B$107,ROW($B$1:$B$107)-MIN(ROW($A$1:$A$107))+1,""), ROW()-23)),"")} | AC28: {=IFERROR(INDEX($A$1:$A$107,SMALL(IF($O$33=$B$1:$B$107,ROW($B$1:$B$107)-MIN(ROW($A$1:$A$107))+1,""), ROW()-26)),"")} | AE28: {=IFERROR(INDEX($A$1:$A$107,SMALL(IF($O$21=$B$1:$B$107,ROW($B$1:$B$107)-MIN(ROW($A$1:$A$107))+1,""), ROW()-20)),"")} | AF28: {=IFERROR(INDEX($A$1:$A$107,SMALL(IF($O$24=$B$1:$B$107,ROW($B$1:$B$107)-MIN(ROW($A$1:$A$107))+1,""), ROW()-26)),"")} | AG28: {=IFERROR(INDEX($A$1:$A$107,SMALL(IF($O$26=$B$1:$B$107,ROW($B$1:$B$107)-MIN(ROW($A$1:$A$107))+1,""), ROW()-17)),"")} | AH28: {=IFERROR(INDEX($A$1:$A$107,SMALL(IF($O$32=$B$1:$B$107,ROW($B$1:$B$107)-MIN(ROW($A$1:$A$107))+1,""), ROW()-12)),"")} | AI28: {=IFERROR(INDEX($A$1:$A$107,SMALL(IF($O$6=$B$1:$B$107,ROW($B$1:$B$107)-MIN(ROW($A$1:$A$107))+1,""), ROW()-1)),"")} | AJ28: {=IFERROR(INDEX($A$71:$A$100,SMALL(IF($M$6=$B$71:$B$100,ROW($B$71:$B$100)-MIN(ROW($A$71:$A$100))+1,""), ROW()-1)),"")} -> 0 | AR28: 46174 | AS28: Jonathan
O29: CS | P29: Cubiscan | Q29: =COUNTIFS($F$5:$L$34,O29) -> 0 | R29: {=_xlfn.IFNA(LOOKUP(TODAY(),'Inbound SOS & EOD'!$1:$1,('Inbound SOS & EOD'!57:57+'Inbound SOS & EOD'!58:58)),0)} -> 0 | AA29: {=IFERROR(INDEX($A$1:$A$107,SMALL(IF($O$27=$B$1:$B$107,ROW($B$1:$B$107)-MIN(ROW($A$1:$A$107))+1,""), ROW()-23)),"")} | AI29: {=IFERROR(INDEX($A$1:$A$107,SMALL(IF($O$6=$B$1:$B$107,ROW($B$1:$B$107)-MIN(ROW($A$1:$A$107))+1,""), ROW()-1)),"")} | AJ29: {=IFERROR(INDEX($A$71:$A$100,SMALL(IF($M$6=$B$71:$B$100,ROW($B$71:$B$100)-MIN(ROW($A$71:$A$100))+1,""), ROW()-1)),"")} -> 0 | AR29: 46204
O30: SL | P30: Support | Q30: =COUNTIFS($F$5:$L$34,O30) -> 0 | S30: =LOOKUP(R1,'Deployment needs'!$2:$2,'Deployment needs'!96:96) -> 0 | AA30: {=IFERROR(INDEX($A$1:$A$107,SMALL(IF($O$27=$B$1:$B$107,ROW($B$1:$B$107)-MIN(ROW($A$1:$A$107))+1,""), ROW()-23)),"")} | AC30: {=IFERROR(INDEX($A$1:$A$107,SMALL(IF($O$33=$B$1:$B$107,ROW($B$1:$B$107)-MIN(ROW($A$1:$A$107))+1,""), ROW()-26)),"")} | AE30: {=IFERROR(INDEX($A$1:$A$107,SMALL(IF($O$21=$B$1:$B$107,ROW($B$1:$B$107)-MIN(ROW($A$1:$A$107))+1,""), ROW()-20)),"")} | AF30: {=IFERROR(INDEX($A$1:$A$107,SMALL(IF($O$24=$B$1:$B$107,ROW($B$1:$B$107)-MIN(ROW($A$1:$A$107))+1,""), ROW()-26)),"")} | AG30: {=IFERROR(INDEX($A$1:$A$107,SMALL(IF($O$26=$B$1:$B$107,ROW($B$1:$B$107)-MIN(ROW($A$1:$A$107))+1,""), ROW()-17)),"")} | AH30: {=IFERROR(INDEX($A$1:$A$107,SMALL(IF($O$32=$B$1:$B$107,ROW($B$1:$B$107)-MIN(ROW($A$1:$A$107))+1,""), ROW()-12)),"")} | AI30: {=IFERROR(INDEX($A$1:$A$107,SMALL(IF($O$6=$B$1:$B$107,ROW($B$1:$B$107)-MIN(ROW($A$1:$A$107))+1,""), ROW()-1)),"")} | AJ30: {=IFERROR(INDEX($A$71:$A$100,SMALL(IF($M$6=$B$71:$B$100,ROW($B$71:$B$100)-MIN(ROW($A$71:$A$100))+1,""), ROW()-1)),"")} -> 0 | AR30: 46235
O31: SP | P31: Special Projects | Q31: =COUNTIFS($F$5:$L$34,O31) -> 0 | S31: =LOOKUP(R1,'Deployment needs'!$2:$2,'Deployment needs'!42:42) -> 0.5 | U31: SLA other areas | AA31: {=IFERROR(INDEX($A$1:$A$107,SMALL(IF($O$27=$B$1:$B$107,ROW($B$1:$B$107)-MIN(ROW($A$1:$A$107))+1,""), ROW()-23)),"")} | AC31: {=IFERROR(INDEX($A$1:$A$107,SMALL(IF($O$33=$B$1:$B$107,ROW($B$1:$B$107)-MIN(ROW($A$1:$A$107))+1,""), ROW()-26)),"")} | AE31: {=IFERROR(INDEX($A$1:$A$107,SMALL(IF($O$21=$B$1:$B$107,ROW($B$1:$B$107)-MIN(ROW($A$1:$A$107))+1,""), ROW()-20)),"")} | AF31: {=IFERROR(INDEX($A$1:$A$107,SMALL(IF($O$24=$B$1:$B$107,ROW($B$1:$B$107)-MIN(ROW($A$1:$A$107))+1,""), ROW()-26)),"")} | AG31: {=IFERROR(INDEX($A$1:$A$107,SMALL(IF($O$26=$B$1:$B$107,ROW($B$1:$B$107)-MIN(ROW($A$1:$A$107))+1,""), ROW()-17)),"")} | AH31: {=IFERROR(INDEX($A$1:$A$107,SMALL(IF($O$32=$B$1:$B$107,ROW($B$1:$B$107)-MIN(ROW($A$1:$A$107))+1,""), ROW()-12)),"")} | AI31: {=IFERROR(INDEX($A$1:$A$107,SMALL(IF($O$6=$B$1:$B$107,ROW($B$1:$B$107)-MIN(ROW($A$1:$A$107))+1,""), ROW()-1)),"")} | AJ31: {=IFERROR(INDEX($A$71:$A$100,SMALL(IF($M$6=$B$71:$B$100,ROW($B$71:$B$100)-MIN(ROW($A$71:$A$100))+1,""), ROW()-1)),"")} -> 0 | AR31: 46266
O32: I | P32: Inventory functions | Q32: =COUNTIFS($F$5:$L$34,O32) -> 3 | S32: =LOOKUP(R1,'Deployment needs'!$2:$2,'Deployment needs'!77:77) -> 1 | U32: Area | V32: # folks | W32: UPH | X32: SLA | AA32: Overstock Cycle Count | AB32: ="Overstock Putaway"&" "&T20 -> Overstock Putaway | AC32: {=IFERROR(INDEX($A$1:$A$107,SMALL(IF($O$33=$B$1:$B$107,ROW($B$1:$B$107)-MIN(ROW($A$1:$A$107))+1,""), ROW()-26)),"")} | AE32: {=IFERROR(INDEX($A$1:$A$107,SMALL(IF($O$21=$B$1:$B$107,ROW($B$1:$B$107)-MIN(ROW($A$1:$A$107))+1,""), ROW()-20)),"")} | AF32: {=IFERROR(INDEX($A$1:$A$107,SMALL(IF($O$24=$B$1:$B$107,ROW($B$1:$B$107)-MIN(ROW($A$1:$A$107))+1,""), ROW()-26)),"")} | AG32: {=IFERROR(INDEX($A$1:$A$107,SMALL(IF($O$26=$B$1:$B$107,ROW($B$1:$B$107)-MIN(ROW($A$1:$A$107))+1,""), ROW()-17)),"")} | AH32: {=IFERROR(INDEX($A$1:$A$107,SMALL(IF($O$32=$B$1:$B$107,ROW($B$1:$B$107)-MIN(ROW($A$1:$A$107))+1,""), ROW()-12)),"")} | AI32: {=IFERROR(INDEX($A$1:$A$107,SMALL(IF($O$6=$B$1:$B$107,ROW($B$1:$B$107)-MIN(ROW($A$1:$A$107))+1,""), ROW()-1)),"")} | AJ32: {=IFERROR(INDEX($A$71:$A$100,SMALL(IF($M$6=$B$71:$B$100,ROW($B$71:$B$100)-MIN(ROW($A$71:$A$100))+1,""), ROW()-1)),"")} | AR32: 46296
O33: W | P33: Warehouse Cleaning | Q33: =COUNTIFS($F$5:$L$34,O33) -> 0 | S33: =SUM(S5:S32) -> 19.927428 | U33: Returns Processing | V33: =Q23 -> 1 | W33: =Narvar -> 34 | X33: =(W33*V33*$V$23)/2.45 -> 48.571429 | AA33: {=IFERROR(INDEX($A$1:$A$107,SMALL(IF($O$18=$B$1:$B$107,ROW($B$1:$B$107)-MIN(ROW($A$1:$A$107))+1,""), ROW()-31)),"")} | AB33: {=IFERROR(INDEX($A$1:$A$107,SMALL(IF($O$19=$B$1:$B$107,ROW($B$1:$B$107)-MIN(ROW($A$1:$A$107))+1,""), ROW()-31)),"")} | AC33: {=IFERROR(INDEX($A$1:$A$107,SMALL(IF($O$33=$B$1:$B$107,ROW($B$1:$B$107)-MIN(ROW($A$1:$A$107))+1,""), ROW()-26)),"")} | AE33: {=IFERROR(INDEX($A$1:$A$107,SMALL(IF($O$21=$B$1:$B$107,ROW($B$1:$B$107)-MIN(ROW($A$1:$A$107))+1,""), ROW()-20)),"")} | AF33: {=IFERROR(INDEX($A$1:$A$107,SMALL(IF($O$24=$B$1:$B$107,ROW($B$1:$B$107)-MIN(ROW($A$1:$A$107))+1,""), ROW()-26)),"")} | AG33: {=IFERROR(INDEX($A$1:$A$107,SMALL(IF($O$26=$B$1:$B$107,ROW($B$1:$B$107)-MIN(ROW($A$1:$A$107))+1,""), ROW()-17)),"")} | AH33: {=IFERROR(INDEX($A$1:$A$107,SMALL(IF($O$32=$B$1:$B$107,ROW($B$1:$B$107)-MIN(ROW($A$1:$A$107))+1,""), ROW()-12)),"")} | AI33: {=IFERROR(INDEX($A$1:$A$107,SMALL(IF($O$6=$B$1:$B$107,ROW($B$1:$B$107)-MIN(ROW($A$1:$A$107))+1,""), ROW()-1)),"")} | AJ33: {=IFERROR(INDEX($A$71:$A$100,SMALL(IF($M$6=$B$71:$B$100,ROW($B$71:$B$100)-MIN(ROW($A$71:$A$100))+1,""), ROW()-1)),"")} | AR33: 46327
P34: Total | Q34: =SUM(Q5:Q33) -> 19 | S34: =LOOKUP(R1,'Deployment needs'!2:2,'Deployment needs'!100:100) -> 22.503843 | U34: Returns Exceptions | V34: =Q24 -> 0 | W34: =Exceptions -> 25 | X34: =W34*V34*$V$23 -> 0 | AA34: {=IFERROR(INDEX($A$1:$A$107,SMALL(IF($O$18=$B$1:$B$107,ROW($B$1:$B$107)-MIN(ROW($A$1:$A$107))+1,""), ROW()-31)),"")} | AB34: {=IFERROR(INDEX($A$1:$A$107,SMALL(IF($O$19=$B$1:$B$107,ROW($B$1:$B$107)-MIN(ROW($A$1:$A$107))+1,""), ROW()-31)),"")} | AC34: {=IFERROR(INDEX($A$1:$A$107,SMALL(IF($O$33=$B$1:$B$107,ROW($B$1:$B$107)-MIN(ROW($A$1:$A$107))+1,""), ROW()-26)),"")} | AE34: {=IFERROR(INDEX($A$1:$A$107,SMALL(IF($O$21=$B$1:$B$107,ROW($B$1:$B$107)-MIN(ROW($A$1:$A$107))+1,""), ROW()-20)),"")} | AF34: {=IFERROR(INDEX($A$1:$A$107,SMALL(IF($O$24=$B$1:$B$107,ROW($B$1:$B$107)-MIN(ROW($A$1:$A$107))+1,""), ROW()-26)),"")} | AG34: {=IFERROR(INDEX($A$1:$A$107,SMALL(IF($O$26=$B$1:$B$107,ROW($B$1:$B$107)-MIN(ROW($A$1:$A$107))+1,""), ROW()-17)),"")} | AH34: {=IFERROR(INDEX($A$1:$A$107,SMALL(IF($O$32=$B$1:$B$107,ROW($B$1:$B$107)-MIN(ROW($A$1:$A$107))+1,""), ROW()-12)),"")} | AI34: {=IFERROR(INDEX($A$1:$A$107,SMALL(IF($O$6=$B$1:$B$107,ROW($B$1:$B$107)-MIN(ROW($A$1:$A$107))+1,""), ROW()-1)),"")} | AJ34: {=IFERROR(INDEX($A$71:$A$100,SMALL(IF($M$6=$B$71:$B$100,ROW($B$71:$B$100)-MIN(ROW($A$71:$A$100))+1,""), ROW()-1)),"")} | AR34: 46357
C35: =COUNTIFS(C5:D34,"*") -> 17 | F35: =COUNTIFS(F5:F34,$O$40)+COUNTIFS(F5:F34,$O$41)+COUNTIFS(F5:F34,$O$42)+COUNTIFS(F5:F34,$O$43)+COUNTIFS(F5:F34,$O$44)+COUNTIFS(F5:F34,$O$45)+COUNTIFS(F5:F34,$O$47)+COUNTIFS(F5:F34,$O$58)+COUNTIFS(F5:F34,$O$46) -> 2 | G35: =COUNTIFS(G5:G34,"*") -> 5 | I35: =COUNTIFS(I5:I34,$O$40)+COUNTIFS(I5:I34,$O$41)+COUNTIFS(I5:I34,$O$42)+COUNTIFS(I5:I34,$O$43)+COUNTIFS(I5:I34,$O$44)+COUNTIFS(I5:I34,$O$45)+COUNTIFS(I5:I34,$O$47)+COUNTIFS(I5:I34,$O$58)+COUNTIFS(I5:I34,$O$46) -> 0 | J35: =COUNTIFS(L5:L35,"*") -> 0 | L35: =COUNTIFS(L5:L22,$O$40)+COUNTIFS(L5:L22,$O$41)+COUNTIFS(L5:L22,$O$42)+COUNTIFS(L5:L22,$O$43)+COUNTIFS(L5:L22,$O$44)+COUNTIFS(L5:L22,$O$45)+COUNTIFS(L5:L22,$O$47)+COUNTIFS(L5:L22,$O$58)+COUNTIFS(L5:L22,$O$46) -> 0 | P35: Plan | Q35: =C35+G35+J35 -> 22 | U35: Returns put-away | V35: =Q26 -> 0 | W35: =Returns_put_away -> 100 | X35: =W35*V35*$V$23 -> 0 | AA35: {=IFERROR(INDEX($A$1:$A$107,SMALL(IF($O$18=$B$1:$B$107,ROW($B$1:$B$107)-MIN(ROW($A$1:$A$107))+1,""), ROW()-31)),"")} | AB35: {=IFERROR(INDEX($A$1:$A$107,SMALL(IF($O$19=$B$1:$B$107,ROW($B$1:$B$107)-MIN(ROW($A$1:$A$107))+1,""), ROW()-31)),"")} | AC35: {=IFERROR(INDEX($A$1:$A$107,SMALL(IF($O$33=$B$1:$B$107,ROW($B$1:$B$107)-MIN(ROW($A$1:$A$107))+1,""), ROW()-26)),"")} | AE35: {=IFERROR(INDEX($A$1:$A$107,SMALL(IF($O$21=$B$1:$B$107,ROW($B$1:$B$107)-MIN(ROW($A$1:$A$107))+1,""), ROW()-20)),"")} | AF35: {=IFERROR(INDEX($A$1:$A$107,SMALL(IF($O$24=$B$1:$B$107,ROW($B$1:$B$107)-MIN(ROW($A$1:$A$107))+1,""), ROW()-26)),"")} | AG35: {=IFERROR(INDEX($A$1:$A$107,SMALL(IF($O$26=$B$1:$B$107,ROW($B$1:$B$107)-MIN(ROW($A$1:$A$107))+1,""), ROW()-17)),"")} | AH35: {=IFERROR(INDEX($A$1:$A$107,SMALL(IF($O$32=$B$1:$B$107,ROW($B$1:$B$107)-MIN(ROW($A$1:$A$107))+1,""), ROW()-12)),"")} | AI35: {=IFERROR(INDEX($A$1:$A$107,SMALL(IF($O$6=$B$1:$B$107,ROW($B$1:$B$107)-MIN(ROW($A$1:$A$107))+1,""), ROW()-1)),"")} | AJ35: {=IFERROR(INDEX($A$71:$A$100,SMALL(IF($M$6=$B$71:$B$100,ROW($B$71:$B$100)-MIN(ROW($A$71:$A$100))+1,""), ROW()-1)),"")}
P36: Total Absent | Q36: =SUM(Q39:Q58) -> 2 | U36: Receiving/Cubiscan | V36: =Q27 -> 0 | W36: =Receiving -> 75 | X36: =W36*V36*$V$23 -> 0 | AA36: {=IFERROR(INDEX($A$1:$A$107,SMALL(IF($O$18=$B$1:$B$107,ROW($B$1:$B$107)-MIN(ROW($A$1:$A$107))+1,""), ROW()-31)),"")} | AB36: {=IFERROR(INDEX($A$1:$A$107,SMALL(IF($O$19=$B$1:$B$107,ROW($B$1:$B$107)-MIN(ROW($A$1:$A$107))+1,""), ROW()-31)),"")} | AC36: {=IFERROR(INDEX($A$1:$A$107,SMALL(IF($O$33=$B$1:$B$107,ROW($B$1:$B$107)-MIN(ROW($A$1:$A$107))+1,""), ROW()-26)),"")} | AE36: {=IFERROR(INDEX($A$1:$A$107,SMALL(IF($O$21=$B$1:$B$107,ROW($B$1:$B$107)-MIN(ROW($A$1:$A$107))+1,""), ROW()-20)),"")} | AF36: {=IFERROR(INDEX($A$1:$A$107,SMALL(IF($O$24=$B$1:$B$107,ROW($B$1:$B$107)-MIN(ROW($A$1:$A$107))+1,""), ROW()-26)),"")} | AG36: {=IFERROR(INDEX($A$1:$A$107,SMALL(IF($O$26=$B$1:$B$107,ROW($B$1:$B$107)-MIN(ROW($A$1:$A$107))+1,""), ROW()-17)),"")} | AH36: {=IFERROR(INDEX($A$1:$A$107,SMALL(IF($O$32=$B$1:$B$107,ROW($B$1:$B$107)-MIN(ROW($A$1:$A$107))+1,""), ROW()-12)),"")} | AI36: {=IFERROR(INDEX($A$1:$A$107,SMALL(IF($O$6=$B$1:$B$107,ROW($B$1:$B$107)-MIN(ROW($A$1:$A$107))+1,""), ROW()-1)),"")} | AJ36: {=IFERROR(INDEX($A$71:$A$100,SMALL(IF($M$6=$B$71:$B$100,ROW($B$71:$B$100)-MIN(ROW($A$71:$A$100))+1,""), ROW()-1)),"")}
P37: Attendance % | Q37: =Q34/Q35 -> 0.86363636 | U37: Resets | V37: 1 | W37: =Resets_per_hour -> 20 | X37: =W37*V37*$V$23 -> 70 | AA37: {=IFERROR(INDEX($A$1:$A$107,SMALL(IF($O$18=$B$1:$B$107,ROW($B$1:$B$107)-MIN(ROW($A$1:$A$107))+1,""), ROW()-31)),"")} | AB37: {=IFERROR(INDEX($A$1:$A$107,SMALL(IF($O$19=$B$1:$B$107,ROW($B$1:$B$107)-MIN(ROW($A$1:$A$107))+1,""), ROW()-31)),"")} | AC37: {=IFERROR(INDEX($A$1:$A$107,SMALL(IF($O$33=$B$1:$B$107,ROW($B$1:$B$107)-MIN(ROW($A$1:$A$107))+1,""), ROW()-26)),"")} | AE37: {=IFERROR(INDEX($A$1:$A$107,SMALL(IF($O$21=$B$1:$B$107,ROW($B$1:$B$107)-MIN(ROW($A$1:$A$107))+1,""), ROW()-20)),"")} | AF37: {=IFERROR(INDEX($A$1:$A$107,SMALL(IF($O$24=$B$1:$B$107,ROW($B$1:$B$107)-MIN(ROW($A$1:$A$107))+1,""), ROW()-26)),"")} | AG37: {=IFERROR(INDEX($A$1:$A$107,SMALL(IF($O$26=$B$1:$B$107,ROW($B$1:$B$107)-MIN(ROW($A$1:$A$107))+1,""), ROW()-17)),"")} | AH37: {=IFERROR(INDEX($A$1:$A$107,SMALL(IF($O$32=$B$1:$B$107,ROW($B$1:$B$107)-MIN(ROW($A$1:$A$107))+1,""), ROW()-12)),"")} | AI37: {=IFERROR(INDEX($A$1:$A$107,SMALL(IF($O$6=$B$1:$B$107,ROW($B$1:$B$107)-MIN(ROW($A$1:$A$107))+1,""), ROW()-1)),"")} | AJ37: {=IFERROR(INDEX($A$71:$A$100,SMALL(IF($M$6=$B$71:$B$100,ROW($B$71:$B$100)-MIN(ROW($A$71:$A$100))+1,""), ROW()-1)),"")}
C38: Headcount | D38: =C35+G35 -> 22 | P38: Absent breakdown | AC38: {=IFERROR(INDEX($A$1:$A$107,SMALL(IF($O$33=$B$1:$B$107,ROW($B$1:$B$107)-MIN(ROW($A$1:$A$107))+1,""), ROW()-26)),"")} | AI38: {=IFERROR(INDEX($A$1:$A$107,SMALL(IF($O$6=$B$1:$B$107,ROW($B$1:$B$107)-MIN(ROW($A$1:$A$107))+1,""), ROW()-1)),"")} | AJ38: {=IFERROR(INDEX($A$71:$A$100,SMALL(IF($M$6=$B$71:$B$100,ROW($B$71:$B$100)-MIN(ROW($A$71:$A$100))+1,""), ROW()-1)),"")}
C39: FTE | D39: =COUNTIF(E5:E35,"FT") + COUNTIF(H5:H35,"FT") -> 17 | O39: NC | P39: NC/NS | Q39: =COUNTIFS($F$5:$L$27,O39) -> 0 | U39: Bander | V39: =Q11 -> 6 | W39: =Autobagger_Bander -> 120 | X39: =W39*V39*$V$23 -> 2520 | AA39: {=IFERROR(INDEX($A$1:$A$107,SMALL(IF($O$18=$B$1:$B$107,ROW($B$1:$B$107)-MIN(ROW($A$1:$A$107))+1,""), ROW()-31)),"")} | AB39: {=IFERROR(INDEX($A$1:$A$107,SMALL(IF($O$19=$B$1:$B$107,ROW($B$1:$B$107)-MIN(ROW($A$1:$A$107))+1,""), ROW()-31)),"")} | AC39: {=IFERROR(INDEX($A$1:$A$107,SMALL(IF($O$33=$B$1:$B$107,ROW($B$1:$B$107)-MIN(ROW($A$1:$A$107))+1,""), ROW()-26)),"")} | AE39: {=IFERROR(INDEX($A$1:$A$107,SMALL(IF($O$21=$B$1:$B$107,ROW($B$1:$B$107)-MIN(ROW($A$1:$A$107))+1,""), ROW()-20)),"")} | AF39: {=IFERROR(INDEX($A$1:$A$107,SMALL(IF($O$24=$B$1:$B$107,ROW($B$1:$B$107)-MIN(ROW($A$1:$A$107))+1,""), ROW()-26)),"")} | AG39: {=IFERROR(INDEX($A$1:$A$107,SMALL(IF($O$26=$B$1:$B$107,ROW($B$1:$B$107)-MIN(ROW($A$1:$A$107))+1,""), ROW()-17)),"")} | AH39: {=IFERROR(INDEX($A$1:$A$107,SMALL(IF($O$32=$B$1:$B$107,ROW($B$1:$B$107)-MIN(ROW($A$1:$A$107))+1,""), ROW()-12)),"")} | AI39: {=IFERROR(INDEX($A$1:$A$107,SMALL(IF($O$6=$B$1:$B$107,ROW($B$1:$B$107)-MIN(ROW($A$1:$A$107))+1,""), ROW()-1)),"")} | AJ39: {=IFERROR(INDEX($A$71:$A$100,SMALL(IF($M$6=$B$71:$B$100,ROW($B$71:$B$100)-MIN(ROW($A$71:$A$100))+1,""), ROW()-1)),"")}
C40: GIGS | D40: =J35 -> 0 | L40: . | O40: Call | P40: Call in | Q40: =COUNTIFS($F$5:$L$41,O40) -> 0 | U40: Autobagger | V40: =Q12 -> 2 | W40: =Autobagger_Operator -> 600 | X40: =W40*V40*$V$23 -> 4200 | AI40: {=IFERROR(INDEX($A$1:$A$107,SMALL(IF($O$6=$B$1:$B$107,ROW($B$1:$B$107)-MIN(ROW($A$1:$A$107))+1,""), ROW()-1)),"")} | AJ40: {=IFERROR(INDEX($A$71:$A$100,SMALL(IF($M$6=$B$71:$B$100,ROW($B$71:$B$100)-MIN(ROW($A$71:$A$100))+1,""), ROW()-1)),"")}
O41: VTO | P41: VTO | Q41: =COUNTIFS($F$5:$L$41,O41) -> 0 | U41: Overstock Putaway | V41: =Q19 -> 0 | W41: =Overstock -> 50 | X41: =W41*V41*$V$23 -> 0 | AA41: NCNS | AB41: Call in | AC41: PTO | AD41: FMLA | AE41: VTO | AF41: Leave Early | AG41: Inclement weather | AH41: {=IFERROR(INDEX($A$1:$A$107,SMALL(IF($O$6=$B$1:$B$107,ROW($B$1:$B$107)-MIN(ROW($A$1:$A$107))+1,""), ROW()-1)),"")} | AI41: {=IFERROR(INDEX($A$71:$A$100,SMALL(IF($M$6=$B$71:$B$100,ROW($B$71:$B$100)-MIN(ROW($A$71:$A$100))+1,""), ROW()-1)),"")}
C42: TOTAL FTE | D42: =D50+D39 -> 17 | O42: PTO | P42: PTO | Q42: =COUNTIFS($F$5:$L$41,O42) -> 2 | U42: Replen Pull | V42: =Q20 -> 1 | W42: =Replenishment_pull -> 45 | X42: =W42*V42*$V$23 -> 157.5 | Z42: 1 | AA42: {=_xlfn._xlws.FILTER($A$1:$A$107,$B$1:$B$107=$O$39,"")} | AB42: {=_xlfn._xlws.FILTER($A$1:$A$107, $B$1:$B$107=$O$40, "")} | AC42: {=_xlfn._xlws.FILTER($A$1:$A$107, $B$1:$B$107=$O$42, "")} -> Xiomara Castro Dominquez | AD42: {=_xlfn._xlws.FILTER($A$1:$A$107, $B$1:$B$107=$O$43, "")} | AE42: {=_xlfn._xlws.FILTER($B$1:$B$107, $C$1:$C$107=$O$41, "")} | AF42: {=_xlfn._xlws.FILTER($B$1:$B$107, $C$1:$C$107=$O$44, "")} | AG42: {=_xlfn._xlws.FILTER($B$1:$B$107, $C$1:$C$107=$O$45, "")} | AH42: {=_xlfn._xlws.FILTER($B$1:$B$107, $C$1:$C$107=$O$42, "")} | AI42: {=IFERROR(INDEX($A$71:$A$100,SMALL(IF($M$6=$B$71:$B$100,ROW($B$71:$B$100)-MIN(ROW($A$71:$A$100))+1,""), ROW()-1)),"")}
O43: FMLA | P43: Family medical leave | Q43: =COUNTIFS($F$5:$L$41,O43) -> 0 | U43: Replen Throw | V43: =Q21 -> 1 | W43: =Replenishment_throw -> 35 | X43: =W43*V43*$V$23 -> 122.5 | Z43: 2 | AA43: {=_xlfn._xlws.FILTER($A$1:$A$107,$B$1:$B$107=$O$39,"")} | AC43: Jacqueline Macias | AE43: {=_xlfn._xlws.FILTER($B$1:$B$107, $C$1:$C$107=$O$41, "")} | AF43: {=_xlfn._xlws.FILTER($B$1:$B$107, $C$1:$C$107=$O$44, "")} | AI43: {=IFERROR(INDEX($A$71:$A$100,SMALL(IF($M$6=$B$71:$B$100,ROW($B$71:$B$100)-MIN(ROW($A$71:$A$100))+1,""), ROW()-1)),"")}
O44: LE | P44: Leave early | Q44: =COUNTIFS($F$5:$L$41,O44) -> 0 | Z44: 3 | AA44: {=_xlfn._xlws.FILTER($A$1:$A$107,$B$1:$B$107=$O$39,"")} | AE44: {=_xlfn._xlws.FILTER($B$1:$B$107, $C$1:$C$107=$O$41, "")} | AF44: {=_xlfn._xlws.FILTER($B$1:$B$107, $C$1:$C$107=$O$44, "")} | AI44: {=IFERROR(INDEX($A$71:$A$100,SMALL(IF($M$6=$B$71:$B$100,ROW($B$71:$B$100)-MIN(ROW($A$71:$A$100))+1,""), ROW()-1)),"")}
O45: LA | P45: Late Arrival | Q45: =COUNTIFS($F$5:$L$41,O45) -> 0 | Z45: 4 | AA45: {=_xlfn._xlws.FILTER($A$1:$A$107,$B$1:$B$107=$O$39,"")} | AE45: {=_xlfn._xlws.FILTER($B$1:$B$107, $C$1:$C$107=$O$41, "")} | AF45: {=_xlfn._xlws.FILTER($B$1:$B$107, $C$1:$C$107=$O$44, "")} | AI45: {=IFERROR(INDEX($A$71:$A$100,SMALL(IF($M$6=$B$71:$B$100,ROW($B$71:$B$100)-MIN(ROW($A$71:$A$100))+1,""), ROW()-1)),"")}
O46: Off | P46: Not Schedule to work | Q46: =COUNTIFS($F$5:$L$41,O46) -> 0 | Z46: 5 | AA46: {=_xlfn._xlws.FILTER($A$1:$A$107,$B$1:$B$107=$O$39,"")} | AE46: {=_xlfn._xlws.FILTER($B$1:$B$107, $C$1:$C$107=$O$41, "")} | AF46: {=_xlfn._xlws.FILTER($B$1:$B$107, $C$1:$C$107=$O$44, "")} | AI46: {=IFERROR(INDEX($A$71:$A$100,SMALL(IF($M$6=$B$71:$B$100,ROW($B$71:$B$100)-MIN(ROW($A$71:$A$100))+1,""), ROW()-1)),"")}
O47: WX | P47: Inclement weather | Q47: =COUNTIFS($F$5:$L$41,O47) -> 0 | Z47: 6 | AA47: {=_xlfn._xlws.FILTER($A$1:$A$107,$B$1:$B$107=$O$39,"")} | AE47: {=_xlfn._xlws.FILTER($B$1:$B$107, $C$1:$C$107=$O$41, "")} | AF47: {=_xlfn._xlws.FILTER($B$1:$B$107, $C$1:$C$107=$O$44, "")} | AI47: {=IFERROR(INDEX($A$71:$A$100,SMALL(IF($M$6=$B$71:$B$100,ROW($B$71:$B$100)-MIN(ROW($A$71:$A$100))+1,""), ROW()-1)),"")}
C48: Picking C.C | D48: Names: | G48: Names: | Z48: 7 | AA48: {=_xlfn._xlws.FILTER($A$1:$A$107,$B$1:$B$107=$O$39,"")} | AE48: {=_xlfn._xlws.FILTER($B$1:$B$107, $C$1:$C$107=$O$41, "")} | AF48: {=_xlfn._xlws.FILTER($B$1:$B$107, $C$1:$C$107=$O$44, "")} | AH48: {=IFERROR(INDEX($A$1:$A$107,SMALL(IF($O$6=$B$1:$B$107,ROW($B$1:$B$107)-MIN(ROW($A$1:$A$107))+1,""), ROW()-1)),"")} | AI48: {=IFERROR(INDEX($A$71:$A$100,SMALL(IF($M$6=$B$71:$B$100,ROW($B$71:$B$100)-MIN(ROW($A$71:$A$100))+1,""), ROW()-1)),"")}
C49: Zone 1 | Z49: 8 | AA49: {=_xlfn._xlws.FILTER($A$1:$A$107,$B$1:$B$107=$O$39,"")} | AE49: {=_xlfn._xlws.FILTER($B$1:$B$107, $C$1:$C$107=$O$41, "")} | AF49: {=_xlfn._xlws.FILTER($B$1:$B$107, $C$1:$C$107=$O$44, "")} | AH49: {=IFERROR(INDEX($A$1:$A$107,SMALL(IF($O$6=$B$1:$B$107,ROW($B$1:$B$107)-MIN(ROW($A$1:$A$107))+1,""), ROW()-1)),"")}
C50: Zone 2 | Z50: 9 | AA50: {=_xlfn._xlws.FILTER($A$1:$A$107,$B$1:$B$107=$O$39,"")} | AE50: {=_xlfn._xlws.FILTER($B$1:$B$107, $C$1:$C$107=$O$41, "")} | AF50: {=_xlfn._xlws.FILTER($B$1:$B$107, $C$1:$C$107=$O$44, "")} | AH50: {=IFERROR(INDEX($A$1:$A$107,SMALL(IF($O$6=$B$1:$B$107,ROW($B$1:$B$107)-MIN(ROW($A$1:$A$107))+1,""), ROW()-1)),"")} | AI50: {=IFERROR(INDEX($A$71:$A$100,SMALL(IF($M$6=$B$71:$B$100,ROW($B$71:$B$100)-MIN(ROW($A$71:$A$100))+1,""), ROW()-1)),"")}
C51: Zone 3 | Z51: 10 | AA51: {=_xlfn._xlws.FILTER($A$1:$A$107,$B$1:$B$107=$O$39,"")} | AE51: {=_xlfn._xlws.FILTER($B$1:$B$107, $C$1:$C$107=$O$41, "")} | AF51: {=_xlfn._xlws.FILTER($B$1:$B$107, $C$1:$C$107=$O$44, "")} | AH51: {=IFERROR(INDEX($A$1:$A$107,SMALL(IF($O$6=$B$1:$B$107,ROW($B$1:$B$107)-MIN(ROW($A$1:$A$107))+1,""), ROW()-1)),"")} | AI51: {=IFERROR(INDEX($A$71:$A$100,SMALL(IF($M$6=$B$71:$B$100,ROW($B$71:$B$100)-MIN(ROW($A$71:$A$100))+1,""), ROW()-1)),"")}
C52: Zone 4 | AA52: Late Arrival | AE52: {=_xlfn._xlws.FILTER($B$1:$B$107, $C$1:$C$107=$O$41, "")} | AF52: {=_xlfn._xlws.FILTER($B$1:$B$107, $C$1:$C$107=$O$44, "")} | AH52: {=IFERROR(INDEX($A$1:$A$107,SMALL(IF($O$6=$B$1:$B$107,ROW($B$1:$B$107)-MIN(ROW($A$1:$A$107))+1,""), ROW()-1)),"")} | AI52: {=IFERROR(INDEX($A$71:$A$100,SMALL(IF($M$6=$B$71:$B$100,ROW($B$71:$B$100)-MIN(ROW($A$71:$A$100))+1,""), ROW()-1)),"")}
C53: Zone 5 | Z53: 1 | AA53: {=_xlfn._xlws.FILTER($A$1:$A$107,$B$1:$B$107=$O$45,"")} | AE53: {=_xlfn._xlws.FILTER($B$1:$B$107, $C$1:$C$107=$O$41, "")} | AF53: {=_xlfn._xlws.FILTER($B$1:$B$107, $C$1:$C$107=$O$44, "")} | AH53: {=IFERROR(INDEX($A$1:$A$107,SMALL(IF($O$6=$B$1:$B$107,ROW($B$1:$B$107)-MIN(ROW($A$1:$A$107))+1,""), ROW()-1)),"")} | AI53: {=IFERROR(INDEX($A$71:$A$100,SMALL(IF($M$6=$B$71:$B$100,ROW($B$71:$B$100)-MIN(ROW($A$71:$A$100))+1,""), ROW()-1)),"")}
C54: Zone 6 | Z54: 2 | AA54: {=_xlfn._xlws.FILTER($A$1:$A$107,$B$1:$B$107=$O$45,"")} | AE54: {=_xlfn._xlws.FILTER($B$1:$B$107, $C$1:$C$107=$O$41, "")} | AF54: {=_xlfn._xlws.FILTER($B$1:$B$107, $C$1:$C$107=$O$44, "")} | AH54: {=IFERROR(INDEX($A$1:$A$107,SMALL(IF($O$6=$B$1:$B$107,ROW($B$1:$B$107)-MIN(ROW($A$1:$A$107))+1,""), ROW()-1)),"")} | AI54: {=IFERROR(INDEX($A$71:$A$100,SMALL(IF($M$6=$B$71:$B$100,ROW($B$71:$B$100)-MIN(ROW($A$71:$A$100))+1,""), ROW()-1)),"")}
C55: Zone 7 | P55: Box cutters | Q55: Names: | Z55: 3 | AA55: {=_xlfn._xlws.FILTER($A$1:$A$107,$B$1:$B$107=$O$45,"")} | AE55: {=_xlfn._xlws.FILTER($B$1:$B$107, $C$1:$C$107=$O$41, "")} | AF55: {=_xlfn._xlws.FILTER($B$1:$B$107, $C$1:$C$107=$O$44, "")} | AH55: {=IFERROR(INDEX($A$1:$A$107,SMALL(IF($O$6=$B$1:$B$107,ROW($B$1:$B$107)-MIN(ROW($A$1:$A$107))+1,""), ROW()-1)),"")} | AI55: {=IFERROR(INDEX($A$71:$A$100,SMALL(IF($M$6=$B$71:$B$100,ROW($B$71:$B$100)-MIN(ROW($A$71:$A$100))+1,""), ROW()-1)),"")}
C56: Zone 8 | P56: Knife1 | Z56: 4 | AA56: {=_xlfn._xlws.FILTER($A$1:$A$107,$B$1:$B$107=$O$45,"")} | AE56: {=_xlfn._xlws.FILTER($B$1:$B$107, $C$1:$C$107=$O$41, "")} | AF56: {=_xlfn._xlws.FILTER($B$1:$B$107, $C$1:$C$107=$O$44, "")} | AH56: {=IFERROR(INDEX($A$1:$A$107,SMALL(IF($O$6=$B$1:$B$107,ROW($B$1:$B$107)-MIN(ROW($A$1:$A$107))+1,""), ROW()-1)),"")} | AI56: {=IFERROR(INDEX($A$71:$A$100,SMALL(IF($M$6=$B$71:$B$100,ROW($B$71:$B$100)-MIN(ROW($A$71:$A$100))+1,""), ROW()-1)),"")}
C57: Zone 9 | P57: Knife2 | Z57: 5 | AA57: {=_xlfn._xlws.FILTER($A$1:$A$107,$B$1:$B$107=$O$45,"")} | AE57: {=_xlfn._xlws.FILTER($B$1:$B$107, $C$1:$C$107=$O$41, "")} | AF57: {=_xlfn._xlws.FILTER($B$1:$B$107, $C$1:$C$107=$O$44, "")} | AH57: {=IFERROR(INDEX($A$1:$A$107,SMALL(IF($O$6=$B$1:$B$107,ROW($B$1:$B$107)-MIN(ROW($A$1:$A$107))+1,""), ROW()-1)),"")} | AI57: {=IFERROR(INDEX($A$71:$A$100,SMALL(IF($M$6=$B$71:$B$100,ROW($B$71:$B$100)-MIN(ROW($A$71:$A$100))+1,""), ROW()-1)),"")}
